Workbook

Sheet Avance
A1: Avance de fichas y fotos para Mercado Libre
A2: Completo = ficha verificada en internet y al menos una foto. Texto azul: dato de entrada.
A4: Productos a publicar | B4: =COUNTA(Revisión!$A$2:$A$1150) -> 1149
A5: Con ficha verificada | B5: =COUNTIF(Revisión!$C$2:$C$1150,"Verificado") -> 1149
A6: Con al menos una foto | B6: =COUNTIF(Revisión!$N$2:$N$1150,">0") -> 1149
A7: Completos (ficha verificada y fotos) | B7: =COUNTIFS(Revisión!$C$2:$C$1150,"Verificado",Revisión!$N$2:$N$1150,">0") -> 1149
A8: Verificados sin fotos | B8: =B5-B7 -> 0
A9: Sin verificar (datos deducidos del nombre) | B9: =COUNTIF(Revisión!$C$2:$C$1150,"Sin verificar") -> 0
A10: Pendientes de investigar | B10: =COUNTIF(Revisión!$C$2:$C$1150,"Pendiente de investigar") -> 0
A11: Por investigar (sin verificar + pendientes) | B11: =B9+B10 -> 0
A12: Avance (completos / total) | B12: =IF(B4=0,0,B7/B4) -> 1
A13: Descartados de Mercado Libre (fuera del layout; hoja Descartados) | B13: =COUNTA(Descartados!$A$2:$A$5000) -> 14
A14: Productos por sesión | B14: 200 | C14: Límite de búsquedas web por sesión: 200 (1 búsqueda por producto)
A15: Sesiones realizadas | B15: 8
A16: Sesiones que faltan | B16: =ROUNDUP(B11/B14,0) -> 0
A17: Total de sesiones estimadas | B17: =B15+B16 -> 8
A19: Historial de sesiones
A20: Sesión | B20: Fecha | C20: Productos investigados | D20: Fichas verificadas | E20: Productos con fotos nuevas
A21: 1 | B21: 2026-09-29 | C21: 425 | D21: 122 | E21: 0
A22: 2 | B22: 2026-09-29 | C22: 199 | D22: 196 | E22: 315
A23: 3 | B23: 2026-09-29 | C23: 200 | D23: 194 | E23: 188
A24: 4 | B24: 2026-09-29 | C24: 200 | D24: 195 | E24: 190
A25: 5 | B25: 2026-09-29 | C25: 200 | D25: 191 | E25: 187
A26: 6 | B26: 2026-09-29 | C26: 200 | D26: 189 | E26: 181
A27: 7 | B27: 2026-09-29 | C27: 76 | D27: 68 | E27: 116
A28: 8 | B28: 2026-09-29 | C28: 0 | D28: 0 | E28: 11

Sheet Layout Mercado Libre
A1: SKU | B1: Código universal de producto | C1: Título | D1: Categoría (ID) | E1: Categoría (ruta) | F1: Precio [$] | G1: Cantidad | H1: Condición | I1: Tipo de publicación | J1: Descripción | K1: Forma de envío | L1: Costo de envío | M1: Retiro en persona | N1: Tipo de garantía | O1: ID de catálogo ML | P1: Marca | Q1: Fabricante / Laboratorio | R1: Línea | S1: Variante / Modelo | T1: Presentación | U1: Contenido neto | V1: Unidad de contenido | W1: Unidades por envase | X1: Principio activo | Y1: Concentración | Z1: Vía de administración | AA1: Edad / Etapa | AB1: Talla | AC1: Sabor / Aroma | AD1: Género | AE1: Tipo de piel / cabello | AF1: Registro sanitario | AG1: Otros atributos | AH1: Imagen 1 | AI1: Imagen 2 | AJ1: Imagen 3 | AK1: Imagen 4 | AL1: Imagen 5 | AM1: Imagen 6 | AN1: Línea de origen | AO1: Nombre en sistema | AP1: Estado de investigación
A2: 7501123013302 | B2: 7501123013302 | C2: Bedoyecta Tri Solución Inyectable 5 Jeringas 2 ml | D2: MLM457812 | E2: Salud y Equipamiento Médico > Cuidado de la Salud > Farmacia > Medicamentos de Venta Libre > Sistema Nervioso Venta Libre | F2: =Precios!R2 -> 419 | G2: 3099 | H2: =Parámetros!$B$28 -> Nuevo | I2: =Parámetros!$B$29 -> Clásica | J2: Descripción: Bedoyecta Tri es una solución inyectable de Laboratorios Grossman que combina tres vitaminas: hidroxocobalamina (vitamina B12), tiamina (vitamina B1) y piridoxina (vitamina B6). Se presenta en jeringas prellenadas de vidrio de 2 ml, listas para su aplicación intramuscular por personal de salud. Beneficios: - Aporta en una sola aplicación vitamina B12, B1 y B6. - Según su ficha, se utiliza en el tratamiento de deficiencias de vitaminas del complejo B. - Se emplea como apoyo en neuropatías nutricionales, diabéticas y alcohólicas, así como en ciática y otras neuropatías periféricas. - También se indica en anemia megaloblástica por deficiencia de vitamina B12. - Jeringa prellenada lista para usar. Composición: Cada jeringa de 2 ml contiene: - Hidroxocobalamina 10,000 mcg - Tiamina (clorhidrato) 100 mg - Piridoxina (clorhidrato) 50 mg Vehículo cbp 2 ml. Contiene alcohol bencílico como conservador. Modo de uso: Aplicación intramuscular profunda por personal de salud. La dosis media indicada en su ficha es de una a dos jeringas por semana según la gravedad del cuadro, o una aplicación cada 2 a 4 semanas en deficiencias crónicas de vitamina B12. La dosis y la duración del tratamiento deben ser determinadas por el médico. Presentación: Caja con 5 jeringas prellenadas de vidrio de 2 ml y 5 agujas desechables. Advertencias: No debe usarse en caso de hipersensibilidad a los componentes, policitemia vera, embarazo ni en recién nacidos. Puede causar erupción cutánea, náusea, vómito, neuropatía periférica y, en personas sensibles, reacciones alérgicas graves. Un exceso de vitamina B6 puede provocar neuropatía periférica; informe a su médico si consume otros multivitamínicos o suplementos. Conservar en lugar fresco. Lea las instrucciones del empaque. Consulte a su médico. No se deje al alcance de los niños. | K2: =Parámetros!$B$30 -> Mercado Envíos | L2: =IF(F2>=Parámetros!$B$7,"Envío gratis (obligatorio en Mercado Libre)",Parámetros!$B$31) -> Envío gratis (obligatorio en Mercado Libre) | M2: =Parámetros!$B$32 -> No acepto | N2: =Parámetros!$B$33 -> Sin garantía | O2: MLM40655899 | P2: Bedoyecta | Q2: Laboratorios Grossman | R2: Tri | S2: Solución inyectable 10,000 mcg/100 mg/50 mg | T2: Solución inyectable en jeringa prellenada | U2: 2 | V2: ml | W2: 5 | X2: Hidroxocobalamina, tiamina y piridoxina | Y2: 10,000 mcg/100 mg/50 mg por 2 ml | Z2: Intramuscular | AA2: Adultos | AF2: 84847 SSA IV | AG2: Incluye agujas desechables: 5; Formato de venta: Caja | AH2: https://raw.githubusercontent.com/zublimemx/marketplaces-product-images/main/products/7501123013302/images/7501123013302_1.jpg | AI2: https://raw.githubusercontent.com/zublimemx/marketplaces-product-images/main/products/7501123013302/images/7501123013302_2.jpg | AJ2: https://raw.githubusercontent.com/zublimemx/marketplaces-product-images/main/products/7501123013302/images/7501123013302_3.jpg | AN2: Farma | AO2: BEDOYECTA TRI AMP | AP2: Verificado
A3: 7501058623300 | B3: 7501058623300 | C3: Fórmula Infantil Nan Optipro 2 Lata 800 g | D3: MLM189058 | E3: Bebés > Comida para Bebés > Leche para Bebés | F3: =Precios!R3 -> 391 | G3: 1814 | H3: =Parámetros!$B$28 -> Nuevo | I3: =Parámetros!$B$29 -> Clásica | J3: Descripción: NAN Optipro 2 (presentada por Nestlé México como NAN 2 Optimal Pro) es una fórmula infantil en polvo para lactantes de 6 a 12 meses. Está elaborada con proteína de suero de leche OPTIPRO y enriquecida con HMO 2'FL, DHA, el probiótico Limosilactobacillus reuteri y hierro. Beneficios: - Contiene proteína de suero de leche desmineralizado OPTIPRO. - Incluye el oligosacárido de leche humana HMO 2'FL (2'-fucosilactosa) y DHA de aceite de pescado. - Contiene el probiótico Limosilactobacillus reuteri. - Fórmula adicionada con hierro, zinc, vitaminas A, C, D, E, K y del complejo B, y otros minerales. - Aporte por cada 100 kcal: 2 g de proteína, 4.8 g de grasa total y 12.2 g de carbohidratos. Ingredientes: Proteína de suero de leche de vaca desmineralizado OPTIPRO (26.84 %), lactosa, leche descremada, aceites vegetales (oleína de palma, palmiste, canola y maíz), citrato tricálcico, lecitina de soya, sales minerales, HMO (0.22 %) [2'-fucosilactosa], aceite de pescado (0.15 %) [DHA], cultivos probióticos de Limosilactobacillus reuteri (0.03 %), vitaminas y minerales. Contiene: leche, soya y aceite de pescado. Modo de uso: Indicada para lactantes de 6 a 12 meses. Prepárese siguiendo estrictamente las instrucciones de preparación y conservación de la etiqueta, con agua segura y utensilios limpios. Presentación: Lata con 800 g de fórmula en polvo. Advertencias: La leche materna es el mejor alimento para el bebé y debe continuarse el mayor tiempo posible. El uso de este producto debe hacerse bajo la orientación de un profesional de la salud. Contiene leche, soya y aceite de pescado. Una preparación o un almacenamiento incorrectos pueden ser perjudiciales para la salud del bebé. | K3: =Parámetros!$B$30 -> Mercado Envíos | L3: =IF(F3>=Parámetros!$B$7,"Envío gratis (obligatorio en Mercado Libre)",Parámetros!$B$31) -> Envío gratis (obligatorio en Mercado Libre) | M3: =Parámetros!$B$32 -> No acepto | N3: =Parámetros!$B$33 -> Sin garantía | P3: Nan | Q3: Nestlé | R3: Optipro | S3: Etapa 2 | T3: Lata en polvo | U3: 800 | V3: g | W3: 1 | AA3: 6 a 12 meses | AC3: Sin sabor | AD3: Unisex | AG3: Etapa: 2; Con HMO: Sí; Con DHA: Sí; Con probióticos: Sí; Con hierro: Sí; Formato de venta: Unidad; Nombre en empaque actual: Optimal Pro | AH3: https://raw.githubusercontent.com/zublimemx/marketplaces-product-images/main/products/7501058623300/images/7501058623300_1.jpg | AI3: https://raw.githubusercontent.com/zublimemx/marketplaces-product-images/main/products/7501058623300/images/7501058623300_2.jpg | AJ3: https://raw.githubusercontent.com/zublimemx/marketplaces-product-images/main/products/7501058623300/images/7501058623300_3.jpg | AN3: Farma + Mark | AO3: NAN 2 800GR | AP3: Verificado
A4: 7501058623317 | B4: 7501058623317 | C4: Fórmula Infantil Nan Optipro 1 Lata 800 g | D4: MLM189058 | E4: Bebés > Comida para Bebés > Leche para Bebés | F4: =Precios!R4 -> 406 | G4: 2350 | H4: =Parámetros!$B$28 -> Nuevo | I4: =Parámetros!$B$29 -> Clásica | J4: Descripción: NAN Optipro 1 (presentada por Nestlé México como NAN 1 Optimal Pro) es una fórmula infantil de inicio en polvo para bebés de 0 a 6 meses. Está elaborada con proteína de suero de leche OPTIPRO y enriquecida con HMO 2'FL, DHA y ARA, el probiótico Limosilactobacillus reuteri y hierro. Beneficios: - Contiene proteína OPTIPRO, DHA y ARA (ácidos grasos omega 3 y omega 6). - Incluye el oligosacárido de leche humana HMO 2'FL (2'-fucosilactosa). - Contiene el probiótico Limosilactobacillus reuteri. - Fórmula adicionada con hierro, vitaminas y minerales. - Aporte por cada 100 kcal: 1.85 g de proteína, 5.26 g de grasa total y 11.29 g de carbohidratos. Ingredientes: Proteína de suero de leche de vaca desmineralizado OPTIPRO (43.87 %), aceites vegetales (oleína de palma, palmiste, canola, maíz y girasol alto oleico), lactosa, minerales, vitaminas, cultivos probióticos de Limosilactobacillus reuteri, HMO (2'-fucosilactosa), DHA y ARA. Contiene: leche, soya y aceite de pescado. Modo de uso: Indicada para bebés de 0 a 6 meses. Prepárese siguiendo estrictamente las instrucciones de preparación y conservación de la etiqueta, con agua segura y utensilios limpios. Presentación: Lata con 800 g de fórmula en polvo. Advertencias: La leche materna es el mejor alimento para el bebé y debe continuarse el mayor tiempo posible. El uso de este producto debe hacerse bajo la orientación de un profesional de la salud. Contiene leche, soya y aceite de pescado. Una preparación o un almacenamiento incorrectos pueden ser perjudiciales para la salud del bebé. | K4: =Parámetros!$B$30 -> Mercado Envíos | L4: =IF(F4>=Parámetros!$B$7,"Envío gratis (obligatorio en Mercado Libre)",Parámetros!$B$31) -> Envío gratis (obligatorio en Mercado Libre) | M4: =Parámetros!$B$32 -> No acepto | N4: =Parámetros!$B$33 -> Sin garantía | O4: MLM28528415 | P4: Nan | Q4: Nestlé | R4: Optipro | S4: Etapa 1 | T4: Lata en polvo | U4: 800 | V4: g | W4: 1 | AA4: 0 a 6 meses | AC4: Sin sabor | AD4: Unisex | AG4: Etapa: 1; Con HMO: Sí; Con DHA: Sí; Con probióticos: Sí; Con hierro: Sí; Formato de venta: Unidad; Nombre en empaque actual: Optimal Pro | AH4: https://raw.githubusercontent.com/zublimemx/marketplaces-product-images/main/products/7501058623317/images/7501058623317_1.jpg | AI4: https://raw.githubusercontent.com/zublimemx/marketplaces-product-images/main/products/7501058623317/images/7501058623317_2.jpg | AJ4: https://raw.githubusercontent.com/zublimemx/marketplaces-product-images/main/products/7501058623317/images/7501058623317_3.jpg | AK4: https://raw.githubusercontent.com/zublimemx/marketplaces-product-images/main/products/7501058623317/images/7501058623317_4.jpg | AN4: Farma + Mark | AO4: NAN 1 800GR OPTIPRO | AP4: Verificado
A5: 7501318612655 | B5: 7501318612655 | C5: Aspirina Protect 100 mg 28 Tabletas | D5: MLM457820 | E5: Salud y Equipamiento Médico > Cuidado de la Salud > Farmacia > Medicamentos de Venta Libre > Para la Sangre Venta Libre | F5: =Precios!R5 -> 261 | G5: 12409 | H5: =Parámetros!$B$28 -> Nuevo | I5: =Parámetros!$B$29 -> Clásica | J5: Descripción: Aspirina Protect 100 mg es un medicamento de Bayer en tabletas de liberación retardada (gastrorresistentes), con 100 mg de ácido acetilsalicílico por tableta. Su cubierta está diseñada para resistir el ácido del estómago, por lo que la tableta se libera más adelante en el tubo digestivo. Beneficios: - Actúa sobre la agregación de las plaquetas y ayuda a prevenir la formación de coágulos de sangre. - Según su ficha, se utiliza para reducir el riesgo de mortalidad y morbilidad en el infarto agudo de miocardio y en la prevención secundaria de infarto y de evento vascular cerebral. - También se indica en ataque isquémico transitorio, angina de pecho e inestable y en la prevención de tromboembolia después de procedimientos vasculares. - Presentación de dosis baja (100 mg) para uso cardiovascular bajo indicación médica. Composición: Cada tableta contiene ácido acetilsalicílico 100 mg, con excipientes cbp. Modo de uso: Vía oral. Las tabletas gastrorresistentes se toman antes de los alimentos, con abundante líquido. La dosis y la duración del tratamiento dependen de la condición a tratar y deben ser indicadas por el médico. Presentación: Caja con 28 tabletas de liberación retardada de 100 mg. Advertencias: No debe usarse en caso de hipersensibilidad al ácido acetilsalicílico o a los salicilatos, asma inducida por salicilatos, úlcera gastroduodenal activa, trastornos hemorrágicos, insuficiencia renal, hepática o cardíaca graves, uso con metotrexato a dosis de 15 mg por semana o más, ni durante el tercer trimestre del embarazo. Puede aumentar el riesgo de sangrado y de lesiones gastrointestinales; tenga precaución si toma anticoagulantes. No se administre a niños o adolescentes con infecciones virales por el riesgo de síndrome de Reye. Lea las instrucciones del empaque. Consulte a su médico. No se deje al alcance de los niños. | K5: =Parámetros!$B$30 -> Mercado Envíos | L5: =IF(F5>=Parámetros!$B$7,"Envío gratis (obligatorio en Mercado Libre)",Parámetros!$B$31) -> A cargo del comprador | M5: =Parámetros!$B$32 -> No acepto | N5: =Parámetros!$B$33 -> Sin garantía | O5: MLM39473264 | P5: Aspirina | Q5: Bayer | R5: Protect | S5: 100 mg liberación retardada | T5: Tabletas de liberación retardada | U5: 28 | V5: tabletas | W5: 28 | X5: Ácido acetilsalicílico | Y5: 100 mg | Z5: Oral | AA5: Adultos | AG5: Formato de venta: Caja; Liberación: Retardada | AH5: https://raw.githubusercontent.com/zublimemx/marketplaces-product-images/main/products/7501318612655/images/7501318612655_2.jpg | AI5: https://raw.githubusercontent.com/zublimemx/marketplaces-product-images/main/products/7501318612655/images/7501318612655_4.jpg | AJ5: https://raw.githubusercontent.com/zublimemx/marketplaces-product-images/main/products/7501318612655/images/7501318612655_5.jpg | AN5: Farma | AO5: ASPIRINA PROTEC C 28 TABS 240 | AP5: Verificado
A6: 7501034692184 | B6: 7501034692184 | C6: Jardianz DPP 25 mg/5 mg 30 Tabletas | D6: MLM457821 | E6: Salud y Equipamiento Médico > Cuidado de la Salud > Farmacia > Medicamentos de Venta Libre > Digestivos Venta Libre | F6: =Precios!R6 -> 3069 | G6: 10 | H6: =Parámetros!$B$28 -> Nuevo | I6: =Parámetros!$B$29 -> Clásica | J6: Descripción: Jardianz DPP 25 mg/5 mg es un medicamento de Boehringer Ingelheim que combina en una sola tableta dos antidiabéticos orales: empagliflozina (inhibidor del cotransportador sodio-glucosa 2, SGLT2) y linagliptina (inhibidor de la enzima DPP-4). Beneficios: - Indicado en adultos con diabetes mellitus tipo 2 como complemento de la dieta y el ejercicio para el control de la glucosa en sangre. - Se utiliza cuando el control con metformina o sulfonilureas más uno de los componentes no es suficiente, o en pacientes que ya reciben ambos principios activos por separado. - Dos mecanismos de acción complementarios en una sola tableta. Composición: Cada tableta contiene empagliflozina 25 mg y linagliptina 5 mg. Modo de uso: Vía oral. La tableta se traga entera con agua, con o sin alimentos, aproximadamente a la misma hora cada día. La dosis y los ajustes (por ejemplo, según la función renal) deben ser determinados por el médico. Presentación: Caja con 30 tabletas. Advertencias: No debe usarse en diabetes tipo 1, enfermedad renal terminal o diálisis, ni en caso de hipersensibilidad a sus componentes. Existe riesgo de cetoacidosis diabética (suspender el tratamiento si se sospecha), infecciones urinarias y genitales y pancreatitis, y mayor riesgo de hipoglucemia si se usa con sulfonilureas o insulina. Se recomienda vigilar la función renal. Evite su uso durante el embarazo y la lactancia. No se recomienda en insuficiencia hepática grave. Lea las instrucciones del empaque. Consulte a su médico. No se deje al alcance de los niños. | K6: =Parámetros!$B$30 -> Mercado Envíos | L6: =IF(F6>=Parámetros!$B$7,"Envío gratis (obligatorio en Mercado Libre)",Parámetros!$B$31) -> Envío gratis (obligatorio en Mercado Libre) | M6: =Parámetros!$B$32 -> No acepto | N6: =Parámetros!$B$33 -> Sin garantía | O6: MLM40172306 | P6: Jardianz | Q6: Boehringer Ingelheim | R6: DPP | S6: 25 mg/5 mg | T6: Tabletas | U6: 30 | V6: tabletas | W6: 30 | X6: Empagliflozina y linagliptina | Y6: 25 mg/5 mg | Z6: Oral | AA6: Adultos | AF6: 512M2016 SSA IV | AG6: Formato de venta: Caja | AH6: https://raw.githubusercontent.com/zublimemx/marketplaces-product-images/main/products/7501034692184/images/7501034692184_1.jpg | AI6: https://raw.githubusercontent.com/zublimemx/marketplaces-product-images/main/products/7501034692184/images/7501034692184_2.jpg | AJ6: https://raw.githubusercontent.com/zublimemx/marketplaces-product-images/main/products/7501034692184/images/7501034692184_3.jpg | AN6: Farma | AO6: JARDIANZ DPP 25 5MG C30 | AP6: Verificado
A7: 7501943441804 | B7: 7501943441804 | C7: Pañales Huggies Supreme Unisex Etapa 5 36 Piezas | D7: MLM178488 | E7: Bebés > Higiene y Cuidado del Bebé > Pañales > Desechables | F7: =Precios!R7 -> 698 | G7: 281 | H7: =Parámetros!$B$28 -> Nuevo | I7: =Parámetros!$B$29 -> Clásica | J7: Descripción: Los pañales Huggies Supreme Etapa 5, de Kimberly-Clark, están diseñados para proteger la delicada piel del bebé con materiales de superior suavidad. Es la línea Huggies que se presenta como única clínica y dermatológicamente probada, con certificación Dermatest de cinco estrellas. Versión unisex para bebés de 11 a 14.5 kg. Características: - Clínica y dermatológicamente probados, con certificación Dermatest de 5 estrellas. - Materiales de superior suavidad que ayudan a evitar la irritación. - Manejo de la humedad que ayuda a mantener la piel fresca y sana. - Cintas ajustables para un ajuste cómodo y seguro que permite libertad de movimiento. - Diseños exclusivos en los pañales. - Unisex: para niños y niñas. Modo de uso: Abra el pañal y colóquelo debajo del bebé, lleve la parte delantera hacia arriba y sujete las cintas a la altura de la cintura, sin apretar en exceso. Cámbielo con frecuencia, en cuanto esté húmedo o sucio. Presentación: Paquete con 36 pañales desechables Etapa 5. Advertencias: Deseche el pañal usado en la basura, no en el inodoro. Mantenga el empaque plástico fuera del alcance de los niños. Verifique que la etapa corresponda al peso de su bebé. | K7: =Parámetros!$B$30 -> Mercado Envíos | L7: =IF(F7>=Parámetros!$B$7,"Envío gratis (obligatorio en Mercado Libre)",Parámetros!$B$31) -> Envío gratis (obligatorio en Mercado Libre) | M7: =Parámetros!$B$32 -> No acepto | N7: =Parámetros!$B$33 -> Sin garantía | O7: MLM17379809 | P7: Huggies | Q7: Kimberly-Clark de México | R7: Supreme | S7: Etapa 5 | T7: Pañales desechables | U7: 36 | V7: piezas | W7: 36 | AA7: Etapa 5 | AB7: Etapa 5 | AD7: Unisex | AG7: Peso del bebé: 11 a 14.5 kg; Dermatest 5 estrellas: Sí; Formato de venta: Paquete | AH7: https://raw.githubusercontent.com/zublimemx/marketplaces-product-images/main/products/7501943441804/images/7501943441804_1.jpg | AI7: https://raw.githubusercontent.com/zublimemx/marketplaces-product-images/main/products/7501943441804/images/7501943441804_3.jpg | AN7: Mark | AO7: HU SUP UNISEX E5 C/36 | AP7: Verificado
A8: 7501943445796 | B8: 7501943445796 | C8: Pañales Huggies Supreme Unisex Etapa 6 36 Piezas | D8: MLM178488 | E8: Bebés > Higiene y Cuidado del Bebé > Pañales > Desechables | F8: =Precios!R8 -> 529 | G8: 510 | H8: =Parámetros!$B$28 -> Nuevo | I8: =Parámetros!$B$29 -> Clásica | J8: Descripción: Los pañales Huggies Supreme Etapa 6, de Kimberly-Clark, están diseñados para proteger la delicada piel del bebé con materiales de superior suavidad. Es la línea Huggies que se presenta como única clínica y dermatológicamente probada, con certificación Dermatest de cinco estrellas. Versión unisex para bebés de más de 13.5 kg. Características: - Clínica y dermatológicamente probados, con certificación Dermatest de 5 estrellas. - Materiales de superior suavidad que ayudan a evitar la irritación. - Manejo de la humedad que ayuda a mantener la piel fresca y sana. - Cintas ajustables para un ajuste cómodo y seguro que permite libertad de movimiento. - Diseños exclusivos en los pañales. - Unisex: para niños y niñas. Modo de uso: Abra el pañal y colóquelo debajo del bebé, lleve la parte delantera hacia arriba y sujete las cintas a la altura de la cintura, sin apretar en exceso. Cámbielo con frecuencia, en cuanto esté húmedo o sucio. Presentación: Paquete con 36 pañales desechables Etapa 6. Advertencias: Deseche el pañal usado en la basura, no en el inodoro. Mantenga el empaque plástico fuera del alcance de los niños. Verifique que la etapa corresponda al peso de su bebé. | K8: =Parámetros!$B$30 -> Mercado Envíos | L8: =IF(F8>=Parámetros!$B$7,"Envío gratis (obligatorio en Mercado Libre)",Parámetros!$B$31) -> Envío gratis (obligatorio en Mercado Libre) | M8: =Parámetros!$B$32 -> No acepto | N8: =Parámetros!$B$33 -> Sin garantía | O8: MLM17379842 | P8: Huggies | Q8: Kimberly-Clark de México | R8: Supreme | S8: Etapa 6 | T8: Pañales desechables | U8: 36 | V8: piezas | W8: 36 | AA8: Etapa 6 | AB8: Etapa 6 | AD8: Unisex | AG8: Peso del bebé: más de 13.5 kg; Dermatest 5 estrellas: Sí; Formato de venta: Paquete | AH8: https://raw.githubusercontent.com/zublimemx/marketplaces-product-images/main/products/7501943445796/images/7501943445796_1.jpg | AI8: https://raw.githubusercontent.com/zublimemx/marketplaces-product-images/main/products/7501943445796/images/7501943445796_3.jpg | AN8: Mark | AO8: HU SUP UNISEX E6 C/36 | AP8: Verificado
A9: 7501058623188 | B9: 7501058623188 | C9: Fórmula Infantil Nan Optipro 1 Lata 400 g | D9: MLM189058 | E9: Bebés > Comida para Bebés > Leche para Bebés | F9: =Precios!R9 -> 212 | G9: 2092 | H9: =Parámetros!$B$28 -> Nuevo | I9: =Parámetros!$B$29 -> Clásica | J9: Descripción: NAN Optipro 1 (presentada por Nestlé México como NAN 1 Optimal Pro) es una fórmula infantil de inicio en polvo para bebés de 0 a 6 meses. Está elaborada con proteína de suero de leche OPTIPRO y enriquecida con HMO 2'FL, DHA y ARA, el probiótico Limosilactobacillus reuteri y hierro. Beneficios: - Contiene proteína OPTIPRO, DHA y ARA (ácidos grasos omega 3 y omega 6). - Incluye el oligosacárido de leche humana HMO 2'FL (2'-fucosilactosa). - Contiene el probiótico Limosilactobacillus reuteri. - Fórmula adicionada con hierro, vitaminas y minerales. - Aporte por cada 100 kcal: 1.85 g de proteína, 5.26 g de grasa total y 11.29 g de carbohidratos. Ingredientes: Proteína de suero de leche de vaca desmineralizado OPTIPRO (43.87 %), aceites vegetales (oleína de palma, palmiste, canola, maíz y girasol alto oleico), lactosa, minerales, vitaminas, cultivos probióticos de Limosilactobacillus reuteri, HMO (2'-fucosilactosa), DHA y ARA. Contiene: leche, soya y aceite de pescado. Modo de uso: Indicada para bebés de 0 a 6 meses. Prepárese siguiendo estrictamente las instrucciones de preparación y conservación de la etiqueta, con agua segura y utensilios limpios. Presentación: Lata con 400 g de fórmula en polvo. Advertencias: La leche materna es el mejor alimento para el bebé y debe continuarse el mayor tiempo posible. El uso de este producto debe hacerse bajo la orientación de un profesional de la salud. Contiene leche, soya y aceite de pescado. Una preparación o un almacenamiento incorrectos pueden ser perjudiciales para la salud del bebé. | K9: =Parámetros!$B$30 -> Mercado Envíos | L9: =IF(F9>=Parámetros!$B$7,"Envío gratis (obligatorio en Mercado Libre)",Parámetros!$B$31) -> A cargo del comprador | M9: =Parámetros!$B$32 -> No acepto | N9: =Parámetros!$B$33 -> Sin garantía | O9: MLM16139645 | P9: Nan | Q9: Nestlé | R9: Optipro | S9: Etapa 1 | T9: Lata en polvo | U9: 400 | V9: g | W9: 1 | AA9: 0 a 6 meses | AC9: Sin sabor | AD9: Unisex | AG9: Etapa: 1; Con HMO: Sí; Con DHA: Sí; Con probióticos: Sí; Con hierro: Sí; Formato de venta: Unidad; Nombre en empaque actual: Optimal Pro | AH9: https://raw.githubusercontent.com/zublimemx/marketplaces-product-images/main/products/7501058623188/images/7501058623188_1.jpg | AI9: https://raw.githubusercontent.com/zublimemx/marketplaces-product-images/main/products/7501058623188/images/7501058623188_2.jpg | AJ9: https://raw.githubusercontent.com/zublimemx/marketplaces-product-images/main/products/7501058623188/images/7501058623188_3.jpg | AN9: Farma + Mark | AO9: NAN 1 400 GR | AP9: Verificado
A10: 4015630064076 | B10: 4015630064076 | C10: Tiras Reactivas Accu-Chek Active 50 Piezas | D10: MLM189948 | E10: Salud y Equipamiento Médico > Equipamiento Médico > Equipos de Monitoreo > Medidores de Glucosa | F10: =Precios!R10 -> 354 | G10: 57 | H10: =Parámetros!$B$28 -> Nuevo | I10: =Parámetros!$B$29 -> Clásica | J10: Descripción: Tiras reactivas Accu-Chek Active, de Roche, para medir la concentración de glucosa en sangre capilar con el medidor Accu-Chek Active (el medidor no está incluido). Están diseñadas para obtener un resultado con una gota de sangre y sin necesidad de codificar. Características: - Requieren una gota de sangre de 1 a 2 µl. - El resultado se obtiene en aproximadamente 5 segundos cuando la sangre se aplica con la tira dentro del medidor (8 segundos si se aplica fuera). - Permiten agregar más sangre hasta 10 segundos después de la primera aplicación. - No requieren codificación: incluyen un chip negro permanente. - Determinación fotométrica de la glucosa. - Zona de dosificación con malla verde y bloques de color en la etiqueta para verificar visualmente la tira y el resultado. - Estables hasta la fecha indicada en el envase, incluso después de abierto. Modo de uso: 1. Inserte la tira en el medidor. 2. Puncione el dedo con un dispositivo de punción, por ejemplo Accu-Chek Softclix (no incluido). 3. Toque con cuidado la gota de sangre con el campo verde de la tira. 4. Lea el resultado en el medidor. Presentación: Envase con 50 tiras reactivas. Advertencias: Use las tiras únicamente con el medidor compatible. Mantenga el envase bien cerrado después de retirar cada tira para conservar su calidad. Consulte el manual del medidor y a su médico para interpretar los resultados. Mantenga fuera del alcance de los niños. | K10: =Parámetros!$B$30 -> Mercado Envíos | L10: =IF(F10>=Parámetros!$B$7,"Envío gratis (obligatorio en Mercado Libre)",Parámetros!$B$31) -> Envío gratis (obligatorio en Mercado Libre) | M10: =Parámetros!$B$32 -> No acepto | N10: =Parámetros!$B$33 -> Sin garantía | O10: MLM37784929 | P10: Accu-Chek | Q10: Roche | R10: Active | S10: Tiras reactivas de glucosa | T10: Tiras reactivas | U10: 50 | V10: tiras | W10: 50 | AA10: Adultos | AF10: 0679R2017 SSA | AG10: Compatible con: medidor Accu-Chek Active; Volumen de muestra: 1 a 2 µl; Tiempo de resultado: 5 segundos; Requiere codificación: No; Tecnología: Fotométrica; Formato de venta: Caja | AH10: https://raw.githubusercontent.com/zublimemx/marketplaces-product-images/main/products/4015630064076/images/4015630064076_1.jpg | AI10: https://raw.githubusercontent.com/zublimemx/marketplaces-product-images/main/products/4015630064076/images/4015630064076_2.jpg | AN10: Farma | AO10: ACCU CHEK C50 TIRAS ACTIVE | AP10: Verificado
A11: 8020030091252 | B11: 8020030091252 | C11: Vessel Due F 250 LRU 50 Cápsulas | D11: MLM457820 | E11: Salud y Equipamiento Médico > Cuidado de la Salud > Farmacia > Medicamentos de Venta Libre > Para la Sangre Venta Libre | F11: =Precios!R11 -> 829 | G11: 529 | H11: =Parámetros!$B$28 -> Nuevo | I11: =Parámetros!$B$29 -> Clásica | J11: Descripción: Vessel Due F 250 LRU es un medicamento de Alfasigma cuyo principio activo es la sulodexida, un antitrombótico de administración oral. Cada cápsula contiene 250 LRU (unidades lipasémicas) de sulodexida. Beneficios: - Según su ficha, está indicado en el tratamiento de la insuficiencia venosa crónica. - Se utiliza en el tratamiento de las úlceras venosas crónicas. - Se indica en la claudicación intermitente sintomática por enfermedad arterial oclusiva periférica (estadio II). Composición: Cada cápsula contiene sulodexida 250 LRU. Modo de uso: Vía oral. Las cápsulas deben ingerirse con líquido y separadas de las comidas. La dosis y la duración del tratamiento deben ser indicadas por el médico. Presentación: Caja con 50 cápsulas. Advertencias: No debe usarse en caso de hipersensibilidad a la sulodexida, a la heparina o a sustancias similares, ni en pacientes con enfermedad o diátesis hemorrágica. No se recomienda en menores de 18 años. Precaución si toma anticoagulantes orales, ya que puede aumentar su efecto. Evite su uso durante el embarazo y la lactancia. Lea las instrucciones del empaque. Consulte a su médico. No se deje al alcance de los niños. | K11: =Parámetros!$B$30 -> Mercado Envíos | L11: =IF(F11>=Parámetros!$B$7,"Envío gratis (obligatorio en Mercado Libre)",Parámetros!$B$31) -> Envío gratis (obligatorio en Mercado Libre) | M11: =Parámetros!$B$32 -> No acepto | N11: =Parámetros!$B$33 -> Sin garantía | O11: MLM39474253 | P11: Vessel | Q11: Alfasigma | R11: Due F | S11: 250 LRU | T11: Cápsulas | U11: 50 | V11: cápsulas | W11: 50 | X11: Sulodexida | Y11: 250 LRU | Z11: Oral | AA11: Adultos | AF11: 043M99 SSA IV | AG11: Formato de venta: Caja | AH11: https://raw.githubusercontent.com/zublimemx/marketplaces-product-images/main/products/8020030091252/images/8020030091252_4.jpg | AI11: https://raw.githubusercontent.com/zublimemx/marketplaces-product-images/main/products/8020030091252/images/8020030091252_2.jpg | AN11: Farma | AO11: VESSEL DUE F 250 CAPS50 | AP11: Verificado
A12: 7501943444966 | B12: 7501943444966 | C12: Pañales KleenBebé Suavelastic Etapa 5 Jumbo 40 Piezas | D12: MLM178488 | E12: Bebés > Higiene y Cuidado del Bebé > Pañales > Desechables | F12: =Precios!R12 -> 293 | G12: 417 | H12: =Parámetros!$B$28 -> Nuevo | I12: =Parámetros!$B$29 -> Clásica | J12: Descripción: Los pañales KleenBebé Suavelastic Max Etapa 5 (Jumbo), de Kimberly-Clark, están pensados para mantener seco al bebé por mucho más tiempo. Combinan tecnología Blockgel de alta absorción, ajuste con cuatro puntos de sujeción y una fórmula suave con ingredientes como manzanilla, aloe vera y vitamina E. Versión unisex para bebés de de 11 a 14.5 kg. Características: - Maxi sequedad: tecnología Blockgel y centro absorbente de alto desempeño para mantener seco al bebé por más tiempo. - Maxi ajuste: cuatro puntos de sujeción que ayudan a que el pañal no se caiga ni se deforme, con orejas elásticas ajustables y barreras laterales suaves. - Maxi cuidado: fórmula Vitta E Plus con vitamina E, aloe vera y manzanilla, y óxido de zinc que ayuda a prevenir la irritación. - Bolsillo trasero que ayuda a evitar fugas cuando el bebé está acostado. - Dermatológicamente certificados. Modo de uso: Abra el pañal y colóquelo debajo del bebé, lleve la parte delantera hacia arriba y sujete las cintas a la altura de la cintura, sin apretar en exceso. Cámbielo con frecuencia, en cuanto esté húmedo o sucio. Presentación: Paquete con 40 pañales desechables Etapa 5 (Jumbo). Advertencias: Deseche el pañal usado en la basura, no en el inodoro. Mantenga el empaque plástico fuera del alcance de los niños. Verifique que la etapa corresponda al peso de su bebé. | K12: =Parámetros!$B$30 -> Mercado Envíos | L12: =IF(F12>=Parámetros!$B$7,"Envío gratis (obligatorio en Mercado Libre)",Parámetros!$B$31) -> A cargo del comprador | M12: =Parámetros!$B$32 -> No acepto | N12: =Parámetros!$B$33 -> Sin garantía | O12: MLM18976117 | P12: KleenBebé | Q12: Kimberly-Clark de México | R12: Suavelastic | S12: Max Etapa 5 Jumbo | T12: Pañales desechables | U12: 40 | V12: piezas | W12: 40 | AA12: Etapa 5 | AB12: Jumbo | AD12: Unisex | AG12: Peso del bebé: 11 a 14.5 kg; Con óxido de zinc: Sí; Formato de venta: Paquete | AH12: https://raw.githubusercontent.com/zublimemx/marketplaces-product-images/main/products/7501943444966/images/7501943444966_4.jpg | AI12: https://raw.githubusercontent.com/zublimemx/marketplaces-product-images/main/products/7501943444966/images/7501943444966_5.jpg | AN12: Mark | AO12: SUAVE JUM E5 C/40 | AP12: Verificado
A13: 7501109902866 | B13: 7501109902866 | C13: Motrin Infantil Ibuprofeno 20 mg/ml Suspensión 120 ml | D13: MLM194673 | E13: Salud y Equipamiento Médico > Cuidado de la Salud > Farmacia > Medicamentos de Venta Libre > Analgésicos | F13: =Precios!R13 -> 399 | G13: 637 | H13: =Parámetros!$B$28 -> Nuevo | I13: =Parámetros!$B$29 -> Clásica | J13: Descripción: Motrin Infantil es una suspensión oral de ibuprofeno para niños de 2 a 12 años. Cada 100 ml contienen 2 g de ibuprofeno (20 mg por ml). Está libre de alcohol y tiene sabor a frutas. Beneficios: - Ayuda a reducir la fiebre en niños. - Alivia temporalmente el dolor leve a moderado asociado a resfriado, gripe, dolor de garganta, dolor de cabeza y dolor de muelas. - Según la marca, actúa en aproximadamente 15 minutos y sus efectos duran hasta 8 horas. - Incluye vasito dosificador y pipeta para medir la dosis. Composición: Ibuprofeno 2 g por cada 100 ml de suspensión (20 mg/ml), en vehículo cbp. Modo de uso: Vía oral. Agite bien antes de cada uso y utilice únicamente el dosificador incluido. Se administra una toma cada 6 a 8 horas, sin exceder 4 tomas en 24 horas. La dosis se determina de preferencia por el peso del niño: - 10 a 15 kg (2 a 3 años): 5 ml - 16 a 21 kg (4 a 5 años): 7.5 ml - 21.5 a 26.5 kg (6 a 8 años): 10 ml - 27 a 32 kg (9 a 10 años): 12.5 ml - 32.5 a 43 kg (11 a 12 años): 15 ml No lo use por más de 5 días sin consultar al médico. Presentación: Caja con un frasco de 120 ml, con vasito dosificador y pipeta. Conservar a temperatura ambiente controlada, entre 15 y 30 grados centígrados. Advertencias: No debe usarse en caso de hipersensibilidad al ibuprofeno, a la aspirina o a otros antiinflamatorios, úlcera péptica activa o hemorragia gastrointestinal, ni insuficiencia renal o hepática grave. Puede causar reacciones alérgicas graves y sangrado estomacal, sobre todo con uso prolongado o dosis mayores; los antiinflamatorios pueden aumentar el riesgo cardiovascular. Consulte al médico si el niño tiene úlceras, enfermedad renal o cardíaca, o toma anticoagulantes. Lea las instrucciones del empaque. Consulte a su médico. No se deje al alcance de los niños. | K13: =Parámetros!$B$30 -> Mercado Envíos | L13: =IF(F13>=Parámetros!$B$7,"Envío gratis (obligatorio en Mercado Libre)",Parámetros!$B$31) -> Envío gratis (obligatorio en Mercado Libre) | M13: =Parámetros!$B$32 -> No acepto | N13: =Parámetros!$B$33 -> Sin garantía | O13: MLM39455417 | P13: Motrin | Q13: Janssen-Cilag de México | R13: Infantil | S13: Suspensión 2 g/100 ml | T13: Suspensión oral | U13: 120 | V13: ml | W13: 1 | X13: Ibuprofeno | Y13: 20 mg/ml (2 g/100 ml) | Z13: Oral | AA13: Niños de 2 a 12 años | AC13: Frutas | AD13: Niños | AF13: 630M98 SSA VI | AG13: Formato de venta: Caja con frasco; Sin alcohol: Sí; Incluye vaso dosificador y pipeta dosificadora: Sí | AH13: https://raw.githubusercontent.com/zublimemx/marketplaces-product-images/main/products/7501109902866/images/7501109902866_1.jpg | AI13: https://raw.githubusercontent.com/zublimemx/marketplaces-product-images/main/products/7501109902866/images/7501109902866_2.jpg | AJ13: https://raw.githubusercontent.com/zublimemx/marketplaces-product-images/main/products/7501109902866/images/7501109902866_3.jpg | AK13: https://raw.githubusercontent.com/zublimemx/marketplaces-product-images/main/products/7501109902866/images/7501109902866_4.jpg | AN13: Farma | AO13: MOTRIN INF SUSP 20MG 1ML FEBRERO 28 30 | AP13: Verificado
A14: 7506425645749 | B14: 7506425645749 | C14: Pañales KleenBebé Suavelastic Etapa 7 XXJumbo 40 Piezas | D14: MLM178488 | E14: Bebés > Higiene y Cuidado del Bebé > Pañales > Desechables | F14: =Precios!R14 -> 493 | G14: 263 | H14: =Parámetros!$B$28 -> Nuevo | I14: =Parámetros!$B$29 -> Clásica | J14: Descripción: Los pañales KleenBebé Suavelastic Max Etapa 7 (Extra Extra Jumbo), de Kimberly-Clark, están pensados para mantener seco al bebé por mucho más tiempo. Combinan tecnología Blockgel de alta absorción, ajuste con cuatro puntos de sujeción y una fórmula suave con ingredientes como manzanilla, aloe vera y vitamina E. Versión unisex para bebés de de 16 a 24 kg. Características: - Maxi sequedad: tecnología Blockgel y centro absorbente de alto desempeño para mantener seco al bebé por más tiempo. - Maxi ajuste: cuatro puntos de sujeción que ayudan a que el pañal no se caiga ni se deforme, con orejas elásticas ajustables y barreras laterales suaves. - Maxi cuidado: fórmula Vitta E Plus con vitamina E, aloe vera y manzanilla, y óxido de zinc que ayuda a prevenir la irritación. - Bolsillo trasero que ayuda a evitar fugas cuando el bebé está acostado. - Dermatológicamente certificados. Modo de uso: Abra el pañal y colóquelo debajo del bebé, lleve la parte delantera hacia arriba y sujete las cintas a la altura de la cintura, sin apretar en exceso. Cámbielo con frecuencia, en cuanto esté húmedo o sucio. Presentación: Paquete con 40 pañales desechables Etapa 7 (Extra Extra Jumbo). Advertencias: Deseche el pañal usado en la basura, no en el inodoro. Mantenga el empaque plástico fuera del alcance de los niños. Verifique que la etapa corresponda al peso de su bebé. | K14: =Parámetros!$B$30 -> Mercado Envíos | L14: =IF(F14>=Parámetros!$B$7,"Envío gratis (obligatorio en Mercado Libre)",Parámetros!$B$31) -> Envío gratis (obligatorio en Mercado Libre) | M14: =Parámetros!$B$32 -> No acepto | N14: =Parámetros!$B$33 -> Sin garantía | O14: MLM23011505 | P14: KleenBebé | Q14: Kimberly-Clark de México | R14: Suavelastic | S14: Etapa 7 Extra Extra Jumbo | T14: Pañales desechables | U14: 40 | V14: piezas | W14: 40 | AA14: Etapa 7 | AB14: Extra Extra Jumbo | AD14: Unisex | AG14: Peso del bebé: 16 a 24 kg; Con óxido de zinc: Sí; Formato de venta: Paquete | AH14: https://raw.githubusercontent.com/zublimemx/marketplaces-product-images/main/products/7506425645749/images/7506425645749_2.jpg | AI14: https://raw.githubusercontent.com/zublimemx/marketplaces-product-images/main/products/7506425645749/images/7506425645749_5.jpg | AN14: Mark | AO14: SUAVE XJBO E7 C40 | AP14: Verificado
A15: 7501943441767 | B15: 7501943441767 | C15: Pañales Huggies Supreme Unisex Etapa 4 36 Piezas | D15: MLM178488 | E15: Bebés > Higiene y Cuidado del Bebé > Pañales > Desechables | F15: =Precios!R15 -> 422 | G15: 680 | H15: =Parámetros!$B$28 -> Nuevo | I15: =Parámetros!$B$29 -> Clásica | J15: Descripción: Los pañales Huggies Supreme Etapa 4, de Kimberly-Clark, están diseñados para proteger la delicada piel del bebé con materiales de superior suavidad. Es la línea Huggies que se presenta como única clínica y dermatológicamente probada, con certificación Dermatest de cinco estrellas. Versión unisex para bebés de 9 a 12 kg. Características: - Clínica y dermatológicamente probados, con certificación Dermatest de 5 estrellas. - Materiales de superior suavidad que ayudan a evitar la irritación. - Manejo de la humedad que ayuda a mantener la piel fresca y sana. - Cintas ajustables para un ajuste cómodo y seguro que permite libertad de movimiento. - Diseños exclusivos en los pañales. - Unisex: para niños y niñas. Modo de uso: Abra el pañal y colóquelo debajo del bebé, lleve la parte delantera hacia arriba y sujete las cintas a la altura de la cintura, sin apretar en exceso. Cámbielo con frecuencia, en cuanto esté húmedo o sucio. Presentación: Paquete con 36 pañales desechables Etapa 4. Advertencias: Deseche el pañal usado en la basura, no en el inodoro. Mantenga el empaque plástico fuera del alcance de los niños. Verifique que la etapa corresponda al peso de su bebé. | K15: =Parámetros!$B$30 -> Mercado Envíos | L15: =IF(F15>=Parámetros!$B$7,"Envío gratis (obligatorio en Mercado Libre)",Parámetros!$B$31) -> Envío gratis (obligatorio en Mercado Libre) | M15: =Parámetros!$B$32 -> No acepto | N15: =Parámetros!$B$33 -> Sin garantía | O15: MLM17379816 | P15: Huggies | Q15: Kimberly-Clark de México | R15: Supreme | S15: Etapa 4 | T15: Pañales desechables | U15: 36 | V15: piezas | W15: 36 | AA15: Etapa 4 | AB15: Etapa 4 | AD15: Unisex | AG15: Peso del bebé: 9 a 12 kg; Dermatest 5 estrellas: Sí; Formato de venta: Paquete | AH15: https://raw.githubusercontent.com/zublimemx/marketplaces-product-images/main/products/7501943441767/images/7501943441767_1.jpg | AI15: https://raw.githubusercontent.com/zublimemx/marketplaces-product-images/main/products/7501943441767/images/7501943441767_2.jpg | AN15: Mark | AO15: HU SUP UNISEX E4 C/36 | AP15: Verificado
A16: 7501943444942 | B16: 7501943444942 | C16: Pañales KleenBebé Suavelastic Etapa 4 Grande 44 Piezas | D16: MLM178488 | E16: Bebés > Higiene y Cuidado del Bebé > Pañales > Desechables | F16: =Precios!R16 -> 275 | G16: 604 | H16: =Parámetros!$B$28 -> Nuevo | I16: =Parámetros!$B$29 -> Clásica | J16: Descripción: Los pañales KleenBebé Suavelastic Max Etapa 4 (Grande), de Kimberly-Clark, están pensados para mantener seco al bebé por mucho más tiempo. Combinan tecnología Blockgel de alta absorción, ajuste con cuatro puntos de sujeción y una fórmula suave con ingredientes como manzanilla, aloe vera y vitamina E. Versión unisex para bebés de de 9 a 12 kg. Características: - Maxi sequedad: tecnología Blockgel y centro absorbente de alto desempeño para mantener seco al bebé por más tiempo. - Maxi ajuste: cuatro puntos de sujeción que ayudan a que el pañal no se caiga ni se deforme, con orejas elásticas ajustables y barreras laterales suaves. - Maxi cuidado: fórmula Vitta E Plus con vitamina E, aloe vera y manzanilla, y óxido de zinc que ayuda a prevenir la irritación. - Bolsillo trasero que ayuda a evitar fugas cuando el bebé está acostado. - Dermatológicamente certificados. Modo de uso: Abra el pañal y colóquelo debajo del bebé, lleve la parte delantera hacia arriba y sujete las cintas a la altura de la cintura, sin apretar en exceso. Cámbielo con frecuencia, en cuanto esté húmedo o sucio. Presentación: Paquete con 44 pañales desechables Etapa 4 (Grande). Advertencias: Deseche el pañal usado en la basura, no en el inodoro. Mantenga el empaque plástico fuera del alcance de los niños. Verifique que la etapa corresponda al peso de su bebé. | K16: =Parámetros!$B$30 -> Mercado Envíos | L16: =IF(F16>=Parámetros!$B$7,"Envío gratis (obligatorio en Mercado Libre)",Parámetros!$B$31) -> A cargo del comprador | M16: =Parámetros!$B$32 -> No acepto | N16: =Parámetros!$B$33 -> Sin garantía | O16: MLM42012939 | P16: KleenBebé | Q16: Kimberly-Clark de México | R16: Suavelastic | S16: Max Etapa 4 Grande | T16: Pañales desechables | U16: 44 | V16: piezas | W16: 44 | AA16: Etapa 4 | AB16: Grande | AD16: Unisex | AG16: Peso del bebé: 9 a 12 kg; Con óxido de zinc: Sí; Formato de venta: Paquete | AH16: https://raw.githubusercontent.com/zublimemx/marketplaces-product-images/main/products/7501943444942/images/7501943444942_2.jpg | AI16: https://raw.githubusercontent.com/zublimemx/marketplaces-product-images/main/products/7501943444942/images/7501943444942_5.jpg | AN16: Mark | AO16: SUAVE GDE E4 C/44 | AP16: Verificado
A17: 7501943447615 | B17: 7501943447615 | C17: Pañales KleenBebé Suavelastic Etapa 6 Extra Jumbo 40 Piezas | D17: MLM178488 | E17: Bebés > Higiene y Cuidado del Bebé > Pañales > Desechables | F17: =Precios!R17 -> 407 | G17: 610 | H17: =Parámetros!$B$28 -> Nuevo | I17: =Parámetros!$B$29 -> Clásica | J17: Descripción: Los pañales KleenBebé Suavelastic Max Etapa 6 (Extra Jumbo), de Kimberly-Clark, están pensados para mantener seco al bebé por mucho más tiempo. Combinan tecnología Blockgel de alta absorción, ajuste con cuatro puntos de sujeción y una fórmula suave con ingredientes como manzanilla, aloe vera y vitamina E. Versión unisex para bebés de de 13.5 a 17 kg. Características: - Maxi sequedad: tecnología Blockgel y centro absorbente de alto desempeño para mantener seco al bebé por más tiempo. - Maxi ajuste: cuatro puntos de sujeción que ayudan a que el pañal no se caiga ni se deforme, con orejas elásticas ajustables y barreras laterales suaves. - Maxi cuidado: fórmula Vitta E Plus con vitamina E, aloe vera y manzanilla, y óxido de zinc que ayuda a prevenir la irritación. - Bolsillo trasero que ayuda a evitar fugas cuando el bebé está acostado. - Dermatológicamente certificados. Modo de uso: Abra el pañal y colóquelo debajo del bebé, lleve la parte delantera hacia arriba y sujete las cintas a la altura de la cintura, sin apretar en exceso. Cámbielo con frecuencia, en cuanto esté húmedo o sucio. Presentación: Paquete con 40 pañales desechables Etapa 6 (Extra Jumbo). Advertencias: Deseche el pañal usado en la basura, no en el inodoro. Mantenga el empaque plástico fuera del alcance de los niños. Verifique que la etapa corresponda al peso de su bebé. | K17: =Parámetros!$B$30 -> Mercado Envíos | L17: =IF(F17>=Parámetros!$B$7,"Envío gratis (obligatorio en Mercado Libre)",Parámetros!$B$31) -> Envío gratis (obligatorio en Mercado Libre) | M17: =Parámetros!$B$32 -> No acepto | N17: =Parámetros!$B$33 -> Sin garantía | O17: MLM18976308 | P17: KleenBebé | Q17: Kimberly-Clark de México | R17: Suavelastic | S17: Max Etapa 6 Extra Jumbo | T17: Pañales desechables | U17: 40 | V17: piezas | W17: 40 | AA17: Etapa 6 | AB17: Extra Jumbo | AD17: Unisex | AG17: Peso del bebé: 13.5 a 17 kg; Con óxido de zinc: Sí; Formato de venta: Paquete | AH17: https://raw.githubusercontent.com/zublimemx/marketplaces-product-images/main/products/7501943447615/images/7501943447615_1.jpg | AI17: https://raw.githubusercontent.com/zublimemx/marketplaces-product-images/main/products/7501943447615/images/7501943447615_3.jpg | AN17: Mark | AO17: SUAVE EX JUM E6C/40 | AP17: Verificado
A18: 7501123013340 | B18: 7501123013340 | C18: Bedoyecta Complejo B Ácido Fólico Vitamina C 30 Cápsulas | D18: MLM438195 | E18: Salud y Equipamiento Médico > Suplementos Alimenticios | F18: =Precios!R18 -> 271.46 | G18: 2942 | H18: =Parámetros!$B$28 -> Nuevo | I18: =Parámetros!$B$29 -> Clásica | J18: Descripción: Bedoyecta Cápsulas, de Laboratorios Grossman, es un multivitamínico en cápsulas de gelatina blanda que reúne vitaminas del complejo B, ácido fólico, vitamina C y rutina. La presentación en gelatina blanda está pensada para una mejor absorción. Beneficios: - Ayuda a obtener la energía necesaria para las actividades del día y un buen rendimiento. - Cubre deficiencias de vitaminas del complejo B, ácido fólico y vitamina C. - Según su ficha, se utiliza en la prevención y el tratamiento de las deficiencias de las vitaminas que contiene, incluso en situaciones de mayor requerimiento como diabetes, alcoholismo o actividad física intensa. - Se indica también como apoyo en neuropatías nutricionales, alcohólicas y diabéticas, dolor de espalda, ciática y calambres musculares. Composición: Vitamina B1 (tiamina), vitamina B2 (riboflavina), vitamina B6 (piridoxina), vitamina B12 (cianocobalamina), ácido fólico, vitamina C (ácido ascórbico) y rutina. Las cantidades por cápsula se indican en la etiqueta del producto. Modo de uso: Vía oral. Tome las cápsulas según lo indicado en el empaque o por su médico. Presentación: Caja con 30 cápsulas de gelatina blanda. Advertencias: No exceda la dosis indicada. Si está embarazada, en lactancia o toma otros multivitamínicos o medicamentos, consulte a su médico antes de usarlo. Lea las instrucciones del empaque. Consulte a su médico. No se deje al alcance de los niños. | K18: =Parámetros!$B$30 -> Mercado Envíos | L18: =IF(F18>=Parámetros!$B$7,"Envío gratis (obligatorio en Mercado Libre)",Parámetros!$B$31) -> A cargo del comprador | M18: =Parámetros!$B$32 -> No acepto | N18: =Parámetros!$B$33 -> Sin garantía | O18: MLM45284329 | P18: Bedoyecta | Q18: Laboratorios Grossman | R18: Cápsulas | S18: Complejo B, ácido fólico, vitamina C y rutina | T18: Cápsulas de gelatina blanda | U18: 30 | V18: cápsulas | W18: 30 | X18: Complejo B, ácido fólico, vitamina C y rutina | Z18: Oral | AA18: Adultos | AG18: Tipo de suplemento: Multivitamínico; Formato de venta: Caja | AH18: https://raw.githubusercontent.com/zublimemx/marketplaces-product-images/main/products/7501123013340/images/7501123013340_1.jpg | AI18: https://raw.githubusercontent.com/zublimemx/marketplaces-product-images/main/products/7501123013340/images/7501123013340_2.jpg | AJ18: https://raw.githubusercontent.com/zublimemx/marketplaces-product-images/main/products/7501123013340/images/7501123013340_3.jpg | AN18: Farma | AO18: BEDOYECTA CAPS C 30 | AP18: Verificado
A19: 008400009418 | B19: 008400009418 | C19: Ribotripsin 18 mg 30 Tabletas | D19: MLM455222 | E19: Salud y Equipamiento Médico > Cuidado de la Salud > Farmacia > Medicamentos de Venta Libre > Antiinflamatorios | F19: =Precios!R19 -> 576.33 | G19: 1094 | H19: =Parámetros!$B$28 -> Nuevo | I19: =Parámetros!$B$29 -> Clásica | J19: Descripción: Ribotripsin es un medicamento de Laboratorios Grin en tabletas con capa entérica. Combina las enzimas proteolíticas tripsina y quimotripsina, que ayudan a acelerar la reparación de los tejidos. Beneficios: - Según su ficha, alivia el edema inflamatorio. - Favorece la reabsorción de la sangre extravasada (moretones) y de los exudados en contusiones leves. - Reduce el dolor en procesos inflamatorios postraumáticos. - Su capa entérica protege las tabletas de la acidez del estómago. Composición: Cada tableta contiene 18 mg de enzimas, equivalentes a tripsina 45,000 U USP y quimotripsina 9,000 U USP, con excipientes cbp. Modo de uso: Vía oral. La dosis habitual de referencia de la ficha es de dos tabletas cada 8 horas; la dosis y la duración del tratamiento deben ser indicadas por el médico. Presentación: Caja con 30 tabletas con capa entérica. Conservar a temperatura ambiente no mayor a 30 grados centígrados. Advertencias: No debe usarse en caso de hipersensibilidad a los componentes, pancreatitis aguda, síndromes hemorrágicos, insuficiencia hepática grave, insuficiencia cardíaca congestiva, hipoprotrombinemia ni antes de una cirugía próxima. No se recomienda su uso simultáneo con anticoagulantes; precaución en pacientes con úlcera gástrica. No lo consuma con bebidas alcohólicas. No se ha establecido su seguridad durante el embarazo y la lactancia. Puede causar molestias gastrointestinales leves, erupción o comezón. Lea las instrucciones del empaque. Consulte a su médico. No se deje al alcance de los niños. | K19: =Parámetros!$B$30 -> Mercado Envíos | L19: =IF(F19>=Parámetros!$B$7,"Envío gratis (obligatorio en Mercado Libre)",Parámetros!$B$31) -> Envío gratis (obligatorio en Mercado Libre) | M19: =Parámetros!$B$32 -> No acepto | N19: =Parámetros!$B$33 -> Sin garantía | O19: MLM39474731 | P19: Ribotripsin | Q19: Laboratorios Grin | S19: 18 mg | T19: Tabletas con capa entérica | U19: 30 | V19: tabletas | W19: 30 | X19: Tripsina y quimotripsina | Y19: 18 mg (45,000 U USP / 9,000 U USP) | Z19: Oral | AA19: Adultos | AF19: 65517 SSA IV | AG19: Formato de venta: Caja | AH19: https://raw.githubusercontent.com/zublimemx/marketplaces-product-images/main/products/008400009418/images/008400009418_1.jpg | AN19: Farma | AO19: RIBOTRIPSIN 18MG C30TAB | AP19: Verificado
A20: 7590002012468 | B20: 7590002012468 | C20: Vick VapoRub Ungüento Tópico 50 g | D20: MLM194695 | E20: Salud y Equipamiento Médico > Cuidado de la Salud > Farmacia > Medicamentos de Venta Libre > Antigripales | F20: =Precios!R20 -> 158.07 | G20: 241 | H20: =Parámetros!$B$28 -> Nuevo | I20: =Parámetros!$B$29 -> Clásica | J20: Descripción: Vick VapoRub es un ungüento tópico de Procter & Gamble elaborado con alcanfor, mentol y aceite de eucalipto en una base de petrolato. Se aplica sobre el pecho y el cuello para ayudar a aliviar la congestión nasal de los resfriados. Beneficios: - Ayuda a aliviar la congestión nasal para respirar con mayor facilidad y descansar mejor. - Se utiliza para el alivio temporal de la tos asociada al resfriado. - Puede aplicarse en la zona afectada para aliviar dolores musculares leves. - Aroma característico a mentol y eucalipto. Composición: Ingredientes activos: alcanfor, mentol y aceite de eucalipto. Excipientes, entre ellos petrolato, aceite de trementina, aceite de nuez moscada, aceite de hoja de cedro y timol. Modo de uso: Uso externo. Aplique una capa gruesa sobre el pecho y el cuello y frote hasta que se absorba; puede usarse por la mañana y por la noche. Para dolores musculares, frote en la zona afectada hasta cuatro veces al día. En niños mayores de 2 años, úselo bajo la supervisión de un adulto. Presentación: Tarro con 50 g de ungüento. Advertencias: No debe usarse en caso de hipersensibilidad a los componentes ni en menores de 2 años (contiene alcanfor). Evite el contacto con los ojos, no lo ingiera, no lo aplique en heridas ni en piel dañada, no lo introduzca en la nariz y no lo caliente directamente ni en horno de microondas por riesgo de quemaduras. Suspenda su uso si aparece irritación. Si presenta fiebre o los síntomas persisten por más de 3 días, consulte a su médico. Lea las instrucciones del empaque. Consulte a su médico. No se deje al alcance de los niños. | K20: =Parámetros!$B$30 -> Mercado Envíos | L20: =IF(F20>=Parámetros!$B$7,"Envío gratis (obligatorio en Mercado Libre)",Parámetros!$B$31) -> A cargo del comprador | M20: =Parámetros!$B$32 -> No acepto | N20: =Parámetros!$B$33 -> Sin garantía | O20: MLM45287887 | P20: Vick | Q20: Procter & Gamble | R20: VapoRub | S20: Ungüento tópico | T20: Ungüento | U20: 50 | V20: g | W20: 1 | X20: Alcanfor, mentol y aceite de eucalipto | Z20: Tópica | AA20: Niños mayores de 2 años y adultos | AC20: Mentol y eucalipto | AD20: Unisex | AG20: Formato de venta: Unidad; Envase: Tarro | AH20: https://raw.githubusercontent.com/zublimemx/marketplaces-product-images/main/products/7590002012468/images/7590002012468_1.jpg | AI20: https://raw.githubusercontent.com/zublimemx/marketplaces-product-images/main/products/7590002012468/images/7590002012468_3.jpg | AN20: Farma | AO20: VAPORUB 50GR TARRO 96 | AP20: Verificado
A21: 7501298217659 | B21: 7501298217659 | C21: Dolo-Neurobión DC Solución Inyectable 3 Jeringas 3 ml | D21: MLM457822 | E21: Salud y Equipamiento Médico > Cuidado de la Salud > Farmacia > Medicamentos de Venta Libre > Musculoarticulares Venta Libre | F21: =Precios!R21 -> 718.06 | G21: 1012 | H21: =Parámetros!$B$28 -> Nuevo | I21: =Parámetros!$B$29 -> Clásica | J21: Descripción: Dolo-Neurobión DC, de Merck, es una solución inyectable en jeringa prellenada de doble cámara de 3 ml. Combina el antiinflamatorio diclofenaco sódico con las vitaminas B1, B6 y B12 y el anestésico local lidocaína; las dos cámaras se mezclan justo antes de la aplicación. Beneficios: - Según su ficha, se utiliza para el alivio del dolor y la inflamación en lumbalgias, cervicalgias, braquialgias y radiculitis. - Se indica en neuropatías periféricas de diversas causas, como la neuropatía diabética. - Presentación de doble cámara que separa los componentes hasta el momento de su uso. Composición: Contenido de cada jeringa: - Diclofenaco sódico 75 mg - Vitamina B12 (cianocobalamina) 1 mg - Vitamina B1 (tiamina) 100 mg - Vitamina B6 (piridoxina) 100 mg - Lidocaína (clorhidrato) 20 mg Modo de uso: Vía intramuscular, aplicada por personal de salud. Antes de la aplicación se mezclan las soluciones de las dos cámaras. La dosis indicada en la ficha es una jeringa prellenada una vez al día; la duración del tratamiento debe ser determinada por el médico. Presentación: Caja con 3 jeringas prellenadas de doble cámara de 3 ml y agujas desechables. Advertencias: No debe usarse en caso de hipersensibilidad a los componentes, úlcera péptica, sensibilidad a la aspirina o a otros antiinflamatorios, trastornos de la sangre ni insuficiencia hepática. No se administre durante el embarazo ni la lactancia ni a menores de 12 años. Precaución en insuficiencia renal, hipertensión no controlada y tratamiento con levodopa. Puede causar náusea, vómito, mareo, dolor de cabeza y, rara vez, hemorragia gastroduodenal. Lea las instrucciones del empaque. Consulte a su médico. No se deje al alcance de los niños. | K21: =Parámetros!$B$30 -> Mercado Envíos | L21: =IF(F21>=Parámetros!$B$7,"Envío gratis (obligatorio en Mercado Libre)",Parámetros!$B$31) -> Envío gratis (obligatorio en Mercado Libre) | M21: =Parámetros!$B$32 -> No acepto | N21: =Parámetros!$B$33 -> Sin garantía | O21: MLM52121009 | P21: Dolo-Neurobión | Q21: Merck | R21: DC | S21: Doble cámara | T21: Solución inyectable en jeringa prellenada de doble cámara | U21: 3 | V21: ml | W21: 3 | X21: Diclofenaco, lidocaína y vitaminas B1, B6 y B12 | Y21: Diclofenaco 75 mg, vitamina B1 100 mg, vitamina B6 100 mg, vitamina B12 1 mg, lidocaína 20 mg por jeringa | Z21: Intramuscular | AA21: Adultos | AF21: 79717 SSA | AG21: Incluye agujas desechables: Sí; Formato de venta: Caja | AH21: https://raw.githubusercontent.com/zublimemx/marketplaces-product-images/main/products/7501298217659/images/7501298217659_3.jpg | AI21: https://raw.githubusercontent.com/zublimemx/marketplaces-product-images/main/products/7501298217659/images/7501298217659_4.jpg | AN21: Farma | AO21: DOLO NEUROBION DC C3AMP | AP21: Verificado
A22: 7506425664191 | B22: 7506425664191 | C22: Pañales Huggies Supreme Unisex Etapa 7 36 Piezas | D22: MLM178488 | E22: Bebés > Higiene y Cuidado del Bebé > Pañales > Desechables | F22: =Precios!R22 -> 529 | G22: 101 | H22: =Parámetros!$B$28 -> Nuevo | I22: =Parámetros!$B$29 -> Clásica | J22: Descripción: Los pañales Huggies Supreme Etapa 7, de Kimberly-Clark, están diseñados para proteger la delicada piel del bebé con materiales de superior suavidad. Es la línea Huggies que se presenta como única clínica y dermatológicamente probada, con certificación Dermatest de cinco estrellas. Versión unisex para bebés de más de 16 kg. Características: - Clínica y dermatológicamente probados, con certificación Dermatest de 5 estrellas. - Materiales de superior suavidad que ayudan a evitar la irritación. - Manejo de la humedad que ayuda a mantener la piel fresca y sana. - Cintas ajustables para un ajuste cómodo y seguro que permite libertad de movimiento. - Diseños exclusivos en los pañales. - Unisex: para niños y niñas. Modo de uso: Abra el pañal y colóquelo debajo del bebé, lleve la parte delantera hacia arriba y sujete las cintas a la altura de la cintura, sin apretar en exceso. Cámbielo con frecuencia, en cuanto esté húmedo o sucio. Presentación: Paquete con 36 pañales desechables Etapa 7. Advertencias: Deseche el pañal usado en la basura, no en el inodoro. Mantenga el empaque plástico fuera del alcance de los niños. Verifique que la etapa corresponda al peso de su bebé. | K22: =Parámetros!$B$30 -> Mercado Envíos | L22: =IF(F22>=Parámetros!$B$7,"Envío gratis (obligatorio en Mercado Libre)",Parámetros!$B$31) -> Envío gratis (obligatorio en Mercado Libre) | M22: =Parámetros!$B$32 -> No acepto | N22: =Parámetros!$B$33 -> Sin garantía | P22: Huggies | Q22: Kimberly-Clark de México | R22: Supreme | S22: Etapa 7 | T22: Pañales desechables | U22: 36 | V22: piezas | W22: 36 | AA22: Etapa 7 | AB22: Etapa 7 | AD22: Unisex | AG22: Peso del bebé: más de 16 kg; Dermatest 5 estrellas: Sí; Formato de venta: Paquete | AH22: https://raw.githubusercontent.com/zublimemx/marketplaces-product-images/main/products/7506425664191/images/7506425664191_1.jpg | AI22: https://raw.githubusercontent.com/zublimemx/marketplaces-product-images/main/products/7506425664191/images/7506425664191_2.jpg | AJ22: https://raw.githubusercontent.com/zublimemx/marketplaces-product-images/main/products/7506425664191/images/7506425664191_3.jpg | AN22: Mark | AO22: HUGG SUPR UNISEX ET7 C/36 C5 | AP22: Verificado
A23: 7506425604364 | B23: 7506425604364 | C23: Pañales Huggies UltraConfort Niño Etapa 6 40 Piezas | D23: MLM178488 | E23: Bebés > Higiene y Cuidado del Bebé > Pañales > Desechables | F23: =Precios!R23 -> 566 | G23: 292 | H23: =Parámetros!$B$28 -> Nuevo | I23: =Parámetros!$B$29 -> Clásica | J23: Descripción: Los pañales Huggies UltraConfort Niño Etapa 6, de Kimberly-Clark, combinan un corte anatómico con mayor cobertura y un material ultra flexible que se adapta al cuerpo del bebé. Están diseñados para niños de más de 13.5 kg. Características: - Corte anatómico con mayor cobertura y material ultra flexible. - Cintas Confort Flex en forma de V con 4 puntos de sujeción. - Cintura elástica más suave y flexible. - Núcleo absorbente reforzado, ubicado en la parte delantera para niños. - Cubierta interna con poros ultra absorbentes. - Indicador de humedad e indicador de cambio de etapa. - Probados dermatológicamente, con certificación Dermatest. Modo de uso: Abra el pañal y colóquelo debajo del bebé, lleve la parte delantera hacia arriba y sujete las cintas a la altura de la cintura, sin apretar en exceso. Cámbielo con frecuencia, en cuanto esté húmedo o sucio. Presentación: Paquete con 40 pañales desechables Etapa 6 para niño. Advertencias: Deseche el pañal usado en la basura, no en el inodoro. Mantenga el empaque plástico fuera del alcance de los niños. Verifique que la etapa corresponda al peso de su bebé. | K23: =Parámetros!$B$30 -> Mercado Envíos | L23: =IF(F23>=Parámetros!$B$7,"Envío gratis (obligatorio en Mercado Libre)",Parámetros!$B$31) -> Envío gratis (obligatorio en Mercado Libre) | M23: =Parámetros!$B$32 -> No acepto | N23: =Parámetros!$B$33 -> Sin garantía | O23: MLM17379861 | P23: Huggies | Q23: Kimberly-Clark de México | R23: UltraConfort | S23: Niño Etapa 6 | T23: Pañales desechables | U23: 40 | V23: piezas | W23: 40 | AA23: Etapa 6 | AB23: Etapa 6 | AD23: Niños | AG23: Peso del bebé: más de 13.5 kg; Indicador de humedad: Sí; Dermatest: Sí; Formato de venta: Paquete | AH23: https://raw.githubusercontent.com/zublimemx/marketplaces-product-images/main/products/7506425604364/images/7506425604364_3.jpg | AI23: https://raw.githubusercontent.com/zublimemx/marketplaces-product-images/main/products/7506425604364/images/7506425604364_4.jpg | AN23: Mark | AO23: HU CONF NINO E6 C40 | AP23: Verificado
A24: 7503007704658 | B24: 7503007704658 | C24: Núcleo C.M.P. Forte 5 mg/3 mg 30 Cápsulas | D24: MLM457812 | E24: Salud y Equipamiento Médico > Cuidado de la Salud > Farmacia > Medicamentos de Venta Libre > Sistema Nervioso Venta Libre | F24: =Precios!R24 -> 587 | G24: 945 | H24: =Parámetros!$B$28 -> Nuevo | I24: =Parámetros!$B$29 -> Clásica | J24: Descripción: Núcleo C.M.P. Forte es un medicamento de Ferrer en cápsulas para administración oral. Combina dos nucleótidos: citidín-5'-monofosfato disódico (CMP) y uridín-5'-trifosfato trisódico (UTP). Beneficios: - Según su ficha, se utiliza en el tratamiento de neuropatías periféricas de origen osteoarticular, metabólico, infeccioso o por frío. - Se indica también en neuralgias. - Aporta grupos fosfato que participan en el metabolismo de componentes de la mielina, lo que favorece la regeneración del tejido nervioso. Composición: Cada cápsula contiene: - Citidín-5'-monofosfato disódico (CMP) 5 mg - Uridín-5'-trifosfato trisódico (UTP) 3 mg Excipientes cbp. Modo de uso: Vía oral. La dosis de referencia de la ficha es de 1 a 2 cápsulas dos veces al día; la dosis y la duración del tratamiento deben ser indicadas por el médico. Presentación: Caja con 30 cápsulas. Conservar a no más de 30 grados centígrados en envase bien cerrado. Advertencias: No debe usarse en caso de hipersensibilidad a alguno de los componentes de la fórmula. En personas sensibles puede causar náusea, vómito y urticaria. Consulte a su médico antes de usarlo durante el embarazo o la lactancia. Lea las instrucciones del empaque. Consulte a su médico. No se deje al alcance de los niños. | K24: =Parámetros!$B$30 -> Mercado Envíos | L24: =IF(F24>=Parámetros!$B$7,"Envío gratis (obligatorio en Mercado Libre)",Parámetros!$B$31) -> Envío gratis (obligatorio en Mercado Libre) | M24: =Parámetros!$B$32 -> No acepto | N24: =Parámetros!$B$33 -> Sin garantía | O24: MLM42117810 | P24: Núcleo C.M.P. | Q24: Ferrer | R24: Forte | S24: 5 mg/3 mg | T24: Cápsulas | U24: 30 | V24: cápsulas | W24: 30 | X24: Citidín-5'-monofosfato disódico y uridín-5'-trifosfato trisódico | Y24: 5 mg/3 mg | Z24: Oral | AA24: Adultos | AF24: 83301 SSA IV | AG24: Formato de venta: Caja | AH24: https://raw.githubusercontent.com/zublimemx/marketplaces-product-images/main/products/7503007704658/images/7503007704658_1.jpg | AI24: https://raw.githubusercontent.com/zublimemx/marketplaces-product-images/main/products/7503007704658/images/7503007704658_2.jpg | AJ24: https://raw.githubusercontent.com/zublimemx/marketplaces-product-images/main/products/7503007704658/images/7503007704658_3.jpg | AN24: Farma | AO24: NUCLEO C M P FORTE 5 3 MG C 30 CAPS | AP24: Verificado
A25: 7501058623195 | B25: 7501058623195 | C25: Fórmula Infantil Nan Optipro 2 Lata 400 g | D25: MLM189058 | E25: Bebés > Comida para Bebés > Leche para Bebés | F25: =Precios!R25 -> 329 | G25: 1641 | H25: =Parámetros!$B$28 -> Nuevo | I25: =Parámetros!$B$29 -> Clásica | J25: Descripción: NAN Optipro 2 (presentada por Nestlé México como NAN 2 Optimal Pro) es una fórmula infantil en polvo para lactantes de 6 a 12 meses. Está elaborada con proteína de suero de leche OPTIPRO y enriquecida con HMO 2'FL, DHA, el probiótico Limosilactobacillus reuteri y hierro. Beneficios: - Contiene proteína de suero de leche desmineralizado OPTIPRO. - Incluye el oligosacárido de leche humana HMO 2'FL (2'-fucosilactosa) y DHA de aceite de pescado. - Contiene el probiótico Limosilactobacillus reuteri. - Fórmula adicionada con hierro, zinc, vitaminas A, C, D, E, K y del complejo B, y otros minerales. - Aporte por cada 100 kcal: 2 g de proteína, 4.8 g de grasa total y 12.2 g de carbohidratos. Ingredientes: Proteína de suero de leche de vaca desmineralizado OPTIPRO (26.84 %), lactosa, leche descremada, aceites vegetales (oleína de palma, palmiste, canola y maíz), citrato tricálcico, lecitina de soya, sales minerales, HMO (0.22 %) [2'-fucosilactosa], aceite de pescado (0.15 %) [DHA], cultivos probióticos de Limosilactobacillus reuteri (0.03 %), vitaminas y minerales. Contiene: leche, soya y aceite de pescado. Modo de uso: Indicada para lactantes de 6 a 12 meses. Prepárese siguiendo estrictamente las instrucciones de preparación y conservación de la etiqueta, con agua segura y utensilios limpios. Presentación: Lata con 400 g de fórmula en polvo. Advertencias: La leche materna es el mejor alimento para el bebé y debe continuarse el mayor tiempo posible. El uso de este producto debe hacerse bajo la orientación de un profesional de la salud. Contiene leche, soya y aceite de pescado. Una preparación o un almacenamiento incorrectos pueden ser perjudiciales para la salud del bebé. | K25: =Parámetros!$B$30 -> Mercado Envíos | L25: =IF(F25>=Parámetros!$B$7,"Envío gratis (obligatorio en Mercado Libre)",Parámetros!$B$31) -> Envío gratis (obligatorio en Mercado Libre) | M25: =Parámetros!$B$32 -> No acepto | N25: =Parámetros!$B$33 -> Sin garantía | O25: MLM16997453 | P25: Nan | Q25: Nestlé | R25: Optipro | S25: Etapa 2 | T25: Lata en polvo | U25: 400 | V25: g | W25: 1 | AA25: 6 a 12 meses | AC25: Sin sabor | AD25: Unisex | AG25: Etapa: 2; Con HMO: Sí; Con DHA: Sí; Con probióticos: Sí; Con hierro: Sí; Formato de venta: Unidad | AH25: https://raw.githubusercontent.com/zublimemx/marketplaces-product-images/main/products/7501058623195/images/7501058623195_1.jpg | AI25: https://raw.githubusercontent.com/zublimemx/marketplaces-product-images/main/products/7501058623195/images/7501058623195_2.jpg | AJ25: https://raw.githubusercontent.com/zublimemx/marketplaces-product-images/main/products/7501058623195/images/7501058623195_3.jpg | AN25: Farma + Mark | AO25: NAN 2 400 GR JUNIO 27 | AP25: Verificado
A26: 7501298223704 | B26: 7501298223704 | C26: Dolo-Neurobión Diclofenaco 50 mg Vitaminas B 20 Tabletas | D26: MLM457822 | E26: Salud y Equipamiento Médico > Cuidado de la Salud > Farmacia > Medicamentos de Venta Libre > Musculoarticulares Venta Libre | F26: =Precios!R26 -> 394 | G26: 879 | H26: =Parámetros!$B$28 -> Nuevo | I26: =Parámetros!$B$29 -> Clásica | J26: Descripción: Dolo-Neurobión es un medicamento en tabletas que combina diclofenaco sódico, un analgésico y antiinflamatorio no esteroideo, con las vitaminas del complejo B: tiamina (B1), piridoxina (B6) y cianocobalamina (B12). Está indicado para el alivio del dolor y la inflamación de músculos, articulaciones y fibras nerviosas del cuerpo. Se presenta en caja con 20 tabletas para administración por vía oral. Beneficios: - Triple acción: analgésica, antiinflamatoria y sobre las fibras nerviosas del cuerpo. - Indicado en dolores provocados por golpes, torceduras y caídas, dolor de espalda baja y de cuello, y los causados por contracturas o mala postura. - Su combinación con vitaminas del complejo B está pensada para actuar tanto sobre el dolor y la inflamación como sobre las fibras nerviosas. Composición: Cada tableta contiene: diclofenaco sódico 50 mg, mononitrato de tiamina (vitamina B1) 50 mg, clorhidrato de piridoxina (vitamina B6) 50 mg, cianocobalamina (vitamina B12) 0.25 mg y excipiente cbp 1 tableta. Modo de uso: Vía oral. Tome la tableta con un poco de agua, de preferencia con alimentos. La dosis y la duración del tratamiento son las que indique su médico o el inserto del empaque; no exceda la dosis recomendada. Presentación: Caja con 20 tabletas. Advertencias: No lo use si es alérgico al diclofenaco, a la aspirina o a otros antiinflamatorios no esteroideos, ni si tiene úlcera o sangrado del estómago o del intestino. Puede causar molestias gástricas, náusea, mareo o dolor de cabeza. No se use durante el embarazo ni la lactancia salvo indicación médica. Precaución en personas con enfermedad del corazón, del hígado o del riñón, o con hipertensión. Lea las instrucciones del empaque. Consulte a su médico. No se deje al alcance de los niños. | K26: =Parámetros!$B$30 -> Mercado Envíos | L26: =IF(F26>=Parámetros!$B$7,"Envío gratis (obligatorio en Mercado Libre)",Parámetros!$B$31) -> Envío gratis (obligatorio en Mercado Libre) | M26: =Parámetros!$B$32 -> No acepto | N26: =Parámetros!$B$33 -> Sin garantía | O26: MLM40172144 | P26: Dolo-Neurobión | Q26: Merck (P&G Health) | R26: Neurobión | S26: Tabletas | T26: Tabletas | U26: 20 | V26: tabletas | W26: 20 | X26: Diclofenaco sódico, tiamina (B1), piridoxina (B6) y cianocobalamina (B12) | Y26: Diclofenaco 50 mg; tiamina 50 mg; piridoxina 50 mg; cianocobalamina 0.25 mg por tableta | Z26: Oral | AG26: Uso: dolor e inflamación de músculos, articulaciones y fibras nerviosas; Formato de venta: Caja | AH26: https://raw.githubusercontent.com/zublimemx/marketplaces-product-images/main/products/7501298223704/images/7501298223704_1.jpg | AI26: https://raw.githubusercontent.com/zublimemx/marketplaces-product-images/main/products/7501298223704/images/7501298223704_3.jpg | AJ26: https://raw.githubusercontent.com/zublimemx/marketplaces-product-images/main/products/7501298223704/images/7501298223704_4.jpg | AK26: https://raw.githubusercontent.com/zublimemx/marketplaces-product-images/main/products/7501298223704/images/7501298223704_5.jpg | AN26: Farma | AO26: DOLO NEUROBION TAB C 20 | AP26: Verificado
A27: 7501943434622 | B27: 7501943434622 | C27: Pañales KleenBebé Suavelastic Etapa 2 Chico 40 Piezas | D27: MLM178488 | E27: Bebés > Higiene y Cuidado del Bebé > Pañales > Desechables | F27: =Precios!R27 -> 196 | G27: 390 | H27: =Parámetros!$B$28 -> Nuevo | I27: =Parámetros!$B$29 -> Clásica | J27: Descripción: Los pañales KleenBebé Suavelastic Max Etapa 2 (Chico), de Kimberly-Clark, están diseñados para ofrecer más sequedad, cuidado y ajuste al bebé. Su versión unisex está pensada para bebés de 5 a 7.5 kg. Características: - Maxi sequedad: tecnología Blockgel 4D que ayuda a mantener al bebé seco por más tiempo. - Maxi cuidado: mayor suavidad gracias a la fórmula Vitta E Plus, con óxido de zinc para ayudar a proteger la piel. - Maxi ajuste: 4 puntos de sujeción para que el pañal no se cuelgue ni se deforme. - Bolsita en la parte trasera que ayuda a evitar escurrimientos cuando el bebé está acostado. - Cuentan con certificación dermatológica. Modo de uso: Abra el pañal y colóquelo debajo del bebé, con la parte delantera hacia arriba, y sujete las cintas a la altura de la cintura sin apretar en exceso. Cámbielo con frecuencia, en cuanto esté húmedo o sucio. Presentación: Paquete con 40 pañales desechables Etapa 2 (Chico). Advertencias: Deseche el pañal usado en la basura, no en el inodoro. Mantenga el empaque plástico fuera del alcance de los niños. Verifique que la etapa corresponda al peso de su bebé. | K27: =Parámetros!$B$30 -> Mercado Envíos | L27: =IF(F27>=Parámetros!$B$7,"Envío gratis (obligatorio en Mercado Libre)",Parámetros!$B$31) -> A cargo del comprador | M27: =Parámetros!$B$32 -> No acepto | N27: =Parámetros!$B$33 -> Sin garantía | O27: MLM36084341 | P27: KleenBebé | Q27: Kimberly-Clark de México | R27: Suavelastic | S27: Max Etapa 2 Chico | T27: Pañales desechables | U27: 40 | V27: piezas | W27: 40 | AA27: Etapa 2 | AB27: Chico | AD27: Unisex | AG27: Peso del bebé: 5 a 7.5 kg; Con óxido de zinc: Sí; Formato de venta: Paquete; Con gel superabsorbente: Sí; Hipoalergénico: Sí; Libre de látex: Sí; Libre de parabenos: Sí; Sin fragancia | AH27: https://raw.githubusercontent.com/zublimemx/marketplaces-product-images/main/products/7501943434622/images/7501943434622_5.jpg | AI27: https://raw.githubusercontent.com/zublimemx/marketplaces-product-images/main/products/7501943434622/images/7501943434622_6.jpg | AN27: Mark | AO27: SUAVE CH E2 C/40 | AP27: Verificado
A28: 7501943444928 | B28: 7501943444928 | C28: Pañales KleenBebé Suavelastic Etapa 3 Mediano 44 Piezas | D28: MLM178488 | E28: Bebés > Higiene y Cuidado del Bebé > Pañales > Desechables | F28: =Precios!R28 -> 278 | G28: 432 | H28: =Parámetros!$B$28 -> Nuevo | I28: =Parámetros!$B$29 -> Clásica | J28: Descripción: Los pañales KleenBebé Suavelastic Max Etapa 3 (Mediano), de Kimberly-Clark, están diseñados para ofrecer más sequedad, cuidado y ajuste al bebé. Su versión unisex está pensada para bebés de 7 a 10 kg. Características: - Maxi sequedad: tecnología Blockgel 4D que ayuda a mantener al bebé seco por más tiempo. - Maxi cuidado: mayor suavidad gracias a la fórmula Vitta E Plus, con óxido de zinc para ayudar a proteger la piel. - Maxi ajuste: 4 puntos de sujeción para que el pañal no se cuelgue ni se deforme. - Bolsita en la parte trasera que ayuda a evitar escurrimientos cuando el bebé está acostado. - Cuentan con certificación dermatológica. Modo de uso: Abra el pañal y colóquelo debajo del bebé, con la parte delantera hacia arriba, y sujete las cintas a la altura de la cintura sin apretar en exceso. Cámbielo con frecuencia, en cuanto esté húmedo o sucio. Presentación: Paquete con 44 pañales desechables Etapa 3 (Mediano). Advertencias: Deseche el pañal usado en la basura, no en el inodoro. Mantenga el empaque plástico fuera del alcance de los niños. Verifique que la etapa corresponda al peso de su bebé. | K28: =Parámetros!$B$30 -> Mercado Envíos | L28: =IF(F28>=Parámetros!$B$7,"Envío gratis (obligatorio en Mercado Libre)",Parámetros!$B$31) -> A cargo del comprador | M28: =Parámetros!$B$32 -> No acepto | N28: =Parámetros!$B$33 -> Sin garantía | O28: MLM58935014 | P28: KleenBebé | Q28: Kimberly-Clark de México | R28: Suavelastic | S28: Max Etapa 3 Mediano | T28: Pañales desechables | U28: 44 | V28: piezas | W28: 44 | AA28: Etapa 3 | AB28: Mediano | AD28: Unisex | AG28: Peso del bebé: 7 a 10 kg; Con óxido de zinc: Sí; Formato de venta: Paquete; Con indicador de humedad: Sí; Con gel superabsorbente: Sí; Hipoalergénico: Sí; Libre de látex: Sí; Libre de parabenos: Sí; Sin fragancia | AH28: https://raw.githubusercontent.com/zublimemx/marketplaces-product-images/main/products/7501943444928/images/7501943444928_1.jpg | AI28: https://raw.githubusercontent.com/zublimemx/marketplaces-product-images/main/products/7501943444928/images/7501943444928_2.jpg | AJ28: https://raw.githubusercontent.com/zublimemx/marketplaces-product-images/main/products/7501943444928/images/7501943444928_3.jpg | AN28: Mark | AO28: SUAVE MED E3 C/44 | AP28: Verificado
A29: 7501287630926 | B29: 7501287630926 | C29: Terramicina Oxitetraciclina 500 mg 16 Cápsulas | D29: MLM457823 | E29: Salud y Equipamiento Médico > Cuidado de la Salud > Farmacia > Medicamentos de Venta Libre > Antiinfecciosos Venta Libre | F29: =Precios!R29 -> 403 | G29: 0 | H29: =Parámetros!$B$28 -> Nuevo | I29: =Parámetros!$B$29 -> Clásica | J29: Descripción: Terramicina, de Pfizer, es un antibiótico de amplio espectro del grupo de las tetraciclinas cuyo principio activo es la oxitetraciclina. Cada cápsula contiene 500 mg y se administra por vía oral. La presentación es una caja con 16 cápsulas. Beneficios: - Antibiótico indicado en infecciones causadas por microorganismos sensibles, siempre con indicación médica. - Su ficha para el médico incluye infecciones por rickettsias (como la fiebre manchada de las Montañas Rocallosas y el tifo), infecciones respiratorias por Mycoplasma pneumoniae, tracoma, cólera, brucelosis, así como infecciones respiratorias, urinarias y de piel y tejidos blandos por bacterias sensibles. - En tratamientos prolongados se emplea también en acné vulgar y rosácea, bajo supervisión médica. Composición: Cada cápsula contiene clorhidrato de oxitetraciclina equivalente a 500 mg de oxitetraciclina y excipiente cbp 1 cápsula. Modo de uso: Vía oral. La dosis, la frecuencia y la duración del tratamiento las determina el médico; complete el tratamiento aunque los síntomas mejoren. Trague las cápsulas con un vaso de agua y evite tomarlas junto con leche, lácteos, antiácidos o suplementos de hierro o calcio, porque pueden disminuir su absorción. Presentación: Caja con 16 cápsulas. Advertencias: Su venta requiere receta médica. No lo use si es alérgico a las tetraciclinas. Las tetraciclinas pueden manchar los dientes en desarrollo, por lo que no se recomiendan durante el embarazo, la lactancia ni en niños menores de 8 años salvo indicación médica. Puede causar molestias gastrointestinales y aumentar la sensibilidad de la piel al sol. Precaución en insuficiencia del hígado o del riñón. El uso de antibióticos sin indicación médica favorece la resistencia bacteriana. Lea las instrucciones del empaque. Consulte a su médico. No se deje al alcance de los niños. | K29: =Parámetros!$B$30 -> Mercado Envíos | L29: =IF(F29>=Parámetros!$B$7,"Envío gratis (obligatorio en Mercado Libre)",Parámetros!$B$31) -> Envío gratis (obligatorio en Mercado Libre) | M29: =Parámetros!$B$32 -> No acepto | N29: =Parámetros!$B$33 -> Sin garantía | O29: MLM39473982 | P29: Terramicina | Q29: Pfizer | S29: 500 mg | T29: Cápsulas | U29: 16 | V29: cápsulas | W29: 16 | X29: Oxitetraciclina | Y29: 500 mg | Z29: Oral | AG29: Grupo: tetraciclinas; Venta con receta médica; Formato de venta: Caja | AH29: https://raw.githubusercontent.com/zublimemx/marketplaces-product-images/main/products/7501287630926/images/7501287630926_2.jpg | AI29: https://raw.githubusercontent.com/zublimemx/marketplaces-product-images/main/products/7501287630926/images/7501287630926_1.jpg | AN29: Farma | AO29: TERRAMICINA CAP C16 AGOSTO 27 112 | AP29: Verificado
A30: 7506425604388 | B30: 7506425604388 | C30: Pañales Huggies UltraConfort Niña Etapa 6 40 Piezas | D30: MLM178488 | E30: Bebés > Higiene y Cuidado del Bebé > Pañales > Desechables | F30: =Precios!R30 -> 454.9 | G30: 235 | H30: =Parámetros!$B$28 -> Nuevo | I30: =Parámetros!$B$29 -> Clásica | J30: Descripción: Los pañales Huggies UltraConfort Niña Etapa 6, de Kimberly-Clark, combinan un corte anatómico de mayor cobertura con un material ultra flexible que se adapta mejor al cuerpo de la bebé. Están pensados para niñas de más de 13.5 kg y cuentan con núcleo absorbente reforzado ubicado al centro. Características: - Nuevo corte con mayor cobertura y material ultra flexible que se adapta al cuerpo. - Cintas Confort Flex en forma de V con 4 puntos de sujeción y cintura elástica más suave y flexible. - Núcleo absorbente reforzado, central para niñas. - Cubierta interna con poros ultra absorbentes. - Indicador de humedad e indicador de cambio de etapa. - Probados dermatológicamente, con certificación Dermatest. Modo de uso: Abra el pañal y colóquelo debajo del bebé, con la parte delantera hacia arriba, y sujete las cintas a la altura de la cintura sin apretar en exceso. Cámbielo con frecuencia, en cuanto esté húmedo o sucio. Presentación: Paquete con 40 pañales desechables Etapa 6 para niña. Advertencias: Deseche el pañal usado en la basura, no en el inodoro. Mantenga el empaque plástico fuera del alcance de los niños. Verifique que la etapa corresponda al peso de su bebé. | K30: =Parámetros!$B$30 -> Mercado Envíos | L30: =IF(F30>=Parámetros!$B$7,"Envío gratis (obligatorio en Mercado Libre)",Parámetros!$B$31) -> Envío gratis (obligatorio en Mercado Libre) | M30: =Parámetros!$B$32 -> No acepto | N30: =Parámetros!$B$33 -> Sin garantía | O30: MLM17379871 | P30: Huggies | Q30: Kimberly-Clark de México | R30: UltraConfort | S30: Niña Etapa 6 | T30: Pañales desechables | U30: 40 | V30: piezas | W30: 40 | AA30: Etapa 6 | AB30: XXG | AD30: Niñas | AG30: Peso del bebé: más de 13.5 kg; Indicador de humedad: Sí; Dermatest: Sí; Formato de venta: Paquete; Protección de hasta 12 h; Con gel superabsorbente: Sí; Libre de látex: Sí; Libre de parabenos: Sí | AH30: https://raw.githubusercontent.com/zublimemx/marketplaces-product-images/main/products/7506425604388/images/7506425604388_1.jpg | AI30: https://raw.githubusercontent.com/zublimemx/marketplaces-product-images/main/products/7506425604388/images/7506425604388_2.jpg | AN30: Mark | AO30: HU CONF NINA E6 C40 | AP30: Verificado
A31: 5000174305449 | B31: 5000174305449 | C31: Fixodent Original Crema Adhesiva para Dentadura 40 ml | D31: MLM180914 | E31: Belleza y Cuidado Personal > Higiene Personal > Cuidado Bucal > Otros | F31: =Precios!R31 -> 214 | G31: 1300 | H31: =Parámetros!$B$28 -> Nuevo | I31: =Parámetros!$B$29 -> Clásica | J31: Descripción: Fixodent Original es una crema adhesiva para dentaduras postizas que ayuda a mantener la prótesis firme en su lugar. Está pensada para quienes desean comer, beber, reír y hablar con confianza durante el día. Se presenta en tubo de 40 ml (47 g). Beneficios: - Fijación fuerte, justa y duradera para todo el día. - Ayuda a que la dentadura tenga mayor estabilidad al masticar y al hablar. - Tubo con boquilla para una aplicación controlada. Ingredientes: Copolímero PVM/MA de calcio y zinc y goma celulosa, con excipientes. Modo de uso: - Limpie y seque bien la dentadura antes de aplicar el producto. - Aplique unas tiras delgadas o puntos de crema sobre la superficie que toca la encía; no use cantidad excesiva. - Coloque la dentadura en la boca y presione firmemente durante unos segundos. - Al terminar el día, retire la dentadura y límpiela con cuidado, eliminando los restos de crema. Presentación: Tubo con 40 ml (47 g) de crema adhesiva. Advertencias: Si la dentadura no ajusta bien, o si aparece irritación, dolor o llagas en las encías, suspenda su uso y consulte a su dentista. No aplique en exceso. Este producto no sustituye la revisión periódica con el dentista. Mantenga fuera del alcance de los niños. | K31: =Parámetros!$B$30 -> Mercado Envíos | L31: =IF(F31>=Parámetros!$B$7,"Envío gratis (obligatorio en Mercado Libre)",Parámetros!$B$31) -> A cargo del comprador | M31: =Parámetros!$B$32 -> No acepto | N31: =Parámetros!$B$33 -> Sin garantía | O31: MLM19531168 | P31: Fixodent | Q31: Procter & Gamble | R31: Fixodent | S31: Original | T31: Crema adhesiva | U31: 40 | V31: ml | W31: 1 | AG31: Peso neto: 47 g; Uso: adhesivo para dentadura postiza; Ingredientes principales: copolímero PVM/MA de calcio y zinc, goma celulosa; Formato de venta: Unidad | AH31: https://raw.githubusercontent.com/zublimemx/marketplaces-product-images/main/products/5000174305449/images/5000174305449_1.jpg | AI31: https://raw.githubusercontent.com/zublimemx/marketplaces-product-images/main/products/5000174305449/images/5000174305449_2.jpg | AN31: Farma | AO31: FIXODENT ORG 40ML ADH DENT | AP31: Verificado
A32: 736085413359 | B32: 736085413359 | C32: Lagricel PF Hialuronato de Sodio 4 mg/ml Gotas 10 ml | D32: MLM457824 | E32: Salud y Equipamiento Médico > Cuidado de la Salud > Farmacia > Medicamentos de Venta Libre > Para Ojos y Oídos Venta Libre | F32: =Precios!R32 -> 522 | G32: 212 | H32: =Parámetros!$B$28 -> Nuevo | I32: =Parámetros!$B$29 -> Clásica | J32: Descripción: Lagricel PF, de Laboratorios Sophia, es una solución oftálmica lubricante que contiene hialuronato de sodio a 4 mg/ml. Es un producto libre de conservadores y se presenta en caja con frasco gotero de 10 ml para aplicación en el ojo. Beneficios: - Lubrica y humecta el ojo en alteraciones del tejido lagrimal por evaporación excesiva de las lágrimas, conocidas como ojo seco. - Ayuda a aliviar la irritación y la sequedad ocular provocadas por factores ambientales como polen, polvo, resplandor, contaminación y uso de monitores de computadora. - Contribuye a proteger la superficie ocular durante los procesos de reparación del epitelio de la córnea. - Fórmula sin conservadores. Composición: Cada ml contiene hialuronato de sodio 4 mg y vehículo cbp 1 ml. Modo de uso: Vía oftálmica; no ingerible. La dosis es la que indique su médico; consulte el instructivo anexo. Lávese las manos antes de aplicar, evite tocar el ojo o los párpados con la punta del gotero y cierre bien el frasco después de cada uso. Presentación: Caja con frasco gotero de 10 ml. Advertencias: Uso externo oftálmico. No se use durante el embarazo o la lactancia sin indicación médica. Suspenda su uso y consulte a su médico si presenta hipersensibilidad, enrojecimiento o dolor en el ojo. Conserve el frasco bien cerrado a no más de 30 °C. Lea las instrucciones del empaque. Consulte a su médico. No se deje al alcance de los niños. | K32: =Parámetros!$B$30 -> Mercado Envíos | L32: =IF(F32>=Parámetros!$B$7,"Envío gratis (obligatorio en Mercado Libre)",Parámetros!$B$31) -> Envío gratis (obligatorio en Mercado Libre) | M32: =Parámetros!$B$32 -> No acepto | N32: =Parámetros!$B$33 -> Sin garantía | O32: MLM47537482 | P32: Lagricel | Q32: Laboratorios Sophia | R32: Lagricel PF | S32: PF (libre de conservadores) | T32: Solución oftálmica (gotas) | U32: 10 | V32: ml | W32: 1 | X32: Hialuronato de sodio | Y32: 4 mg/ml | Z32: Oftálmica | AF32: 0208C99 SSA | AG32: Producto libre de conservadores; Frasco gotero; Formato de venta: Caja | AH32: https://raw.githubusercontent.com/zublimemx/marketplaces-product-images/main/products/736085413359/images/736085413359_1.jpg | AI32: https://raw.githubusercontent.com/zublimemx/marketplaces-product-images/main/products/736085413359/images/736085413359_2.jpg | AJ32: https://raw.githubusercontent.com/zublimemx/marketplaces-product-images/main/products/736085413359/images/736085413359_3.jpg | AN32: Farma | AO32: LAGRICEL PF OFT 4MG ML SOL 10ML | AP32: Verificado
A33: 7506425604340 | B33: 7506425604340 | C33: Pañales Huggies UltraConfort Niña Etapa 5 40 Piezas | D33: MLM178488 | E33: Bebés > Higiene y Cuidado del Bebé > Pañales > Desechables | F33: =Precios!R33 -> 478 | G33: 305 | H33: =Parámetros!$B$28 -> Nuevo | I33: =Parámetros!$B$29 -> Clásica | J33: Descripción: Los pañales Huggies UltraConfort Niña Etapa 5, de Kimberly-Clark, combinan un corte anatómico de mayor cobertura con un material ultra flexible que se adapta mejor al cuerpo de la bebé. Cuentan con núcleo absorbente reforzado ubicado al centro, pensado para niñas. Características: - Nuevo corte con mayor cobertura y material ultra flexible que se adapta al cuerpo. - Cintas Confort Flex en forma de V con 4 puntos de sujeción y cintura elástica más suave y flexible. - Núcleo absorbente reforzado, central para niñas. - Cubierta interna con poros ultra absorbentes. - Indicador de humedad e indicador de cambio de etapa. - Probados dermatológicamente, con certificación Dermatest. Modo de uso: Abra el pañal y colóquelo debajo del bebé, con la parte delantera hacia arriba, y sujete las cintas a la altura de la cintura sin apretar en exceso. Cámbielo con frecuencia, en cuanto esté húmedo o sucio. Presentación: Paquete con 40 pañales desechables Etapa 5 para niña. Advertencias: Deseche el pañal usado en la basura, no en el inodoro. Mantenga el empaque plástico fuera del alcance de los niños. Verifique que la etapa corresponda al peso de su bebé. | K33: =Parámetros!$B$30 -> Mercado Envíos | L33: =IF(F33>=Parámetros!$B$7,"Envío gratis (obligatorio en Mercado Libre)",Parámetros!$B$31) -> Envío gratis (obligatorio en Mercado Libre) | M33: =Parámetros!$B$32 -> No acepto | N33: =Parámetros!$B$33 -> Sin garantía | O33: MLM17379866 | P33: Huggies | Q33: Kimberly-Clark de México | R33: UltraConfort | S33: Niña Etapa 5 | T33: Pañales desechables | U33: 40 | V33: piezas | W33: 40 | AA33: Etapa 5 | AB33: XG | AD33: Niñas | AG33: Indicador de humedad: Sí; Dermatest: Sí; Formato de venta: Paquete; Peso del bebé: 11 a 14.5 kg; Protección de hasta 12 h; Con gel superabsorbente: Sí; Hipoalergénico: Sí; Libre de látex: Sí; Libre de parabenos: Sí; Sin fragancia | AH33: https://raw.githubusercontent.com/zublimemx/marketplaces-product-images/main/products/7506425604340/images/7506425604340_1.jpg | AI33: https://raw.githubusercontent.com/zublimemx/marketplaces-product-images/main/products/7506425604340/images/7506425604340_2.jpg | AN33: Mark | AO33: HU CONF NINA E5 C40 | AP33: Verificado
A34: 3662042003059 | B34: 3662042003059 | C34: Thealoz Duo Trehalosa 3% Hialuronato 0.15% Gotas 10 ml | D34: MLM457824 | E34: Salud y Equipamiento Médico > Cuidado de la Salud > Farmacia > Medicamentos de Venta Libre > Para Ojos y Oídos Venta Libre | F34: =Precios!R34 -> 829 | G34: 295 | H34: =Parámetros!$B$28 -> Nuevo | I34: =Parámetros!$B$29 -> Clásica | J34: Descripción: Thealoz Duo, de Laboratorios Théa, es una solución oftálmica estéril, sin conservadores, que combina trehalosa al 3% e hialuronato de sodio al 0.15%. Funciona como lágrima artificial para proteger, hidratar y lubricar la superficie del ojo, y puede usarse con lentes de contacto. Se presenta en frasco de 10 ml. Beneficios: - Indicado en caso de molestia, escozor o irritación del ojo causados por factores externos como viento, humo, contaminación, polvo, sol o frío, calefacción, aire acondicionado, viajes en avión o trabajo prolongado frente a una computadora. - La trehalosa aporta protección e hidratación; el hialuronato de sodio ayuda a retener agua y a lubricar la superficie corneal. - Fórmula sin conservadores, con envase multidosis ABAK que filtra el producto al dispensar cada gota. - Se puede usar con lentes de contacto puestas. Composición: Cada 100 ml contiene trehalosa 3 g e hialuronato de sodio 0.15 g. Excipientes: cloruro de sodio, trometamol, ácido clorhídrico y agua para inyectables. Modo de uso: Vía oftálmica. Lávese las manos antes de usarlo y evite que la punta del envase toque el ojo o los párpados. Tire suavemente del párpado inferior hacia abajo, mire hacia arriba e instile 1 gota en cada ojo, de 4 a 6 veces al día o según indicación de su médico. Cierre el envase después de cada uso. Si usa otro producto para los ojos, deje pasar al menos 10 minutos entre uno y otro. Presentación: Frasco multidosis de 10 ml. Advertencias: No lo use si es alérgico a alguno de sus componentes. No permita que la punta del envase toque el ojo. No inyectar ni ingerir. No lo use si el anillo de seguridad está dañado. Respete el tiempo máximo de uso después de abierto indicado en el empaque y conserve a menos de 25 °C. Lea las instrucciones del empaque. Consulte a su médico. No se deje al alcance de los niños. | K34: =Parámetros!$B$30 -> Mercado Envíos | L34: =IF(F34>=Parámetros!$B$7,"Envío gratis (obligatorio en Mercado Libre)",Parámetros!$B$31) -> Envío gratis (obligatorio en Mercado Libre) | M34: =Parámetros!$B$32 -> No acepto | N34: =Parámetros!$B$33 -> Sin garantía | O34: MLM50964112 | P34: Thealoz | Q34: Théa | R34: Thealoz Duo | S34: Trehalosa 3% e hialuronato 0.15% | T34: Solución oftálmica (gotas) | U34: 10 | V34: ml | W34: 1 | X34: Trehalosa e hialuronato de sodio | Y34: Trehalosa 3 %; hialuronato de sodio 0.15 % | Z34: Oftálmica | AG34: Sin conservadores; Envase multidosis ABAK; Compatible con lentes de contacto; Formato de venta: Caja | AH34: https://raw.githubusercontent.com/zublimemx/marketplaces-product-images/main/products/3662042003059/images/3662042003059_2.jpg | AI34: https://raw.githubusercontent.com/zublimemx/marketplaces-product-images/main/products/3662042003059/images/3662042003059_1.jpg | AJ34: https://raw.githubusercontent.com/zublimemx/marketplaces-product-images/main/products/3662042003059/images/3662042003059_4.jpg | AN34: Farma | AO34: THEALOZ DUO 10ML TREALOSA 3 HIALURONATO 0 15 AGOSTO 27 | AP34: Verificado
A35: 7501058623294 | B35: 7501058623294 | C35: Fórmula Infantil Nan Optipro 3 Lata 800 g | D35: MLM189058 | E35: Bebés > Comida para Bebés > Leche para Bebés | F35: =Precios!R35 -> 391 | G35: 472 | H35: =Parámetros!$B$28 -> Nuevo | I35: =Parámetros!$B$29 -> Clásica | J35: Descripción: NAN Optipro 3 (presentada por Nestlé México como NAN 3 Optimal Pro) es una fórmula en polvo para niños a partir de 1 año de edad. Está elaborada con proteína de suero de leche Optipro y contiene HMO 2'FL, DHA y el probiótico Limosilactobacillus reuteri. Beneficios: - Combinación de HMO, proteína Optipro y probiótico que, según el fabricante, puede ayudar a promover una buena digestión. - Contiene DHA de aceite de pescado. - Con vitaminas A, B1, B2, B3, B5, B6, B9, B12, C, D3, E y K1, y minerales como calcio, fósforo, hierro, magnesio, zinc, potasio, yodo, cobre, selenio y manganeso. - Aporte por cada 100 kcal: 2.5 g de proteínas, 4.34 g de grasas totales, 12.7 g de hidratos de carbono, 90.2 mg de calcio y 7.17 mg de DHA. Ingredientes: Proteína de suero de leche desmineralizado Optipro, leche descremada, maltodextrina, aceites vegetales, citrato de calcio, lactosa, lecitina de soya, fosfato de potasio, aceite de pescado (DHA 0.24 %), HMO 2'-O-fucosil lactosa (0.18 %), cultivos probióticos de Limosilactobacillus reuteri (0.04 %), vitaminas, minerales y otros componentes nutritivos. Contiene: leche, soya y aceite de pescado. Modo de uso: Indicada a partir de 1 año de edad. Prepárese siguiendo estrictamente las instrucciones de preparación y conservación de la etiqueta, con agua segura y utensilios limpios. Presentación: Lata con 800 g de fórmula en polvo. Advertencias: Contiene leche, soya y aceite de pescado. El uso de este producto debe hacerse bajo la orientación de un profesional de la salud. Una preparación o un almacenamiento incorrectos pueden ser perjudiciales para la salud. | K35: =Parámetros!$B$30 -> Mercado Envíos | L35: =IF(F35>=Parámetros!$B$7,"Envío gratis (obligatorio en Mercado Libre)",Parámetros!$B$31) -> Envío gratis (obligatorio en Mercado Libre) | M35: =Parámetros!$B$32 -> No acepto | N35: =Parámetros!$B$33 -> Sin garantía | O35: MLM14562941 | P35: Nan | Q35: Nestlé | R35: Optipro | S35: Etapa 3 | T35: Lata en polvo | U35: 800 | V35: g | W35: 1 | AA35: De 1 a 3 años | AD35: Unisex | AG35: Etapa: 3; Con HMO: Sí; Con DHA: Sí; Con probióticos: Sí; Formato de venta: Unidad; Contiene lactosa: Sí; Conservación a temperatura ambiente | AH35: https://raw.githubusercontent.com/zublimemx/marketplaces-product-images/main/products/7501058623294/images/7501058623294_3.jpg | AI35: https://raw.githubusercontent.com/zublimemx/marketplaces-product-images/main/products/7501058623294/images/7501058623294_1.jpg | AJ35: https://raw.githubusercontent.com/zublimemx/marketplaces-product-images/main/products/7501058623294/images/7501058623294_2.jpg | AN35: Farma + Mark | AO35: NAN 3 800G OPTIMAL PRO 12 AGOSTO 27 | AP35: Verificado
A36: 7501065008473 | B36: 7501065008473 | C36: Theraflu Resfriado Severo Sabor Limón 10 Sobres | D36: MLM194695 | E36: Salud y Equipamiento Médico > Cuidado de la Salud > Farmacia > Medicamentos de Venta Libre > Antigripales | F36: =Precios!R36 -> 236 | G36: 1872 | H36: =Parámetros!$B$28 -> Nuevo | I36: =Parámetros!$B$29 -> Clásica | J36: Descripción: Theraflu Resfriado Severo en sobres, sabor limón, es un té instantáneo para preparar con agua caliente, que ayuda a aliviar los síntomas del resfriado y la gripe: congestión nasal, dolor de garganta, dolor de cabeza, dolores musculares y fiebre. Se presenta en caja con 10 sobres. Beneficios: - Alivio de varios síntomas del resfriado y la gripe en una sola preparación. - Se toma caliente, en forma de té, fácil de preparar en casa o en el trabajo. - Sabor limón. Modo de uso: Vía oral. Disuelva el contenido de un sobre en una taza de agua caliente, mezcle bien y tome la bebida mientras esté tibia. Respete la dosis y el intervalo indicados en el empaque y no exceda la dosis recomendada. Presentación: Caja con 10 sobres. Advertencias: No se use en el embarazo ni en la lactancia. No exceder la dosis recomendada. No usar en niños menores de 12 años. Si los síntomas persisten por más de unos días o se acompañan de fiebre alta, suspenda su uso y consulte a su médico. Lea las instrucciones del empaque. Consulte a su médico. No se deje al alcance de los niños. | K36: =Parámetros!$B$30 -> Mercado Envíos | L36: =IF(F36>=Parámetros!$B$7,"Envío gratis (obligatorio en Mercado Libre)",Parámetros!$B$31) -> A cargo del comprador | M36: =Parámetros!$B$32 -> No acepto | N36: =Parámetros!$B$33 -> Sin garantía | O36: MLM58916395 | P36: Theraflu | Q36: Haleon | S36: Resfriado Severo | T36: Sobres (polvo para preparar bebida caliente) | U36: 10 | V36: sobres | W36: 10 | X36: Paracetamol / Maleato de feniramina / Clorhidrato de fenilefrina | Y36: 650 mg / 20 mg / 10 mg | Z36: Oral | AA36: Adultos y niños mayores de 12 años | AC36: Limón | AF36: 318M94 SSA VI | AG36: Formato de venta: Caja | AH36: https://raw.githubusercontent.com/zublimemx/marketplaces-product-images/main/products/7501065008473/images/7501065008473_1.jpg | AI36: https://raw.githubusercontent.com/zublimemx/marketplaces-product-images/main/products/7501065008473/images/7501065008473_2.jpg | AJ36: https://raw.githubusercontent.com/zublimemx/marketplaces-product-images/main/products/7501065008473/images/7501065008473_3.jpg | AN36: Farma | AO36: THERAFLU VERDE C10 SBS RESFRIADO SEVERO | AP36: Verificado
A37: 7501249606778 | B37: 7501249606778 | C37: Postday Levonorgestrel 1.5 mg 1 Comprimido | D37: MLM457813 | E37: Salud y Equipamiento Médico > Cuidado de la Salud > Farmacia > Medicamentos de Venta Libre > Hormonales Venta Libre | F37: =Precios!R37 -> 96 | G37: 2411 | H37: =Parámetros!$B$28 -> Nuevo | I37: =Parámetros!$B$29 -> Clásica | J37: Descripción: Postday es un anticonceptivo de emergencia en comprimido de dosis única que contiene 1.5 mg de levonorgestrel. Está indicado para prevenir un embarazo no deseado después de una relación sexual sin protección o cuando falla el método anticonceptivo utilizado. Se presenta en caja con 1 comprimido para administración por vía oral. Beneficios: - Su principio activo, el levonorgestrel, actúa principalmente inhibiendo o retrasando la ovulación. - Dosis única: un solo comprimido de 1.5 mg. - Es más efectivo cuanto antes se toma después de la relación sexual, de preferencia dentro de las primeras 72 horas, aunque puede utilizarse hasta 120 horas (5 días) después; su eficacia disminuye con el paso del tiempo. Composición: Cada comprimido contiene 1.5 mg de levonorgestrel y excipientes. Modo de uso: Vía oral. Tome 1 comprimido en una sola dosis, lo antes posible después de la relación sexual sin protección. No debe usarse como método anticonceptivo regular y no protege contra infecciones de transmisión sexual. Presentación: Caja con 1 comprimido de 1.5 mg. Advertencias: No lo use si es alérgica al levonorgestrel o a alguno de los componentes, si está embarazada o sospecha estarlo, ni si presenta hemorragia vaginal de origen desconocido. Consulte a un médico si la menstruación no se presenta dentro de las tres semanas posteriores a la toma. Precaución en mujeres con antecedentes de trombosis, hipertensión, diabetes o enfermedades del hígado. No se recomienda en menores de 16 años sin asesoría médica. Conserve a temperatura ambiente, entre 15 y 30 °C, protegido de la luz y la humedad. Lea las instrucciones del empaque. Consulte a su médico. No se deje al alcance de los niños. | K37: =Parámetros!$B$30 -> Mercado Envíos | L37: =IF(F37>=Parámetros!$B$7,"Envío gratis (obligatorio en Mercado Libre)",Parámetros!$B$31) -> A cargo del comprador | M37: =Parámetros!$B$32 -> No acepto | N37: =Parámetros!$B$33 -> Sin garantía | O37: MLM39455911 | P37: Postday | Q37: IFA Celtics | T37: Comprimido | U37: 1 | V37: comprimido | W37: 1 | X37: Levonorgestrel | Y37: 1.5 mg | Z37: Oral | AD37: Mujer | AG37: Anticonceptivo de emergencia de dosis única; Formato de venta: Caja | AH37: https://raw.githubusercontent.com/zublimemx/marketplaces-product-images/main/products/7501249606778/images/7501249606778_2.jpg | AI37: https://raw.githubusercontent.com/zublimemx/marketplaces-product-images/main/products/7501249606778/images/7501249606778_1.jpg | AN37: Farma | AO37: POSTDAY 1 CPR | AP37: Verificado
A38: 4015630981977 | B38: 4015630981977 | C38: Tiras Reactivas Accu-Chek Performa 50 Piezas | D38: MLM189948 | E38: Salud y Equipamiento Médico > Equipamiento Médico > Equipos de Monitoreo > Medidores de Glucosa | F38: =Precios!R38 -> 419 | G38: 285 | H38: =Parámetros!$B$28 -> Nuevo | I38: =Parámetros!$B$29 -> Clásica | J38: Descripción: Tiras reactivas Accu-Chek Performa, de Roche, para medir la glucosa en sangre capilar con el medidor Accu-Chek Performa (el medidor no está incluido). Están diseñadas para una aplicación fácil y para obtener el resultado con una sola gota de sangre. Características: - Ventana de aplicación en forma de Y que facilita colocar la gota de sangre. - Requieren solo 0.6 µl de sangre, equivalente a una gota. - Resultado en aproximadamente 5 segundos. - Método enzimático electroquímico. - No requieren codificación. - Cuentan con 6 electrodos dorados para mejorar la conducción. - Se mantienen estables hasta la fecha de caducidad, incluso después de abrir el tubo, mientras se conserve bien cerrado. Modo de uso: 1. Inserte la tira en el medidor Accu-Chek Performa. 2. Puncione el dedo con un dispositivo de punción (no incluido). 3. Acerque la gota de sangre a la ventana de la tira. 4. Lea el resultado en la pantalla del medidor. Presentación: Envase con 50 tiras reactivas. Advertencias: Use las tiras únicamente con el medidor compatible. Cierre bien el envase después de retirar cada tira para conservar su calidad y no las use después de la fecha de caducidad. Consulte el manual del medidor y a su médico para interpretar los resultados. Mantenga fuera del alcance de los niños. | K38: =Parámetros!$B$30 -> Mercado Envíos | L38: =IF(F38>=Parámetros!$B$7,"Envío gratis (obligatorio en Mercado Libre)",Parámetros!$B$31) -> Envío gratis (obligatorio en Mercado Libre) | M38: =Parámetros!$B$32 -> No acepto | N38: =Parámetros!$B$33 -> Sin garantía | O38: MLM69334459 | P38: Accu-Chek | Q38: Roche | R38: Performa | S38: Tiras reactivas de glucosa | T38: Tiras reactivas | U38: 50 | V38: tiras | W38: 50 | AA38: Adultos | AF38: 1445R2014 SSA | AG38: Compatible con: medidor Accu-Chek Performa; Volumen de muestra: 0.6 µl; Tiempo de resultado: 5 segundos; Requiere codificación: No; Tecnología: Enzimática electroquímica; Formato de venta: Caja; Modelo: 06454011 | AH38: https://raw.githubusercontent.com/zublimemx/marketplaces-product-images/main/products/4015630981977/images/4015630981977_2.jpg | AI38: https://raw.githubusercontent.com/zublimemx/marketplaces-product-images/main/products/4015630981977/images/4015630981977_3.jpg | AJ38: https://raw.githubusercontent.com/zublimemx/marketplaces-product-images/main/products/4015630981977/images/4015630981977_4.jpg | AK38: https://raw.githubusercontent.com/zublimemx/marketplaces-product-images/main/products/4015630981977/images/4015630981977_5.jpg | AN38: Farma | AO38: ACCU CHEK C 50 TIRAS PERFORMA | AP38: Verificado
A39: 7501008498880 | B39: 7501008498880 | C39: Flanax 550 mg Naproxeno Sódico 30 Tabletas | D39: MLM194673 | E39: Salud y Equipamiento Médico > Cuidado de la Salud > Farmacia > Medicamentos de Venta Libre > Analgésicos | F39: =Precios!R39 -> 463 | G39: 273 | H39: =Parámetros!$B$28 -> Nuevo | I39: =Parámetros!$B$29 -> Clásica | J39: Descripción: Flanax 550 mg, de Bayer, es un medicamento en tabletas cuyo principio activo es el naproxeno sódico, un antiinflamatorio no esteroideo con acción analgésica. Se presenta en caja con 30 tabletas para administración por vía oral. Beneficios: - Alivio del dolor y la inflamación. - Se utiliza en dolores de espalda y contracturas musculares, dolor muscular, lesiones deportivas, dolores articulares y molestias menstruales. - Tabletas de 550 mg en presentación de 30 piezas. Composición: Cada tableta contiene naproxeno sódico 550 mg. Modo de uso: Vía oral. Tome la tableta con un vaso de agua, de preferencia con alimentos, y respete la dosis y la duración indicadas en el empaque o por su médico. No exceda la dosis recomendada. Presentación: Caja con 30 tabletas de 550 mg. Advertencias: No lo use si es alérgico al naproxeno, a la aspirina o a otros antiinflamatorios no esteroideos, ni si tiene úlcera o sangrado del estómago o del intestino. Puede causar molestias gástricas, náusea, mareo o dolor de cabeza. Evite su uso durante el embarazo y la lactancia, salvo indicación médica. Precaución en personas con hipertensión o con enfermedad del corazón, del hígado o del riñón. Si persisten las molestias, consulte a su médico. Lea las instrucciones del empaque. Consulte a su médico. No se deje al alcance de los niños. | K39: =Parámetros!$B$30 -> Mercado Envíos | L39: =IF(F39>=Parámetros!$B$7,"Envío gratis (obligatorio en Mercado Libre)",Parámetros!$B$31) -> Envío gratis (obligatorio en Mercado Libre) | M39: =Parámetros!$B$32 -> No acepto | N39: =Parámetros!$B$33 -> Sin garantía | O39: MLM39455468 | P39: Flanax | Q39: Bayer | S39: 550 mg | T39: Tabletas | U39: 30 | V39: tabletas | W39: 30 | X39: Naproxeno sódico | Y39: 550 mg | Z39: Oral | AA39: Adultos | AF39: 006M90 SSA | AG39: Formato de venta: Caja | AH39: https://raw.githubusercontent.com/zublimemx/marketplaces-product-images/main/products/7501008498880/images/7501008498880_2.jpg | AI39: https://raw.githubusercontent.com/zublimemx/marketplaces-product-images/main/products/7501008498880/images/7501008498880_1.jpg | AN39: Farma | AO39: FLANAX 550 C30TAB | AP39: Verificado
A40: 7501943474895 | B40: 7501943474895 | C40: Pañales para Adulto Diapro Gel Predoblados Unitalla 10 Pzas | D40: MLM194512 | E40: Salud y Equipamiento Médico > Cuidado de la Salud > Protección para Incontinencia > Pañales para Adultos | F40: =Precios!R40 -> 163 | G40: 288 | H40: =Parámetros!$B$28 -> Nuevo | I40: =Parámetros!$B$29 -> Clásica | J40: Descripción: Diapro Gel Predoblado es un pañal desechable para adulto de talla única, diseñado para dar protección confiable contra la incontinencia. Su núcleo con gel gelatiniza los líquidos y ayuda a mantener la piel seca. Se vende en paquete con 10 pañales predoblados. Características: - Unitalla: un solo tamaño para adultos. - Con gel que gelatiniza los líquidos para una mejor absorción. - Rombos que distribuyen los líquidos de manera uniforme. - Cubierta suave tipo tela y respirable. - Con aloe y manzanilla, que ayudan a cuidar la piel. - Odorlock, tecnología que ayuda a controlar los olores. - Cintas adhesivas para sujetarlo al cuerpo y ajustarlo cómodamente. - Formato predoblado, listo para usar. Modo de uso: Abra el pañal, colóquelo entre las piernas y ajuste las cintas adhesivas a la cintura hasta lograr un ajuste cómodo y seguro. Cámbielo cuando esté húmedo o sucio para mantener la piel limpia y seca. Presentación: Paquete con 10 pañales desechables predoblados con gel, talla unitalla. Advertencias: Producto de un solo uso. Deséchelo en la basura, no en el inodoro. Mantenga fuera del alcance de los niños. Si aparece irritación en la piel, suspenda su uso y consulte a su médico. | K40: =Parámetros!$B$30 -> Mercado Envíos | L40: =IF(F40>=Parámetros!$B$7,"Envío gratis (obligatorio en Mercado Libre)",Parámetros!$B$31) -> A cargo del comprador | M40: =Parámetros!$B$32 -> No acepto | N40: =Parámetros!$B$33 -> Sin garantía | O40: MLM19543669 | P40: Diapro | Q40: Kimberly-Clark | R40: Diapro Gel | S40: Predoblado | T40: Pañal desechable predoblado con gel | U40: 10 | V40: piezas | W40: 10 | AA40: Adultos | AB40: Unitalla | AG40: Con aloe y manzanilla; Odorlock para control de olores; Cubierta tipo tela respirable; Cintas adhesivas; Formato de venta: Paquete | AH40: https://raw.githubusercontent.com/zublimemx/marketplaces-product-images/main/products/7501943474895/images/7501943474895_1.jpg | AI40: https://raw.githubusercontent.com/zublimemx/marketplaces-product-images/main/products/7501943474895/images/7501943474895_2.jpg | AN40: Mark | AO40: DIAPRO PRED GEL ADC-10 | AP40: Verificado
A41: 7509546054032 | B41: 7509546054032 | C41: Crema Dental Colgate Luminous White Brilliant 22 ml | D41: MLM168075 | E41: Belleza y Cuidado Personal > Higiene Personal > Cuidado Bucal > Pastas Dentales | F41: =Precios!R41 -> 68.5 | G41: 867 | H41: =Parámetros!$B$28 -> Nuevo | I41: =Parámetros!$B$29 -> Clásica | J41: Descripción: Colgate Luminous White Brilliant es una crema dental anticaries con flúor de sabor Brilliant Mint, formulada para ayudar a eliminar manchas y lograr una sonrisa más blanca. Se presenta en tubo de 22 ml, práctico para llevar en el bolso, la mochila o de viaje. Beneficios: - Crema dental anticaries con flúor para el cuidado diario de los dientes. - Ayuda a evitar la formación de manchas amarillas ocasionadas por hábitos como el café, el té o el tabaco. - Su etiqueta promete una sonrisa más blanca en 1 semana con el uso regular. - Aliento fresco con sabor Brilliant Mint. - Tamaño de 22 ml, ideal para viaje. Modo de uso: Aplique una cantidad de crema dental del tamaño de un chícharo sobre el cepillo y cepille todos los dientes durante al menos dos minutos. Úsela después de cada comida, hasta tres veces al día, o siguiendo la recomendación de su odontólogo. Escupa el exceso y enjuáguese la boca. Presentación: Tubo con 22 ml de crema dental. Hecho en México. Advertencias: Para niños menores de 6 años, use solo una cantidad mínima y supervise el cepillado para evitar que traguen la crema dental. Si se ingiere más de la cantidad usada para cepillarse, busque ayuda médica. Mantenga fuera del alcance de los niños. | K41: =Parámetros!$B$30 -> Mercado Envíos | L41: =IF(F41>=Parámetros!$B$7,"Envío gratis (obligatorio en Mercado Libre)",Parámetros!$B$31) -> A cargo del comprador | M41: =Parámetros!$B$32 -> No acepto | N41: =Parámetros!$B$33 -> Sin garantía | O41: MLM21635965 | P41: Colgate | Q41: Colgate-Palmolive | R41: Luminous White | S41: Brilliant | T41: Crema dental | U41: 22 | V41: ml | W41: 1 | AC41: Menta (Brilliant Mint) | AG41: Anticaries con flúor; Industria mexicana; Formato de venta: Unidad | AH41: https://raw.githubusercontent.com/zublimemx/marketplaces-product-images/main/products/7509546054032/images/7509546054032_2.jpg | AI41: https://raw.githubusercontent.com/zublimemx/marketplaces-product-images/main/products/7509546054032/images/7509546054032_3.jpg | AN41: Mark | AO41: C D COLGATE LUMINOUS WHITE22 | AP41: Verificado
A42: 7506425604326 | B42: 7506425604326 | C42: Pañales Huggies UltraConfort Niño Etapa 5 40 Piezas | D42: MLM178488 | E42: Bebés > Higiene y Cuidado del Bebé > Pañales > Desechables | F42: =Precios!R42 -> 478 | G42: 98 | H42: =Parámetros!$B$28 -> Nuevo | I42: =Parámetros!$B$29 -> Clásica | J42: Descripción: Los pañales Huggies UltraConfort Niño Etapa 5, de Kimberly-Clark, combinan un corte anatómico de mayor cobertura con un material ultra flexible que se adapta mejor al cuerpo del bebé. Cuentan con núcleo absorbente reforzado ubicado en la parte delantera, pensado para niños. Características: - Nuevo corte con mayor cobertura y material ultra flexible que se adapta al cuerpo. - Cintas Confort Flex en forma de V con 4 puntos de sujeción y cintura elástica más suave y flexible. - Núcleo absorbente reforzado, frontal para niños. - Cubierta interna con poros ultra absorbentes. - Indicador de humedad e indicador de cambio de etapa. - Probados dermatológicamente, con certificación Dermatest. Modo de uso: Abra el pañal y colóquelo debajo del bebé, con la parte delantera hacia arriba, y sujete las cintas a la altura de la cintura sin apretar en exceso. Cámbielo con frecuencia, en cuanto esté húmedo o sucio. Presentación: Paquete con 40 pañales desechables Etapa 5 para niño. Advertencias: Deseche el pañal usado en la basura, no en el inodoro. Mantenga el empaque plástico fuera del alcance de los niños. Verifique que la etapa corresponda al peso de su bebé. | K42: =Parámetros!$B$30 -> Mercado Envíos | L42: =IF(F42>=Parámetros!$B$7,"Envío gratis (obligatorio en Mercado Libre)",Parámetros!$B$31) -> Envío gratis (obligatorio en Mercado Libre) | M42: =Parámetros!$B$32 -> No acepto | N42: =Parámetros!$B$33 -> Sin garantía | O42: MLM17379849 | P42: Huggies | Q42: Kimberly-Clark de México | R42: UltraConfort | S42: Niño Etapa 5 | T42: Pañales desechables | U42: 40 | V42: piezas | W42: 40 | AA42: Etapa 5 | AB42: XG | AD42: Niños | AG42: Indicador de humedad: Sí; Dermatest: Sí; Formato de venta: Paquete; Peso del bebé: 11 a 14.5 kg; Protección de hasta 12 h; Con gel superabsorbente: Sí; Hipoalergénico: Sí; Libre de látex: Sí; Libre de parabenos: Sí; Sin fragancia | AH42: https://raw.githubusercontent.com/zublimemx/marketplaces-product-images/main/products/7506425604326/images/7506425604326_1.jpg | AI42: https://raw.githubusercontent.com/zublimemx/marketplaces-product-images/main/products/7506425604326/images/7506425604326_2.jpg | AN42: Mark | AO42: HU CONF NINO E5 C40 | AP42: Verificado
A43: 7501471800265 | B43: 7501471800265 | C43: Panclasa 80 mg/80 mg Antiespasmódico 20 Cápsulas | D43: MLM457821 | E43: Salud y Equipamiento Médico > Cuidado de la Salud > Farmacia > Medicamentos de Venta Libre > Digestivos Venta Libre | F43: =Precios!R43 -> 431 | G43: 586 | H43: =Parámetros!$B$28 -> Nuevo | I43: =Parámetros!$B$29 -> Clásica | J43: Descripción: Panclasa es un antiespasmódico a base de floroglucinol y trimetilfloroglucinol, en cápsulas de 80 mg/80 mg. Está indicado para el dolor de estómago, la colitis y los cólicos producidos por diarrea y los cólicos menstruales. Se presenta en caja con 20 cápsulas para administración por vía oral. Beneficios: - Actúa relajando el músculo liso, lo que ayuda a eliminar el espasmo y combatir la inflamación. - Según el fabricante, su acción inicia entre 5 y 10 minutos después de tomarlo y el efecto puede mantenerse por varias horas. - Indicado para dolor de estómago, colitis y cólicos por diarrea o menstruales. Composición: Cada cápsula contiene floroglucinol 80 mg y trimetilfloroglucinol 80 mg. Modo de uso: Vía oral. Adolescentes y adultos: de 1 a 2 cápsulas cada 8 horas, sin exceder 6 cápsulas al día, o según lo indique su médico. Si las molestias persisten, consulte a su médico. Presentación: Caja con 20 cápsulas. Advertencias: No se use en embarazo ni lactancia. No lo use si es alérgico a alguno de los componentes de la fórmula. Ocasionalmente pueden presentarse náuseas o vómito. Consérvese a no más de 30 °C. Si los síntomas persisten, suspenda su uso y consulte a su médico. Lea las instrucciones del empaque. Consulte a su médico. No se deje al alcance de los niños. | K43: =Parámetros!$B$30 -> Mercado Envíos | L43: =IF(F43>=Parámetros!$B$7,"Envío gratis (obligatorio en Mercado Libre)",Parámetros!$B$31) -> Envío gratis (obligatorio en Mercado Libre) | M43: =Parámetros!$B$32 -> No acepto | N43: =Parámetros!$B$33 -> Sin garantía | O43: MLM40170397 | P43: Panclasa | Q43: Bausch Health (Atlantis) | T43: Cápsulas | U43: 20 | V43: cápsulas | W43: 20 | X43: Floroglucinol y trimetilfloroglucinol | Y43: 80 mg / 80 mg por cápsula | Z43: Oral | AA43: Adolescentes y adultos | AG43: Antiespasmódico; Formato de venta: Caja | AH43: https://raw.githubusercontent.com/zublimemx/marketplaces-product-images/main/products/7501471800265/images/7501471800265_2.jpg | AI43: https://raw.githubusercontent.com/zublimemx/marketplaces-product-images/main/products/7501471800265/images/7501471800265_1.jpg | AN43: Farma | AO43: PANCLASA C/20 CAPS FLOROGLUCINO L TRIMETILFLOROGLUCINOL | AP43: Verificado
A44: 4015630067084 | B44: 4015630067084 | C44: Tiras Reactivas Accu-Chek Instant 50 Piezas | D44: MLM189948 | E44: Salud y Equipamiento Médico > Equipamiento Médico > Equipos de Monitoreo > Medidores de Glucosa | F44: =Precios!R44 -> 367 | G44: 158 | H44: =Parámetros!$B$28 -> Nuevo | I44: =Parámetros!$B$29 -> Clásica | J44: Descripción: Tiras reactivas Accu-Chek Instant, de Roche, para medir la glucosa en sangre capilar con el medidor Accu-Chek Instant (el medidor no está incluido). Cuentan con un borde amplio que facilita tomar la muestra y con tecnología de rápida absorción. Características: - Borde amplio para facilitar la toma de la muestra y tecnología de rápida absorción. - Requieren solo 0.6 µl de sangre, equivalente a una gota. - Resultado en aproximadamente 4 segundos después de aplicar la muestra. - Método enzimático electroquímico, que ayuda a disminuir interferencias. - Se mantienen estables hasta la fecha de caducidad impresa en el tubo, incluso después de abierto, si se conservan entre 4 y 30 °C. Modo de uso: 1. Inserte la tira en el medidor Accu-Chek Instant. 2. Puncione el dedo con un dispositivo de punción (no incluido). 3. Acerque la gota de sangre al borde de la tira. 4. Lea el resultado en la pantalla del medidor. Presentación: Envase con 50 tiras reactivas. Advertencias: Use únicamente tiras reactivas Accu-Chek Instant con el medidor Accu-Chek Instant. Cierre bien el envase después de retirar cada tira y no las use después de la fecha de caducidad. Consulte el manual del medidor y a su médico para interpretar los resultados. Mantenga fuera del alcance de los niños. | K44: =Parámetros!$B$30 -> Mercado Envíos | L44: =IF(F44>=Parámetros!$B$7,"Envío gratis (obligatorio en Mercado Libre)",Parámetros!$B$31) -> Envío gratis (obligatorio en Mercado Libre) | M44: =Parámetros!$B$32 -> No acepto | N44: =Parámetros!$B$33 -> Sin garantía | P44: Accu-Chek | Q44: Roche | R44: Instant | S44: Tiras reactivas de glucosa | T44: Tiras reactivas | U44: 50 | V44: tiras | W44: 50 | AA44: Adultos | AF44: 2120R2017 SSA | AG44: Compatible con: medidor Accu-Chek Instant; Volumen de muestra: 0.6 µl; Tiempo de resultado: 4 segundos; Tecnología: Enzimática electroquímica; Formato de venta: Caja | AH44: https://raw.githubusercontent.com/zublimemx/marketplaces-product-images/main/products/4015630067084/images/4015630067084_3.jpg | AI44: https://raw.githubusercontent.com/zublimemx/marketplaces-product-images/main/products/4015630067084/images/4015630067084_4.jpg | AJ44: https://raw.githubusercontent.com/zublimemx/marketplaces-product-images/main/products/4015630067084/images/4015630067084_5.jpg | AN44: Farma | AO44: ACCU CHEK C50 TIRAS INSTANT | AP44: Verificado
A45: 7501298223711 | B45: 7501298223711 | C45: Dolo-Neurobión Diclofenaco 50 mg Vitaminas B 10 Tabletas | D45: MLM457822 | E45: Salud y Equipamiento Médico > Cuidado de la Salud > Farmacia > Medicamentos de Venta Libre > Musculoarticulares Venta Libre | F45: =Precios!R45 -> 239.57 | G45: 1783 | H45: =Parámetros!$B$28 -> Nuevo | I45: =Parámetros!$B$29 -> Clásica | J45: Descripción: Dolo-Neurobión es un medicamento en tabletas que combina diclofenaco sódico, un analgésico y antiinflamatorio no esteroideo, con las vitaminas del complejo B: tiamina (B1), piridoxina (B6) y cianocobalamina (B12). Está indicado para el alivio del dolor y la inflamación de músculos, articulaciones y fibras nerviosas del cuerpo. Se presenta en caja con 10 tabletas para administración por vía oral. Beneficios: - Triple acción: analgésica, antiinflamatoria y sobre las fibras nerviosas del cuerpo. - Indicado en dolores provocados por golpes, torceduras y caídas, dolor de espalda baja y de cuello, y los causados por contracturas o mala postura. - Su combinación con vitaminas del complejo B está pensada para actuar tanto sobre el dolor y la inflamación como sobre las fibras nerviosas. Composición: Cada tableta contiene: diclofenaco sódico 50 mg, mononitrato de tiamina (vitamina B1) 50 mg, clorhidrato de piridoxina (vitamina B6) 50 mg, cianocobalamina (vitamina B12) 0.25 mg y excipiente cbp 1 tableta. Modo de uso: Vía oral. Tome la tableta con un poco de agua, de preferencia con alimentos. La dosis y la duración del tratamiento son las que indique su médico o el inserto del empaque; no exceda la dosis recomendada. Presentación: Caja con 10 tabletas. Advertencias: No lo use si es alérgico al diclofenaco, a la aspirina o a otros antiinflamatorios no esteroideos, ni si tiene úlcera o sangrado del estómago o del intestino. Puede causar molestias gástricas, náusea, mareo o dolor de cabeza. No se use durante el embarazo ni la lactancia salvo indicación médica. Precaución en personas con enfermedad del corazón, del hígado o del riñón, o con hipertensión. Lea las instrucciones del empaque. Consulte a su médico. No se deje al alcance de los niños. | K45: =Parámetros!$B$30 -> Mercado Envíos | L45: =IF(F45>=Parámetros!$B$7,"Envío gratis (obligatorio en Mercado Libre)",Parámetros!$B$31) -> A cargo del comprador | M45: =Parámetros!$B$32 -> No acepto | N45: =Parámetros!$B$33 -> Sin garantía | O45: MLM40171448 | P45: Dolo-Neurobión | Q45: Merck (P&G Health) | R45: Neurobión | S45: Tabletas | T45: Tabletas | U45: 10 | V45: tabletas | W45: 10 | X45: Diclofenaco sódico, tiamina (B1), piridoxina (B6) y cianocobalamina (B12) | Y45: Diclofenaco 50 mg; tiamina 50 mg; piridoxina 50 mg; cianocobalamina 0.25 mg por tableta | Z45: Oral | AG45: Uso: dolor e inflamación de músculos, articulaciones y fibras nerviosas; Formato de venta: Caja | AH45: https://raw.githubusercontent.com/zublimemx/marketplaces-product-images/main/products/7501298223711/images/7501298223711_1.jpg | AI45: https://raw.githubusercontent.com/zublimemx/marketplaces-product-images/main/products/7501298223711/images/7501298223711_2.jpg | AJ45: https://raw.githubusercontent.com/zublimemx/marketplaces-product-images/main/products/7501298223711/images/7501298223711_3.jpg | AN45: Farma | AO45: DOLO NEUROBION TAB C 10 | AP45: Verificado
A46: 7501943498815 | B46: 7501943498815 | C46: Pañales KleenBebé Suavelastic Recién Nacido 40 Piezas | D46: MLM178488 | E46: Bebés > Higiene y Cuidado del Bebé > Pañales > Desechables | F46: =Precios!R46 -> 162 | G46: 477 | H46: =Parámetros!$B$28 -> Nuevo | I46: =Parámetros!$B$29 -> Clásica | J46: Descripción: Los pañales KleenBebé Suavelastic Max Etapa 1 (Recién Nacido), de Kimberly-Clark, están diseñados para ofrecer más sequedad, cuidado y ajuste al bebé desde los primeros días. Su versión unisex está pensada para bebés de 2.5 a 5.5 kg. Características: - Maxi sequedad: tecnología Blockgel 4D que ayuda a mantener al bebé seco por más tiempo. - Maxi cuidado: mayor suavidad gracias a la fórmula Vitta E Plus, con óxido de zinc para ayudar a proteger la piel. - Maxi ajuste: 4 puntos de sujeción para que el pañal no se cuelgue ni se deforme. - Bolsita en la parte trasera que ayuda a evitar escurrimientos cuando el bebé está acostado. - Cuentan con certificación dermatológica. Modo de uso: Abra el pañal y colóquelo debajo del bebé, con la parte delantera hacia arriba, y sujete las cintas a la altura de la cintura sin apretar en exceso. Cámbielo con frecuencia, en cuanto esté húmedo o sucio. Presentación: Paquete con 40 pañales desechables Etapa 1 (Recién Nacido). Advertencias: Deseche el pañal usado en la basura, no en el inodoro. Mantenga el empaque plástico fuera del alcance de los niños. Verifique que la etapa corresponda al peso de su bebé. | K46: =Parámetros!$B$30 -> Mercado Envíos | L46: =IF(F46>=Parámetros!$B$7,"Envío gratis (obligatorio en Mercado Libre)",Parámetros!$B$31) -> A cargo del comprador | M46: =Parámetros!$B$32 -> No acepto | N46: =Parámetros!$B$33 -> Sin garantía | O46: MLM38429330 | P46: KleenBebé | Q46: Kimberly-Clark de México | R46: Suavelastic | S46: Max Etapa 1 Recién Nacido | T46: Pañales desechables | U46: 40 | V46: piezas | W46: 40 | AA46: Etapa 1 | AB46: Recién Nacido | AD46: Unisex | AG46: Peso del bebé: 2.5 a 5.5 kg; Con óxido de zinc: Sí; Formato de venta: Paquete; Con gel superabsorbente: Sí; Con barreras reforzadas anti-derrames: Sí; Hipoalergénico: Sí; Libre de látex: Sí; Libre de parabenos: Sí | AH46: https://raw.githubusercontent.com/zublimemx/marketplaces-product-images/main/products/7501943498815/images/7501943498815_1.jpg | AI46: https://raw.githubusercontent.com/zublimemx/marketplaces-product-images/main/products/7501943498815/images/7501943498815_2.jpg | AN46: Mark | AO46: SUAVE R-N E1 C/40 | AP46: Verificado
A47: 3662042003240 | B47: 3662042003240 | C47: Hyabak Hialuronato de Sodio 0.15% Solución Oftálmica 10 ml | D47: MLM457824 | E47: Salud y Equipamiento Médico > Cuidado de la Salud > Farmacia > Medicamentos de Venta Libre > Para Ojos y Oídos Venta Libre | F47: =Precios!R47 -> 789 | G47: 100 | H47: =Parámetros!$B$28 -> Nuevo | I47: =Parámetros!$B$29 -> Clásica | J47: Descripción: Hyabak, de Laboratorios Théa, es una solución oftálmica sin conservadores con hialuronato de sodio al 0.15% para la hidratación y lubricación de los ojos y de las lentes de contacto. Se presenta en caja con frasco de 10 ml. Beneficios: - Lubricante y humectante ocular en alteraciones del tejido lagrimal por evaporación excesiva de las lágrimas, conocidas como ojo seco. - Ayuda a aliviar la irritación y la sequedad por factores ambientales como polen, polvo, resplandor, contaminación y uso de monitores de computadora. - Asegura la protección de la superficie ocular durante los procesos de reparación del epitelio de la córnea. - Sin conservadores; puede usarse con lentes de contacto. Composición: Cada ml contiene hialuronato de sodio 1.5 mg y vehículo cbp 1 ml. Modo de uso: Vía oftálmica. Aplique una gota en cada ojo, tantas veces como sea necesario. Para usuarios de lentes de contacto, aplique una gota en cada lente al ponerlo y/o al quitarlo. Evite tocar el ojo o los párpados con la punta del frasco. Presentación: Caja con frasco de 10 ml. Advertencias: No lo use si es alérgico a alguno de los componentes de la fórmula. Una vez abierto el frasco, no lo conserve por más de 8 semanas. Consérvese a temperatura no mayor a 25 °C. Si la molestia persiste, consulte a su médico. Lea las instrucciones del empaque. Consulte a su médico. No se deje al alcance de los niños. | K47: =Parámetros!$B$30 -> Mercado Envíos | L47: =IF(F47>=Parámetros!$B$7,"Envío gratis (obligatorio en Mercado Libre)",Parámetros!$B$31) -> Envío gratis (obligatorio en Mercado Libre) | M47: =Parámetros!$B$32 -> No acepto | N47: =Parámetros!$B$33 -> Sin garantía | O47: MLM50963712 | P47: Hyabak | Q47: Théa | T47: Solución oftálmica (gotas) | U47: 10 | V47: ml | W47: 1 | X47: Hialuronato de sodio | Y47: 0.15 % (1.5 mg/ml) | Z47: Oftálmica | AG47: Sin conservadores; Apto para lentes de contacto; Una vez abierto no conservar más de 8 semanas; Formato de venta: Caja | AH47: https://raw.githubusercontent.com/zublimemx/marketplaces-product-images/main/products/3662042003240/images/3662042003240_1.jpg | AI47: https://raw.githubusercontent.com/zublimemx/marketplaces-product-images/main/products/3662042003240/images/3662042003240_2.jpg | AJ47: https://raw.githubusercontent.com/zublimemx/marketplaces-product-images/main/products/3662042003240/images/3662042003240_3.jpg | AN47: Farma | AO47: HYABAK 0 15 SOL OFT 10ML | AP47: Verificado
A48: 7506425604302 | B48: 7506425604302 | C48: Pañales Huggies UltraConfort Niña Etapa 4 40 Piezas | D48: MLM178488 | E48: Bebés > Higiene y Cuidado del Bebé > Pañales > Desechables | F48: =Precios!R48 -> 457 | G48: 201 | H48: =Parámetros!$B$28 -> Nuevo | I48: =Parámetros!$B$29 -> Clásica | J48: Descripción: Los pañales Huggies UltraConfort Niña Etapa 4, de Kimberly-Clark, combinan un corte anatómico de mayor cobertura con un material ultra flexible que se adapta mejor al cuerpo de la bebé. Cuentan con núcleo absorbente reforzado ubicado al centro, pensado para niñas. Características: - Nuevo corte con mayor cobertura y material ultra flexible que se adapta al cuerpo. - Cintas Confort Flex en forma de V con 4 puntos de sujeción y cintura elástica más suave y flexible. - Núcleo absorbente reforzado, central para niñas. - Cubierta interna con poros ultra absorbentes. - Indicador de humedad e indicador de cambio de etapa. - Probados dermatológicamente, con certificación Dermatest. Modo de uso: Abra el pañal y colóquelo debajo del bebé, con la parte delantera hacia arriba, y sujete las cintas a la altura de la cintura sin apretar en exceso. Cámbielo con frecuencia, en cuanto esté húmedo o sucio. Presentación: Paquete con 40 pañales desechables Etapa 4 para niña. Advertencias: Deseche el pañal usado en la basura, no en el inodoro. Mantenga el empaque plástico fuera del alcance de los niños. Verifique que la etapa corresponda al peso de su bebé. | K48: =Parámetros!$B$30 -> Mercado Envíos | L48: =IF(F48>=Parámetros!$B$7,"Envío gratis (obligatorio en Mercado Libre)",Parámetros!$B$31) -> Envío gratis (obligatorio en Mercado Libre) | M48: =Parámetros!$B$32 -> No acepto | N48: =Parámetros!$B$33 -> Sin garantía | O48: MLM17379869 | P48: Huggies | Q48: Kimberly-Clark de México | R48: UltraConfort | S48: Niña Etapa 4 | T48: Pañales desechables | U48: 40 | V48: piezas | W48: 40 | AA48: Etapa 4 | AB48: Grande (G) | AD48: Niñas | AG48: Indicador de humedad: Sí; Dermatest: Sí; Formato de venta: Paquete; Peso del bebé: 9 a 12 kg; Con gel superabsorbente: Sí; Libre de látex: Sí | AH48: https://raw.githubusercontent.com/zublimemx/marketplaces-product-images/main/products/7506425604302/images/7506425604302_1.jpg | AI48: https://raw.githubusercontent.com/zublimemx/marketplaces-product-images/main/products/7506425604302/images/7506425604302_2.jpg | AJ48: https://raw.githubusercontent.com/zublimemx/marketplaces-product-images/main/products/7506425604302/images/7506425604302_3.jpg | AN48: Mark | AO48: HU CONF NINA E4 C40 | AP48: Verificado
A49: 7501034630124 | B49: 7501034630124 | C49: Jardianz Duo 12.5 mg/850 mg 60 Tabletas | D49: MLM457821 | E49: Salud y Equipamiento Médico > Cuidado de la Salud > Farmacia > Medicamentos de Venta Libre > Digestivos Venta Libre | F49: =Precios!R49 -> 2119 | G49: 0 | H49: =Parámetros!$B$28 -> Nuevo | I49: =Parámetros!$B$29 -> Clásica | J49: Descripción: Jardianz Duo 12.5 mg/850 mg es un medicamento de Boehringer Ingelheim que combina en una sola tableta dos antidiabéticos orales: empagliflozina, un inhibidor del cotransportador sodio-glucosa 2 (SGLT2), y metformina, una biguanida. Se presenta en caja con 60 tabletas. Beneficios: - Indicado en adultos con diabetes mellitus tipo 2 como complemento de la dieta y el ejercicio para el control de la glucosa en sangre, cuando el tratamiento con ambos principios activos es apropiado. - Dos mecanismos de acción complementarios en una sola tableta. - Presentación de 60 tabletas para un mes de tratamiento con dos tomas al día, según indicación médica. Composición: Cada tableta contiene empagliflozina 12.5 mg y clorhidrato de metformina 850 mg. Modo de uso: Vía oral. Tome las tabletas enteras con agua y con los alimentos, en la frecuencia indicada por su médico. La dosis y los ajustes (por ejemplo, según la función renal) deben ser determinados por el médico. Presentación: Caja con 60 tabletas. Advertencias: Su venta requiere receta médica. No debe usarse en diabetes tipo 1, cetoacidosis diabética, enfermedad renal grave o diálisis, ni en caso de hipersensibilidad a sus componentes. La metformina puede causar acidosis láctica, una complicación poco frecuente pero grave; evite el consumo excesivo de alcohol. Pueden presentarse infecciones urinarias y genitales, deshidratación y molestias gastrointestinales; con insulina o sulfonilureas aumenta el riesgo de hipoglucemia. Consulte a su médico antes de un estudio con medio de contraste o una cirugía. Evite su uso durante el embarazo y la lactancia. Lea las instrucciones del empaque. Consulte a su médico. No se deje al alcance de los niños. | K49: =Parámetros!$B$30 -> Mercado Envíos | L49: =IF(F49>=Parámetros!$B$7,"Envío gratis (obligatorio en Mercado Libre)",Parámetros!$B$31) -> Envío gratis (obligatorio en Mercado Libre) | M49: =Parámetros!$B$32 -> No acepto | N49: =Parámetros!$B$33 -> Sin garantía | O49: MLM40169652 | P49: Jardianz | Q49: Boehringer Ingelheim | R49: Duo | S49: 12.5 mg/850 mg | T49: Tabletas | U49: 60 | V49: tabletas | W49: 60 | X49: Empagliflozina y clorhidrato de metformina | Y49: Empagliflozina 12.5 mg / Clorhidrato de metformina 850 mg | Z49: Oral | AA49: Adultos | AF49: 432M2015 SSA | AG49: Venta con receta médica; Uso: Diabetes mellitus tipo 2; Formato de venta: Caja; Receta simple; Fracción IV | AH49: https://raw.githubusercontent.com/zublimemx/marketplaces-product-images/main/products/7501034630124/images/7501034630124_2.jpg | AI49: https://raw.githubusercontent.com/zublimemx/marketplaces-product-images/main/products/7501034630124/images/7501034630124_3.jpg | AJ49: https://raw.githubusercontent.com/zublimemx/marketplaces-product-images/main/products/7501034630124/images/7501034630124_4.jpg | AN49: Farma | AO49: JARDIANZ DUO 12 5 850MG TAB C60 | AP49: Verificado
A50: 7506425600007 | B50: 7506425600007 | C50: Pañales Huggies UltraConfort Unisex Recién Nacido 44 Piezas | D50: MLM178488 | E50: Bebés > Higiene y Cuidado del Bebé > Pañales > Desechables | F50: =Precios!R50 -> 192.12 | G50: 375 | H50: =Parámetros!$B$28 -> Nuevo | I50: =Parámetros!$B$29 -> Clásica | J50: Descripción: Los pañales Huggies UltraConfort Unisex Recién Nacido (Etapa 1), de Kimberly-Clark, combinan un corte anatómico de mayor cobertura con un material ultra flexible que se adapta mejor al cuerpo del bebé desde los primeros días de vida. Características: - Nuevo corte con mayor cobertura y material ultra flexible que se adapta al cuerpo. - Cintas Confort Flex en forma de V con 4 puntos de sujeción y cintura elástica más suave y flexible. - Núcleo absorbente reforzado. - Cubierta interna con poros ultra absorbentes. - Indicador de humedad e indicador de cambio de etapa. - Probados dermatológicamente, con certificación Dermatest. Modo de uso: Abra el pañal y colóquelo debajo del bebé, con la parte delantera hacia arriba, y sujete las cintas a la altura de la cintura sin apretar en exceso. Cámbielo con frecuencia, en cuanto esté húmedo o sucio. Presentación: Paquete con 44 pañales desechables Etapa 1 (Recién Nacido), unisex. Advertencias: Deseche el pañal usado en la basura, no en el inodoro. Mantenga el empaque plástico fuera del alcance de los niños. Verifique que la etapa corresponda al peso de su bebé. | K50: =Parámetros!$B$30 -> Mercado Envíos | L50: =IF(F50>=Parámetros!$B$7,"Envío gratis (obligatorio en Mercado Libre)",Parámetros!$B$31) -> A cargo del comprador | M50: =Parámetros!$B$32 -> No acepto | N50: =Parámetros!$B$33 -> Sin garantía | O50: MLM58752506 | P50: Huggies | Q50: Kimberly-Clark de México | R50: UltraConfort | S50: Unisex Recién Nacido Etapa 1 | T50: Pañales desechables | U50: 44 | V50: piezas | W50: 44 | AA50: Etapa 1 | AB50: Recién Nacido | AD50: Unisex | AG50: Indicador de humedad: Sí; Dermatest: Sí; Formato de venta: Paquete; Peso del bebé: 3 a 5.5 kg; Protección de hasta 12 h; Con barreras reforzadas anti-derrames: Sí; Con gel superabsorbente: Sí; Hipoalergénico: Sí; Libre de látex: Sí; Libre de parabenos: Sí; Sin fragancia | AH50: https://raw.githubusercontent.com/zublimemx/marketplaces-product-images/main/products/7506425600007/images/7506425600007_1.jpg | AI50: https://raw.githubusercontent.com/zublimemx/marketplaces-product-images/main/products/7506425600007/images/7506425600007_2.jpg | AN50: Mark | AO50: HU CONF UNI RN/E1 C44 | AP50: Verificado
A51: 7501300450210 | B51: 7501300450210 | C51: Bactrim F 800 mg/160 mg 15 Tabletas | D51: MLM457823 | E51: Salud y Equipamiento Médico > Cuidado de la Salud > Farmacia > Medicamentos de Venta Libre > Antiinfecciosos Venta Libre | F51: =Precios!R51 -> 477 | G51: 497 | H51: =Parámetros!$B$28 -> Nuevo | I51: =Parámetros!$B$29 -> Clásica | J51: Descripción: Bactrim F es un medicamento antibacteriano en tabletas que combina dos principios activos, sulfametoxazol y trimetoprima, en concentración de 800 mg/160 mg por tableta. Esta combinación actúa contra bacterias sensibles y se emplea en el tratamiento de infecciones bacterianas que el médico determine según el tipo de infección y la sensibilidad del microorganismo. La letra F identifica la presentación forte, con mayor contenido de principio activo por tableta. Composición: - Sulfametoxazol 800 mg - Trimetoprima 160 mg Cada tableta contiene los dos principios activos; consulte el empaque para conocer los excipientes. Modo de uso: Vía oral. La dosis, la frecuencia y la duración del tratamiento deben ser las que indique el médico. Se recomienda ingerir las tabletas con un vaso de agua y completar el tratamiento indicado aunque los síntomas mejoren, para evitar que las bacterias sobrevivan y se vuelvan resistentes. Presentación: Caja con 15 tabletas. Advertencias: - No lo use si es alérgico a las sulfonamidas, a la trimetoprima o a cualquiera de los componentes de la fórmula. - Informe a su médico si está embarazada o en periodo de lactancia, o si padece enfermedad del hígado o de los riñones. - Suspenda su uso y consulte a su médico si aparecen erupciones en la piel u otras reacciones inesperadas. - Su uso debe ser indicado y supervisado por un médico. Lea las instrucciones del empaque. Consulte a su médico. No se deje al alcance de los niños. | K51: =Parámetros!$B$30 -> Mercado Envíos | L51: =IF(F51>=Parámetros!$B$7,"Envío gratis (obligatorio en Mercado Libre)",Parámetros!$B$31) -> Envío gratis (obligatorio en Mercado Libre) | M51: =Parámetros!$B$32 -> No acepto | N51: =Parámetros!$B$33 -> Sin garantía | P51: Bactrim | S51: F (forte) 800 mg/160 mg | T51: Tabletas | U51: 15 | V51: tabletas | W51: 15 | X51: Sulfametoxazol / Trimetoprima | Y51: 800 mg/160 mg | Z51: Oral | AG51: Forma farmacéutica: Tabletas; Formato de venta: Unidad | AH51: https://raw.githubusercontent.com/zublimemx/marketplaces-product-images/main/products/7501300450210/images/7501300450210_2.jpg | AN51: Farma | AO51: BACTRIM F 800 160MG C15T 216 | AP51: Verificado
A52: 7501298221403 | B52: 7501298221403 | C52: Dolo-Neurobión Forte Diclofenaco y Vitaminas B 30 Tabletas | D52: MLM194673 | E52: Salud y Equipamiento Médico > Cuidado de la Salud > Farmacia > Medicamentos de Venta Libre > Analgésicos | F52: =Precios!R52 -> 684.99 | G52: 829 | H52: =Parámetros!$B$28 -> Nuevo | I52: =Parámetros!$B$29 -> Clásica | J52: Descripción: Dolo-Neurobión Forte es un medicamento en tabletas que combina un antiinflamatorio no esteroideo, el diclofenaco, con vitaminas del complejo B (B1, B6 y B12). Está formulado para el alivio del dolor de intensidad leve a moderada, como el dolor de cabeza, el dolor muscular y el dolor de espalda, y aporta vitaminas que participan en el funcionamiento del sistema nervioso y en la prevención de deficiencias del complejo B. Beneficios: - Combina un analgésico y antiinflamatorio con vitaminas B1, B6 y B12 en una sola tableta. - Pensado para dolores musculares, de espalda y de cabeza de leves a moderados. - Presentación de 30 tabletas para un tratamiento prolongado bajo indicación médica. Composición: - Diclofenaco - Vitamina B1 (tiamina) - Vitamina B6 (piridoxina) - Vitamina B12 (cianocobalamina) Consulte el empaque para conocer la concentración de cada componente. Modo de uso: Vía oral. Ingiera las tabletas con agua, de preferencia después de los alimentos, y siga la dosis que indique su médico o el instructivo del empaque. No exceda la dosis recomendada ni prolongue el tratamiento sin indicación médica. Presentación: Caja con 30 tabletas. Advertencias: - No lo use si es alérgico al diclofenaco, a la aspirina o a otros antiinflamatorios no esteroideos, ni si tiene úlcera del estómago activa. - Puede causar molestias gástricas; consulte a su médico si tiene antecedentes de problemas del estómago, del corazón, de los riñones o del hígado. - No lo use durante el embarazo ni la lactancia salvo indicación médica. Lea las instrucciones del empaque. Consulte a su médico. No se deje al alcance de los niños. | K52: =Parámetros!$B$30 -> Mercado Envíos | L52: =IF(F52>=Parámetros!$B$7,"Envío gratis (obligatorio en Mercado Libre)",Parámetros!$B$31) -> Envío gratis (obligatorio en Mercado Libre) | M52: =Parámetros!$B$32 -> No acepto | N52: =Parámetros!$B$33 -> Sin garantía | O52: MLM40172270 | P52: Dolo-Neurobión | Q52: Procter & Gamble | R52: Forte | T52: Tabletas | U52: 30 | V52: tabletas | W52: 30 | X52: Diclofenaco / Tiamina (B1) / Piridoxina (B6) / Cianocobalamina (B12) | Z52: Oral | AG52: Forma farmacéutica: Tabletas; Formato de venta: Unidad | AH52: https://raw.githubusercontent.com/zublimemx/marketplaces-product-images/main/products/7501298221403/images/7501298221403_1.jpg | AI52: https://raw.githubusercontent.com/zublimemx/marketplaces-product-images/main/products/7501298221403/images/7501298221403_2.jpg | AJ52: https://raw.githubusercontent.com/zublimemx/marketplaces-product-images/main/products/7501298221403/images/7501298221403_3.jpg | AN52: Farma | AO52: DOLO NEUROBION FTE 30GRAG | AP52: Verificado
A53: 7501008497340 | B53: 7501008497340 | C53: Flanax Naproxeno Sódico 550 mg 12 Tabletas | D53: MLM194673 | E53: Salud y Equipamiento Médico > Cuidado de la Salud > Farmacia > Medicamentos de Venta Libre > Analgésicos | F53: =Precios!R53 -> 253 | G53: 5585 | H53: =Parámetros!$B$28 -> Nuevo | I53: =Parámetros!$B$29 -> Clásica | J53: Descripción: Flanax 550 mg es un medicamento en tabletas cuyo principio activo es el naproxeno sódico, un antiinflamatorio no esteroideo con acción analgésica. Está indicado para el manejo del dolor y la inflamación, por ejemplo el dolor muscular, de espalda, cuello y hombros, así como la migraña, los cólicos menstruales (dismenorrea) y otros padecimientos dolorosos o inflamatorios como la artritis reumatoide, la gota y la espondilitis anquilosante. Beneficios: - Desinflama y alivia el dolor intenso muscular, de espalda, cuello y hombros. - Concentración de 550 mg por tableta. - Presentación práctica de 12 tabletas. Composición: Cada tableta contiene naproxeno sódico 550 mg. Modo de uso: Vía oral. Ingiera la tableta entera con un vaso de agua, de preferencia con alimentos. Tome la dosis que indique su médico o el instructivo del empaque y utilice la menor dosis efectiva durante el menor tiempo posible. Presentación: Caja con 12 tabletas. Conservar a temperatura ambiente controlada, entre 15 y 30 °C. Advertencias: - No lo use si es alérgico al naproxeno, a la aspirina o a otros antiinflamatorios no esteroideos. - Puede causar irritación o sangrado del estómago; consulte a su médico si tiene úlcera, gastritis o enfermedad del corazón, de los riñones o del hígado. - No lo use durante el embarazo, sobre todo en el último trimestre, ni en la lactancia sin indicación médica. - No exceda la dosis recomendada. Lea las instrucciones del empaque. Consulte a su médico. No se deje al alcance de los niños. | K53: =Parámetros!$B$30 -> Mercado Envíos | L53: =IF(F53>=Parámetros!$B$7,"Envío gratis (obligatorio en Mercado Libre)",Parámetros!$B$31) -> A cargo del comprador | M53: =Parámetros!$B$32 -> No acepto | N53: =Parámetros!$B$33 -> Sin garantía | O53: MLM47333646 | P53: Flanax | Q53: Bayer | S53: 550 mg | T53: Tabletas | U53: 12 | V53: tabletas | W53: 12 | X53: Naproxeno sódico | Y53: 550 mg | Z53: Oral | AF53: 006M90SSAVI | AG53: Forma farmacéutica: Tabletas; Formato de venta: Unidad | AH53: https://raw.githubusercontent.com/zublimemx/marketplaces-product-images/main/products/7501008497340/images/7501008497340_1.jpg | AI53: https://raw.githubusercontent.com/zublimemx/marketplaces-product-images/main/products/7501008497340/images/7501008497340_2.jpg | AJ53: https://raw.githubusercontent.com/zublimemx/marketplaces-product-images/main/products/7501008497340/images/7501008497340_3.jpg | AN53: Farma | AO53: FLANAX 550 C 12 TABS 162 | AP53: Verificado
A54: 7501159526029 | B54: 7501159526029 | C54: Eucaliptine Guayacol 100 mg 10 Ampolletas de 1 ml | D54: MLM457814 | E54: Salud y Equipamiento Médico > Cuidado de la Salud > Farmacia > Medicamentos de Venta Libre > Respiratorios Venta Libre | F54: =Precios!R54 -> 460 | G54: 257 | H54: =Parámetros!$B$28 -> Nuevo | I54: =Parámetros!$B$29 -> Clásica | J54: Descripción: Eucaliptine es una solución inyectable presentada en ampolletas de 1 ml, con guayacol como principio activo en concentración de 100 mg por ml. Se vende en caja con 10 ampolletas. Es un medicamento de uso inyectable que debe ser indicado por un médico y aplicado por personal de salud capacitado, de acuerdo con la indicación médica. Composición: Cada ampolleta de 1 ml contiene guayacol 100 mg. Consulte el empaque para conocer el resto de los componentes de la fórmula. Modo de uso: Vía inyectable. La dosis, la vía de aplicación y la duración del tratamiento deben ser las que indique el médico. La aplicación debe realizarla personal capacitado, con material estéril y desechable. Presentación: Caja con 10 ampolletas de 1 ml cada una. Advertencias: - No lo use si es alérgico a alguno de los componentes de la fórmula. - Informe a su médico si está embarazada o en periodo de lactancia. - Revise que la ampolleta esté íntegra y que la solución no presente partículas antes de aplicarla. - Consulte a su médico ante cualquier reacción inesperada. Lea las instrucciones del empaque. Consulte a su médico. No se deje al alcance de los niños. | K54: =Parámetros!$B$30 -> Mercado Envíos | L54: =IF(F54>=Parámetros!$B$7,"Envío gratis (obligatorio en Mercado Libre)",Parámetros!$B$31) -> Envío gratis (obligatorio en Mercado Libre) | M54: =Parámetros!$B$32 -> No acepto | N54: =Parámetros!$B$33 -> Sin garantía | O54: MLM47334148 | P54: Eucaliptine | Q54: Laboratorios Sanfer | T54: Solución inyectable en ampolletas | U54: 10 | V54: ampolletas | W54: 10 | X54: Guayacol | Y54: 100 mg/ml | Z54: Inyectable | AF54: 419M2001 SSA IV | AG54: Volumen por ampolleta: 1 ml; Formato de venta: Unidad; Hecho en México por Sanofi Aventis de México para Dinafarma; distribuido por Laboratorios Sanfer | AH54: https://raw.githubusercontent.com/zublimemx/marketplaces-product-images/main/products/7501159526029/images/7501159526029_1.jpg | AI54: https://raw.githubusercontent.com/zublimemx/marketplaces-product-images/main/products/7501159526029/images/7501159526029_2.jpg | AJ54: https://raw.githubusercontent.com/zublimemx/marketplaces-product-images/main/products/7501159526029/images/7501159526029_3.jpg | AN54: Farma | AO54: EUCALIPTINE AMP C 10 100MG DICIEMBRE 26 | AP54: Verificado
A55: 7501298217635 | B55: 7501298217635 | C55: Dolo-Neurobión Forte DC Inyectable Jeringa Prellenada 3 ml | D55: MLM457822 | E55: Salud y Equipamiento Médico > Cuidado de la Salud > Farmacia > Medicamentos de Venta Libre > Musculoarticulares Venta Libre | F55: =Precios!R55 -> 434 | G55: 1635 | H55: =Parámetros!$B$28 -> Nuevo | I55: =Parámetros!$B$29 -> Clásica | J55: Descripción: Dolo-Neurobión Forte DC es una solución inyectable en jeringa prellenada de 3 ml que combina diclofenaco, un antiinflamatorio no esteroideo, con vitaminas del complejo B (B1, B6 y B12). Se utiliza para aliviar distintos tipos de dolor, como dolor de cabeza, dolor muscular y dolor de espalda de intensidad leve a moderada, y las vitaminas contribuyen a la salud del sistema nervioso y a prevenir deficiencias del complejo B. La jeringa prellenada facilita la preparación de la dosis por parte del personal de salud. Beneficios: - Combina un antiinflamatorio con vitaminas B1, B6 y B12 en una sola aplicación. - Presentación en jeringa prellenada de 3 ml, lista para usarse. - Formato de una jeringa por caja. Composición: - Diclofenaco - Vitamina B1 (tiamina) - Vitamina B6 (piridoxina) - Vitamina B12 (cianocobalamina) Consulte el empaque para conocer la concentración exacta y el resto de los componentes. Modo de uso: Vía inyectable. Debe ser aplicada por personal de salud capacitado, conforme a la dosis y a la duración que indique el médico. No reutilice la jeringa. Presentación: Caja con 1 jeringa prellenada de 3 ml. Advertencias: - No lo use si es alérgico al diclofenaco, a la aspirina o a otros antiinflamatorios no esteroideos. - Consulte a su médico si tiene antecedentes de úlcera o sangrado del estómago, o enfermedad del corazón, de los riñones o del hígado. - No lo use durante el embarazo ni la lactancia salvo indicación médica. Lea las instrucciones del empaque. Consulte a su médico. No se deje al alcance de los niños. | K55: =Parámetros!$B$30 -> Mercado Envíos | L55: =IF(F55>=Parámetros!$B$7,"Envío gratis (obligatorio en Mercado Libre)",Parámetros!$B$31) -> Envío gratis (obligatorio en Mercado Libre) | M55: =Parámetros!$B$32 -> No acepto | N55: =Parámetros!$B$33 -> Sin garantía | O55: MLM40998724 | P55: Dolo-Neurobión | Q55: Procter & Gamble | R55: Forte | S55: DC | T55: Solución inyectable en jeringa prellenada | U55: 3 | V55: ml | W55: 1 | X55: Diclofenaco / Vitaminas B1, B6 y B12 | Z55: Inyectable | AG55: Formato de venta: Unidad; Volumen por jeringa: 3 ml | AH55: https://raw.githubusercontent.com/zublimemx/marketplaces-product-images/main/products/7501298217635/images/7501298217635_1.jpg | AI55: https://raw.githubusercontent.com/zublimemx/marketplaces-product-images/main/products/7501298217635/images/7501298217635_2.jpg | AN55: Farma | AO55: DOLO NEUROBION FTE C 1 PRELLE | AP55: Verificado
A56: 7501943433090 | B56: 7501943433090 | C56: Pañales Huggies Ultra Confort Unisex Etapa 2 44 Piezas | D56: MLM178488 | E56: Bebés > Higiene y Cuidado del Bebé > Pañales > Desechables | F56: =Precios!R56 -> 359 | G56: 364 | H56: =Parámetros!$B$28 -> Nuevo | I56: =Parámetros!$B$29 -> Clásica | J56: Descripción: Pañales desechables Huggies Ultra Confort Unisex, Etapa 2, en paquete con 44 piezas. Están pensados para ofrecer comodidad, ajuste y protección al bebé, con un diseño anatómico que brinda mayor cobertura y flexibilidad, según el fabricante. Características: - Diseño anatómico con mayor cobertura y flexibilidad, adaptado al cuerpo del bebé. - Cintas Confort Flex V-Shape con cuatro puntos de sujeción para un ajuste seguro. - Cintura elástica más suave y flexible. - Núcleo absorbente reforzado y cubierta interna con poros ultra absorbentes. - Indicador de humedad. - Indicador de cambio de etapa. - Cuenta con certificación Dermatest®. Presentación: Paquete con 44 pañales desechables, Etapa 2 (talla Chico), versión unisex. Advertencias: - Consulte la guía de peso del empaque para elegir la etapa adecuada para su bebé. - Cambie el pañal con frecuencia y mantenga la piel del bebé limpia y seca. - Mantenga el producto fuera del alcance de los niños. Deseche el pañal usado en la basura, no en el drenaje. | K56: =Parámetros!$B$30 -> Mercado Envíos | L56: =IF(F56>=Parámetros!$B$7,"Envío gratis (obligatorio en Mercado Libre)",Parámetros!$B$31) -> Envío gratis (obligatorio en Mercado Libre) | M56: =Parámetros!$B$32 -> No acepto | N56: =Parámetros!$B$33 -> Sin garantía | O56: MLM17379867 | P56: Huggies | Q56: Kimberly-Clark | R56: Ultra Confort | S56: Unisex | T56: Pañales desechables | U56: 44 | V56: piezas | W56: 44 | AA56: Etapa 2 | AB56: Chico | AD56: Unisex | AG56: Tipo de pañal: Desechable; Certificación: Dermatest | AH56: https://raw.githubusercontent.com/zublimemx/marketplaces-product-images/main/products/7501943433090/images/7501943433090_1.jpg | AI56: https://raw.githubusercontent.com/zublimemx/marketplaces-product-images/main/products/7501943433090/images/7501943433090_2.jpg | AJ56: https://raw.githubusercontent.com/zublimemx/marketplaces-product-images/main/products/7501943433090/images/7501943433090_3.jpg | AN56: Mark | AO56: HU CONF UNI E2 C44 | AP56: Verificado
A57: 7501165005624 | B57: 7501165005624 | C57: Neuroflax Cobamamida Tiocolchicósido 20/4 mg 3 Ampolletas | D57: MLM457822 | E57: Salud y Equipamiento Médico > Cuidado de la Salud > Farmacia > Medicamentos de Venta Libre > Musculoarticulares Venta Libre | F57: =Precios!R57 -> 1502.28 | G57: 98 | H57: =Parámetros!$B$28 -> Nuevo | I57: =Parámetros!$B$29 -> Clásica | J57: Descripción: Neuroflax 20 mg/4 mg es un medicamento inyectable de laboratorios Sanfer que combina cobamamida, una forma activa de la vitamina B12, con tiocolchicósido, un relajante muscular. Se clasifica entre los medicamentos empleados en el manejo del dolor de tipo reumático, neurológico y traumatológico, y debe ser indicado por un médico. La caja incluye las ampolletas de solución inyectable junto con su diluyente. Composición: - Cobamamida 20 mg - Tiocolchicósido 4 mg Consulte el empaque para conocer el resto de los componentes de la fórmula y del diluyente. Modo de uso: Vía intramuscular. Prepare la solución con el diluyente que se incluye en la caja, conforme al instructivo. La preparación y la aplicación deben realizarlas personal de salud capacitado, con la dosis y la duración que indique el médico. Presentación: Caja con 3 ampolletas de solución inyectable con su diluyente. Advertencias: - No lo use si es alérgico a alguno de los componentes de la fórmula. - Informe a su médico si está embarazada, planea un embarazo o está en periodo de lactancia. - Informe a su médico si tiene epilepsia o antecedentes de convulsiones. - Su uso debe ser indicado y supervisado por un médico. Lea las instrucciones del empaque. Consulte a su médico. No se deje al alcance de los niños. | K57: =Parámetros!$B$30 -> Mercado Envíos | L57: =IF(F57>=Parámetros!$B$7,"Envío gratis (obligatorio en Mercado Libre)",Parámetros!$B$31) -> Envío gratis (obligatorio en Mercado Libre) | M57: =Parámetros!$B$32 -> No acepto | N57: =Parámetros!$B$33 -> Sin garantía | O57: MLM39475976 | P57: Neuroflax | Q57: Sanfer | S57: 20 mg/4 mg | T57: Solución inyectable en ampolletas con diluyente | U57: 3 | V57: ampolletas | W57: 3 | X57: Cobamamida / Tiocolchicósido | Y57: 20 mg/4 mg | Z57: Intramuscular | AG57: Incluye diluyente; Formato de venta: Unidad | AH57: https://raw.githubusercontent.com/zublimemx/marketplaces-product-images/main/products/7501165005624/images/7501165005624_1.jpg | AI57: https://raw.githubusercontent.com/zublimemx/marketplaces-product-images/main/products/7501165005624/images/7501165005624_2.jpg | AN57: Farma | AO57: NEUROFLAX 20 4MG C3 AMP SEPTIEMBRE 27 | AP57: Verificado
A58: 7501298217703 | B58: 7501298217703 | C58: Dexabión DC Solución Inyectable 3 Jeringas Prellenadas 3 ml | D58: MLM457822 | E58: Salud y Equipamiento Médico > Cuidado de la Salud > Farmacia > Medicamentos de Venta Libre > Musculoarticulares Venta Libre | F58: =Precios!R58 -> 598 | G58: 839 | H58: =Parámetros!$B$28 -> Nuevo | I58: =Parámetros!$B$29 -> Clásica | J58: Descripción: Dexabión DC es una solución inyectable de doble cámara en jeringa prellenada de 3 ml que combina dexametasona, un corticosteroide antiinflamatorio, lidocaína, un anestésico local, y vitaminas del complejo B (B1, B6 y B12). Está indicado en el manejo de neuralgias, neuritis, polineuritis, ciática, tendinitis, lumbalgias, mialgias, reumatismo articular, inflamación por traumatismos, síndromes cervical y escapulohumeral, y en el periodo pre y posoperatorio, siempre bajo prescripción médica. Composición: - Dexametasona - Lidocaína - Vitamina B1 (tiamina) - Vitamina B6 (piridoxina) - Vitamina B12 (cianocobalamina) Consulte el empaque para conocer la concentración de cada componente. Modo de uso: Vía intramuscular. Debe ser aplicado por personal de salud capacitado, conforme a la dosis y a la duración que indique el médico. No reutilice la jeringa. Presentación: Caja con 3 jeringas prellenadas de doble cámara, de 3 ml cada una. Advertencias: - No lo use si es alérgico a la dexametasona, a la lidocaína o a alguno de los componentes de la fórmula. - Informe a su médico si tiene diabetes, hipertensión, infecciones, úlcera del estómago o si está embarazada o en periodo de lactancia. - Su uso debe ser indicado y supervisado por un médico. Lea las instrucciones del empaque. Consulte a su médico. No se deje al alcance de los niños. | K58: =Parámetros!$B$30 -> Mercado Envíos | L58: =IF(F58>=Parámetros!$B$7,"Envío gratis (obligatorio en Mercado Libre)",Parámetros!$B$31) -> Envío gratis (obligatorio en Mercado Libre) | M58: =Parámetros!$B$32 -> No acepto | N58: =Parámetros!$B$33 -> Sin garantía | O58: MLM39474643 | P58: Dexabión | S58: DC (doble cámara) | T58: Solución inyectable en jeringa prellenada | U58: 3 | V58: jeringas | W58: 3 | X58: Dexametasona / Lidocaína / Vitaminas B1, B6 y B12 | Z58: Intramuscular | AF58: 89399SSAIV | AG58: Volumen por jeringa: 3 ml; Formato de venta: Unidad | AH58: https://raw.githubusercontent.com/zublimemx/marketplaces-product-images/main/products/7501298217703/images/7501298217703_1.jpg | AI58: https://raw.githubusercontent.com/zublimemx/marketplaces-product-images/main/products/7501298217703/images/7501298217703_3.jpg | AN58: Farma | AO58: DEXABION DC INY 3 X 3 ML | AP58: Verificado
A59: 7506425604289 | B59: 7506425604289 | C59: Pañales Huggies Ultra Confort Niño Etapa 4 40 Piezas | D59: MLM178488 | E59: Bebés > Higiene y Cuidado del Bebé > Pañales > Desechables | F59: =Precios!R59 -> 457 | G59: 142 | H59: =Parámetros!$B$28 -> Nuevo | I59: =Parámetros!$B$29 -> Clásica | J59: Descripción: Pañales desechables Huggies Ultra Confort para niño, Etapa 4, en paquete con 40 piezas. Están pensados para ofrecer comodidad, ajuste y protección al bebé, con un diseño anatómico que brinda mayor cobertura y flexibilidad, según el fabricante. Características: - Diseño anatómico con mayor cobertura y flexibilidad, adaptado al cuerpo del bebé. - Cintas Confort Flex V-Shape con cuatro puntos de sujeción para un ajuste seguro. - Cintura elástica más suave y flexible. - Núcleo absorbente reforzado al frente en la versión para niño. - Cubierta interna con poros ultra absorbentes e indicador de humedad. - Indicador de cambio de etapa. - Cuenta con certificación Dermatest®. Presentación: Paquete con 40 pañales desechables, Etapa 4 (talla Grande), versión para niño. Advertencias: - Consulte la guía de peso del empaque para elegir la etapa adecuada para su bebé. - Cambie el pañal con frecuencia y mantenga la piel del bebé limpia y seca. - Mantenga el producto fuera del alcance de los niños. Deseche el pañal usado en la basura, no en el drenaje. | K59: =Parámetros!$B$30 -> Mercado Envíos | L59: =IF(F59>=Parámetros!$B$7,"Envío gratis (obligatorio en Mercado Libre)",Parámetros!$B$31) -> Envío gratis (obligatorio en Mercado Libre) | M59: =Parámetros!$B$32 -> No acepto | N59: =Parámetros!$B$33 -> Sin garantía | O59: MLM17379872 | P59: Huggies | Q59: Kimberly-Clark | R59: Ultra Confort | S59: Niño | T59: Pañales desechables | U59: 40 | V59: piezas | W59: 40 | AA59: Etapa 4 | AB59: Grande | AD59: Niños | AG59: Tipo de pañal: Desechable; Certificación: Dermatest; Peso del bebé: 9 a 12 kg; Con gel superabsorbente: Sí; Con barreras reforzadas anti-derrames: Sí; Libre de látex: Sí | AH59: https://raw.githubusercontent.com/zublimemx/marketplaces-product-images/main/products/7506425604289/images/7506425604289_1.jpg | AI59: https://raw.githubusercontent.com/zublimemx/marketplaces-product-images/main/products/7506425604289/images/7506425604289_2.jpg | AN59: Mark | AO59: HU CONF NINO E4 C40 | AP59: Verificado
A60: 7501070612368 | B60: 7501070612368 | C60: Treda Neomicina Caolín Pectina 20 Tabletas | D60: MLM457821 | E60: Salud y Equipamiento Médico > Cuidado de la Salud > Farmacia > Medicamentos de Venta Libre > Digestivos Venta Libre | F60: =Precios!R60 -> 205 | G60: 2652 | H60: =Parámetros!$B$28 -> Nuevo | I60: =Parámetros!$B$29 -> Clásica | J60: Descripción: Treda, de Laboratorios Sanfer, es un medicamento antidiarreico en tabletas que combina neomicina, caolín y pectina. Está pensado para eliminar la diarrea infecciosa y no infecciosa. Se presenta en caja con 20 tabletas para administración por vía oral. Beneficios: - Antidiarreico, protector intestinal y astringente. - Ayuda a aumentar la consistencia de las heces y a reducir el número de evacuaciones. - Contribuye a eliminar toxinas irritantes causantes de la diarrea. - Combina un antibiótico local (neomicina) con dos agentes que protegen la mucosa intestinal (caolín y pectina). Composición: Cada tableta contiene neomicina 129 mg, caolín 280 mg y pectina 30 mg. Modo de uso: Vía oral. La dosis y la duración del tratamiento son las indicadas por su médico o en el instructivo del empaque. No exceda la dosis recomendada ni prolongue el tratamiento sin indicación médica. Mantenga una buena hidratación mientras dure la diarrea. Presentación: Caja con 20 tabletas. Advertencias: No lo use si es alérgico a la neomicina o a otros antibióticos aminoglucósidos. Si la diarrea dura más de dos días, hay fiebre alta, sangre en las heces o signos de deshidratación, suspenda su uso y acuda con su médico. Precaución en personas con enfermedad del riñón. No se use en el embarazo ni la lactancia sin indicación médica. Lea las instrucciones del empaque. Consulte a su médico. No se deje al alcance de los niños. | K60: =Parámetros!$B$30 -> Mercado Envíos | L60: =IF(F60>=Parámetros!$B$7,"Envío gratis (obligatorio en Mercado Libre)",Parámetros!$B$31) -> A cargo del comprador | M60: =Parámetros!$B$32 -> No acepto | N60: =Parámetros!$B$33 -> Sin garantía | O60: MLM40172770 | P60: Treda | Q60: Sanfer | T60: Tabletas | U60: 20 | V60: tabletas | W60: 20 | X60: Neomicina, caolín y pectina | Y60: Neomicina 129 mg; caolín 280 mg; pectina 30 mg por tableta | Z60: Oral | AG60: Antidiarreico; Formato de venta: Caja | AH60: https://raw.githubusercontent.com/zublimemx/marketplaces-product-images/main/products/7501070612368/images/7501070612368_1.jpg | AI60: https://raw.githubusercontent.com/zublimemx/marketplaces-product-images/main/products/7501070612368/images/7501070612368_2.jpg | AJ60: https://raw.githubusercontent.com/zublimemx/marketplaces-product-images/main/products/7501070612368/images/7501070612368_3.jpg | AN60: Farma | AO60: TREDA C20 TABS | AP60: Verificado
A61: 7506425662920 | B61: 7506425662920 | C61: Pañales Huggies UltraConfort Niño Etapa 7 40 Piezas | D61: MLM178488 | E61: Bebés > Higiene y Cuidado del Bebé > Pañales > Desechables | F61: =Precios!R61 -> 852.65 | G61: 141 | H61: =Parámetros!$B$28 -> Nuevo | I61: =Parámetros!$B$29 -> Clásica | J61: Descripción: Los pañales Huggies UltraConfort Etapa 7 para niños están pensados para bebés que ya se mueven mucho y necesitan comodidad para gatear, caminar y explorar. Son ultradelgados y ultraflexibles, con cintas estirables que se ajustan a cada movimiento y absorbencia focalizada al frente. Se venden en paquete con 40 piezas. Características: - Etapa 7, ideal para bebés de 16 kg. - Ultradelgados y ultraflexibles para dar mayor libertad de movimiento. - Cintas estirables que dan un mejor ajuste en cada movimiento. - Absorbencia focalizada al frente. - Centro texturizado que ayuda a distribuir los líquidos. - Cintura elástica y ajuste anatómico. - Sistema de absorción que ofrece hasta 12 horas de protección contra derrames y ayuda a mantener la piel seca. Modo de uso: Abra el pañal y colóquelo debajo del bebé con las cintas hacia atrás. Lleve la parte delantera entre las piernas, sujete las cintas a los lados y ajuste sin apretar. Cámbielo cuando esté húmedo o sucio, y limpie la piel del bebé en cada cambio. Presentación: Paquete con 40 pañales desechables, Etapa 7, para niños. Advertencias: Producto de un solo uso. Deséchelo en la basura, no en el inodoro. Mantenga las bolsas de plástico fuera del alcance de los niños para evitar riesgo de asfixia. Si aparece irritación en la piel del bebé, suspenda su uso y consulte a su pediatra. | K61: =Parámetros!$B$30 -> Mercado Envíos | L61: =IF(F61>=Parámetros!$B$7,"Envío gratis (obligatorio en Mercado Libre)",Parámetros!$B$31) -> Envío gratis (obligatorio en Mercado Libre) | M61: =Parámetros!$B$32 -> No acepto | N61: =Parámetros!$B$33 -> Sin garantía | O61: MLM48937609 | P61: Huggies | Q61: Kimberly-Clark | R61: UltraConfort | S61: Niño | T61: Pañales desechables | U61: 40 | V61: piezas | W61: 40 | AA61: Etapa 7 | AB61: Etapa 7 | AD61: Niño | AG61: Peso ideal: 16 kg; Cintas estirables; Absorbencia focalizada al frente; Formato de venta: Paquete | AH61: https://raw.githubusercontent.com/zublimemx/marketplaces-product-images/main/products/7506425662920/images/7506425662920_3.jpg | AI61: https://raw.githubusercontent.com/zublimemx/marketplaces-product-images/main/products/7506425662920/images/7506425662920_4.jpg | AN61: Mark | AO61: HUGG ULT CON ET 7 NIÑO C40 5 | AP61: Verificado
A62: 7501868900134 | B62: 7501868900134 | C62: Gasa Simple Estéril Dibar 10 x 10 cm 100 Piezas | D62: MLM191087 | E62: Salud y Equipamiento Médico > Cuidado de la Salud > Farmacia > Gasas | F62: =Precios!R62 -> 189 | G62: 341 | H62: =Parámetros!$B$28 -> Nuevo | I62: =Parámetros!$B$29 -> Clásica | J62: Descripción: La gasa simple Dibar es un material de curación de algodón, esterilizado con óxido de etileno, que sirve para limpiar, proteger y cubrir heridas, absorber fluidos y apoyar procedimientos de curación. Cada caja contiene 100 piezas de 10 x 10 cm (doblada), envueltas en sobres individuales. Características: - Esterilizada con óxido de etileno. - Cada pieza viene en su propio sobre, lo que ayuda a mantenerla limpia hasta el momento de usarla. - Tejido 20 x 12 de 8 capas, con buena capacidad de absorción y suavidad. - Medidas: 10 cm x 10 cm doblada y 20 cm x 40 cm extendida. - Útil para curaciones, limpieza de heridas, cuidados posteriores a una cirugía y aplicación de medicamentos tópicos. Modo de uso: Lávese las manos antes de manipular la gasa. Abra el sobre sin tocar la gasa con los dedos, colóquela sobre la zona a limpiar o cubrir y fíjela con cinta si es necesario. Use una gasa nueva en cada curación. Presentación: Caja con 100 piezas de gasa simple estéril, cada una en sobre individual. Advertencias: Producto de un solo uso. No la use si el sobre está abierto, roto o dañado. No la reutilice ni la vuelva a esterilizar. Manténgala en un lugar limpio y seco, fuera del alcance de los niños. Ante heridas profundas, con signos de infección o que no cicatrizan, consulte a su médico. | K62: =Parámetros!$B$30 -> Mercado Envíos | L62: =IF(F62>=Parámetros!$B$7,"Envío gratis (obligatorio en Mercado Libre)",Parámetros!$B$31) -> A cargo del comprador | M62: =Parámetros!$B$32 -> No acepto | N62: =Parámetros!$B$33 -> Sin garantía | O62: MLM19639133 | P62: Dibar | T62: Gasa simple estéril en sobres individuales | U62: 100 | V62: piezas | W62: 100 | AG62: Medidas: 10 x 10 cm doblada, 20 x 40 cm extendida; Tejido 20 x 12 de 8 capas; Esterilizada con óxido de etileno; Cada pieza en sobre individual; Formato de venta: Caja | AH62: https://raw.githubusercontent.com/zublimemx/marketplaces-product-images/main/products/7501868900134/images/7501868900134_1.jpg | AI62: https://raw.githubusercontent.com/zublimemx/marketplaces-product-images/main/products/7501868900134/images/7501868900134_3.jpg | AJ62: https://raw.githubusercontent.com/zublimemx/marketplaces-product-images/main/products/7501868900134/images/7501868900134_4.jpg | AN62: Farma | AO62: DIBAR GASA 100 | AP62: Verificado
A63: 736085905373 | B63: 736085905373 | C63: Krytantek Ofteno Dorzolamida Timolol Brimonidina 5 ml | D63: MLM457824 | E63: Salud y Equipamiento Médico > Cuidado de la Salud > Farmacia > Medicamentos de Venta Libre > Para Ojos y Oídos Venta Libre | F63: =Precios!R63 -> 1189 | G63: 403 | H63: =Parámetros!$B$28 -> Nuevo | I63: =Parámetros!$B$29 -> Clásica | J63: Descripción: Krytantek Ofteno, de Laboratorios Sophia, es una solución oftálmica que combina tres principios activos para reducir la presión intraocular: dorzolamida, timolol y brimonidina. Se presenta en caja con un frasco gotero de 5 ml y es de uso exclusivo en el ojo. Su indicación principal es el tratamiento del glaucoma de ángulo abierto y de la hipertensión ocular crónica, en los casos en que la presión intraocular es difícil de controlar con una sola sustancia. Beneficios: - Reúne tres mecanismos de acción en un solo frasco: la dorzolamida (inhibidor de la anhidrasa carbónica) y el timolol (betabloqueador) disminuyen la producción de humor acuoso, y la brimonidina (agonista adrenérgico alfa-2) reduce esa producción y favorece su drenaje. - Indicado para el control de la presión intraocular cuando un solo medicamento no es suficiente, bajo supervisión del médico oftalmólogo. - Frasco gotero de 5 ml. Composición: Cada mL contiene: clorhidrato de dorzolamida equivalente a 20 mg de dorzolamida; maleato de timolol equivalente a 5 mg de timolol; tartrato de brimonidina 2 mg; vehículo cbp 1 mL. Modo de uso: Vía oftálmica. No ingerible. La dosis es la que señale el médico; lea el instructivo anexo. Evite tocar la punta del gotero con los dedos, los ojos u otras superficies para no contaminarlo y mantenga el frasco bien cerrado después de cada aplicación. Presentación: Caja con frasco gotero de 5 ml. Solución 20 mg/5 mg/2 mg por mL. Advertencias: Su venta requiere receta médica. No se use durante el embarazo ni la lactancia, ni en menores de 2 años. Conserve el frasco bien cerrado a no más de 30 °C; una vez abierto, el producto se conserva durante 30 días a no más de 30 °C. Este medicamento puede producir somnolencia, cansancio o visión borrosa, por lo que no debe conducir vehículos ni operar maquinaria pesada hasta que estos efectos hayan desaparecido. Lea las instrucciones del empaque. Consulte a su médico. No se deje al alcance de los niños. | K63: =Parámetros!$B$30 -> Mercado Envíos | L63: =IF(F63>=Parámetros!$B$7,"Envío gratis (obligatorio en Mercado Libre)",Parámetros!$B$31) -> Envío gratis (obligatorio en Mercado Libre) | M63: =Parámetros!$B$32 -> No acepto | N63: =Parámetros!$B$33 -> Sin garantía | O63: MLM47401608 | P63: Krytantek | Q63: Laboratorios Sophia | R63: Ofteno | T63: Solución oftálmica | U63: 5 | V63: ml | W63: 1 | X63: Dorzolamida, timolol y brimonidina | Y63: Dorzolamida 20 mg, timolol 5 mg y brimonidina 2 mg por mL | Z63: Oftálmica | AF63: 074M2007 SSA IV | AG63: Uso: glaucoma de ángulo abierto e hipertensión ocular; No usar en menores de 2 años; Conservación: no más de 30 °C y 30 días una vez abierto; Formato de venta: Caja con frasco gotero | AH63: https://raw.githubusercontent.com/zublimemx/marketplaces-product-images/main/products/736085905373/images/736085905373_1.jpg | AI63: https://raw.githubusercontent.com/zublimemx/marketplaces-product-images/main/products/736085905373/images/736085905373_2.jpg | AJ63: https://raw.githubusercontent.com/zublimemx/marketplaces-product-images/main/products/736085905373/images/736085905373_3.jpg | AK63: https://raw.githubusercontent.com/zublimemx/marketplaces-product-images/main/products/736085905373/images/736085905373_4.jpg | AN63: Farma | AO63: KRYTANTEK SOL 5ML | AP63: Verificado
A64: 7506425608867 | B64: 7506425608867 | C64: Toallitas Húmedas Huggies Supreme 2 Paquetes de 80 Piezas | D64: MLM187794 | E64: Bebés > Higiene y Cuidado del Bebé > Toallitas Húmedas | F64: =Precios!R64 -> 147 | G64: 1638 | H64: =Parámetros!$B$28 -> Nuevo | I64: =Parámetros!$B$29 -> Clásica | J64: Descripción: Las toallitas húmedas Huggies Supreme Protección Delicada están pensadas para la limpieza diaria de la piel del bebé en cada cambio de pañal. Tienen textura 3D algodonosa hecha con fibras naturales, son una toallita de tamaño más grande y están adicionadas con glicerina y aceite de almendras. Son clínica y dermatológicamente probadas, hipoalergénicas, libres de parabenos y sin alcohol. Se venden en presentación de 2 paquetes con 80 toallitas cada uno, 160 toallitas en total. Características: - Suavidad superior con textura 3D algodonosa. - Cuidado superior con aceite de almendras. - Tecnología superior de limpieza gracias a sus fibras naturales. - Toallita más grande. - Tapa con sistema Easy Push. - Hipoalergénicas, libres de parabenos y sin alcohol. - Clínica y dermatológicamente probadas. Composición: Toallitas de fibras naturales con glicerina y aceite de almendras. Consulte el listado completo de ingredientes en el empaque. Modo de uso: Abra la tapa, tome una toallita y limpie suavemente la piel del bebé en cada cambio de pañal. Cierre bien la tapa después de cada uso para que las toallitas conserven su humedad. Presentación: 2 paquetes con 80 toallitas húmedas cada uno (160 toallitas en total). Advertencias: Producto de un solo uso; no se deseche en el inodoro. Evite el contacto con los ojos. Mantenga los paquetes fuera del alcance de los niños. Si aparece irritación en la piel del bebé, suspenda su uso y consulte a su pediatra. | K64: =Parámetros!$B$30 -> Mercado Envíos | L64: =IF(F64>=Parámetros!$B$7,"Envío gratis (obligatorio en Mercado Libre)",Parámetros!$B$31) -> A cargo del comprador | M64: =Parámetros!$B$32 -> No acepto | N64: =Parámetros!$B$33 -> Sin garantía | O64: MLM22031540 | P64: Huggies | Q64: Kimberly-Clark | R64: Supreme | S64: Protección Delicada | T64: Toallitas húmedas | U64: 160 | V64: toallitas | W64: 2 | AG64: Contenido: 2 paquetes con 80 toallitas cada uno; Con aceite de almendras y glicerina; Hipoalergénicas; Libres de parabenos; Sin alcohol; Tapa Easy Push; Formato de venta: Pack de 2 paquetes | AH64: https://raw.githubusercontent.com/zublimemx/marketplaces-product-images/main/products/7506425608867/images/7506425608867_1.jpg | AI64: https://raw.githubusercontent.com/zublimemx/marketplaces-product-images/main/products/7506425608867/images/7506425608867_2.jpg | AJ64: https://raw.githubusercontent.com/zublimemx/marketplaces-product-images/main/products/7506425608867/images/7506425608867_3.jpg | AN64: Mark | AO64: TAS HUGGIES SUPREME 2PACK C/80 | AP64: Verificado
A65: 7501943441705 | B65: 7501943441705 | C65: Pañales Huggies Supreme Unisex Etapa 2 38 Piezas | D65: MLM178488 | E65: Bebés > Higiene y Cuidado del Bebé > Pañales > Desechables | F65: =Precios!R65 -> 290.6 | G65: 224 | H65: =Parámetros!$B$28 -> Nuevo | I65: =Parámetros!$B$29 -> Clásica | J65: Descripción: Pañales desechables Huggies Supreme Etapa 2, versión unisex, para bebés de 5 a 7.5 kg. Están elaborados con materiales Delicate Care y adicionados con ingredientes como aloe vera, manzanilla, vitamina E y avena, pensados para cuidar la piel delicada del bebé y ayudar a evitar irritaciones. Incorporan tecnología de comodidad en movimiento para que el pequeño juegue y se desplace sin sentirse limitado. Beneficios: - Gel superabsorbente y absorción focalizada que ayudan a retener la humedad y a prevenir fugas - Barreras reforzadas anti-derrames y una bolsa interna que contiene el líquido, mejora el ajuste y ayuda a evitar escurrimientos por la parte trasera - Cubierta ultrarespirable y canales de aire que ayudan a mantener la piel fresca - Cubierta suave, cintura elastizada y cintas elastizadas para un ajuste cómodo - Indicador de humedad que avisa cuándo es momento de cambiar el pañal - Protección de hasta 12 horas - Hipoalergénico, libre de parabenos y libre de látex, con fragancia Presentación: Paquete con 38 pañales desechables, talla P (Chico), unisex. Advertencias: - Consulte la guía de peso del empaque para elegir la etapa adecuada para su bebé. - Cambie el pañal con frecuencia y mantenga la piel del bebé limpia y seca. - Deseche el pañal usado en la basura, no en el drenaje. Mantenga el producto fuera del alcance de los niños. | K65: =Parámetros!$B$30 -> Mercado Envíos | L65: =IF(F65>=Parámetros!$B$7,"Envío gratis (obligatorio en Mercado Libre)",Parámetros!$B$31) -> A cargo del comprador | M65: =Parámetros!$B$32 -> No acepto | N65: =Parámetros!$B$33 -> Sin garantía | O65: MLM17379811 | P65: Huggies | Q65: Kimberly-Clark | R65: Supreme | S65: Unisex | T65: Pañales desechables | U65: 38 | V65: piezas | W65: 38 | AA65: Etapa 2 | AB65: Chico (P) | AD65: Unisex | AG65: Tipo de pañal: Desechable; Rango de peso: 5 a 7.5 kg; Con gel superabsorbente; Con indicador de humedad; Cintura y cintas elastizadas; Hipoalergénico; Libre de parabenos; Libre de látex; Protección de hasta 12 horas | AH65: https://raw.githubusercontent.com/zublimemx/marketplaces-product-images/main/products/7501943441705/images/7501943441705_1.jpg | AN65: Mark | AO65: HU SUP UNISEX E2 C38 C/6 | AP65: Verificado
A66: 7501314701827 | B66: 7501314701827 | C66: Ciproflox Ciprofloxacino 500 mg 12 Cápsulas | D66: MLM457823 | E66: Salud y Equipamiento Médico > Cuidado de la Salud > Farmacia > Medicamentos de Venta Libre > Antiinfecciosos Venta Libre | F66: =Precios!R66 -> 707.3 | G66: 356 | H66: =Parámetros!$B$28 -> Nuevo | I66: =Parámetros!$B$29 -> Clásica | J66: Descripción: Ciproflox, de la línea Altia de Laboratorios Senosiain, es un antibiótico de amplio espectro del grupo de las fluoroquinolonas cuyo principio activo es el ciprofloxacino. Cada cápsula contiene 500 mg y se toma por vía oral. Actúa inhibiendo la ADN girasa bacteriana, por lo que tiene acción bactericida. Solo es útil contra infecciones bacterianas; no actúa contra infecciones virales como el resfriado o la gripe. Beneficios: Antibiótico indicado, siempre con supervisión médica, en infecciones causadas por bacterias sensibles al ciprofloxacino, como: - Infecciones de las vías urinarias y genitourinarias (cistitis, pielonefritis). - Infecciones respiratorias (bronquitis, neumonía). - Infecciones gastrointestinales, como enteritis o diarrea infecciosa. - Infecciones de la piel, los tejidos blandos, los huesos y las articulaciones. Composición: Cada cápsula contiene: clorhidrato de ciprofloxacino monohidratado equivalente a 500 mg de ciprofloxacino; excipiente cbp 1 cápsula. Modo de uso: Vía oral. La dosis, la frecuencia y la duración del tratamiento las determina el médico. Tome las cápsulas con un vaso de agua y complete el tratamiento aunque los síntomas mejoren. Evite tomarlas junto con antiácidos o suplementos de calcio, hierro o zinc, porque pueden disminuir su absorción. Presentación: Caja con 12 cápsulas de 500 mg. Advertencias: Antibiótico de venta con receta médica. No lo use si es alérgico al ciprofloxacino o a otras quinolonas. No se recomienda durante el embarazo ni la lactancia, ni en niños y adolescentes, salvo indicación médica. Las fluoroquinolonas pueden causar dolor o inflamación en los tendones, mareo y mayor sensibilidad de la piel al sol; suspenda el medicamento y consulte a su médico si presenta dolor en tendones o articulaciones, hormigueo o entumecimiento. El uso de antibióticos sin indicación médica favorece la resistencia bacteriana. Lea las instrucciones del empaque. Consulte a su médico. No se deje al alcance de los niños. | K66: =Parámetros!$B$30 -> Mercado Envíos | L66: =IF(F66>=Parámetros!$B$7,"Envío gratis (obligatorio en Mercado Libre)",Parámetros!$B$31) -> Envío gratis (obligatorio en Mercado Libre) | M66: =Parámetros!$B$32 -> No acepto | N66: =Parámetros!$B$33 -> Sin garantía | O66: MLM39474259 | P66: Ciproflox | Q66: Laboratorios Senosiain | R66: Altia | T66: Cápsulas | U66: 12 | V66: cápsulas | W66: 12 | X66: Ciprofloxacino | Y66: 500 mg por cápsula | Z66: Oral | AG66: Grupo: antibiótico fluoroquinolona; Formato de venta: Caja | AH66: https://raw.githubusercontent.com/zublimemx/marketplaces-product-images/main/products/7501314701827/images/7501314701827_2.jpg | AI66: https://raw.githubusercontent.com/zublimemx/marketplaces-product-images/main/products/7501314701827/images/7501314701827_1.jpg | AN66: Farma | AO66: CIPROFLOX 500MG C12 CAPS | AP66: Verificado
A67: 7501165000230 | B67: 7501165000230 | C67: Neo-Melubrina Metamizol Sódico 500 mg 10 Tabletas | D67: MLM194673 | E67: Salud y Equipamiento Médico > Cuidado de la Salud > Farmacia > Medicamentos de Venta Libre > Analgésicos | F67: =Precios!R67 -> 116 | G67: 4287 | H67: =Parámetros!$B$28 -> Nuevo | I67: =Parámetros!$B$29 -> Clásica | J67: Descripción: Neo-Melubrina, de Sanofi, es un analgésico y antipirético cuyo principio activo es el metamizol sódico. Cada tableta contiene 500 mg y se toma por vía oral. Está indicado como auxiliar en el tratamiento del dolor intenso, como el dolor de cabeza y la migraña, y de la fiebre. Se presenta en caja con 10 tabletas y se recomienda para adultos y personas mayores de 15 años. Beneficios: - Auxiliar en el alivio del dolor de cabeza, la migraña y otros dolores intensos. - Auxiliar en el manejo de la fiebre. - Presentación de 10 tabletas de 500 mg. Composición: Cada tableta contiene: metamizol sódico monohidratado 500 mg; excipiente cbp 1 tableta. Modo de uso: Vía oral. La dosis es la que el médico señale. Tome la tableta con un poco de agua; no exceda la dosis indicada ni prolongue el tratamiento sin indicación médica. Presentación: Caja con 10 tabletas de 500 mg. Advertencias: Su venta requiere receta médica. No lo use si es alérgico al metamizol o a otras pirazolonas. No se use durante el embarazo ni la lactancia, ni por períodos prolongados. Consérvese a temperatura ambiente a no más de 30 °C, en lugar seco y protegido de la luz. Lea las instrucciones del empaque. Consulte a su médico. No se deje al alcance de los niños. | K67: =Parámetros!$B$30 -> Mercado Envíos | L67: =IF(F67>=Parámetros!$B$7,"Envío gratis (obligatorio en Mercado Libre)",Parámetros!$B$31) -> A cargo del comprador | M67: =Parámetros!$B$32 -> No acepto | N67: =Parámetros!$B$33 -> Sin garantía | O67: MLM39476184 | P67: Neo-Melubrina | Q67: Sanofi-Aventis de México | T67: Tabletas | U67: 10 | V67: tabletas | W67: 10 | X67: Metamizol sódico | Y67: 500 mg por tableta | Z67: Oral | AF67: 5909 SSA IV | AG67: Analgésico y antipirético; Uso recomendado en adultos y mayores de 15 años; Conservación: no más de 30 °C; Formato de venta: Caja | AH67: https://raw.githubusercontent.com/zublimemx/marketplaces-product-images/main/products/7501165000230/images/7501165000230_1.jpg | AI67: https://raw.githubusercontent.com/zublimemx/marketplaces-product-images/main/products/7501165000230/images/7501165000230_2.jpg | AJ67: https://raw.githubusercontent.com/zublimemx/marketplaces-product-images/main/products/7501165000230/images/7501165000230_3.jpg | AK67: https://raw.githubusercontent.com/zublimemx/marketplaces-product-images/main/products/7501165000230/images/7501165000230_4.jpg | AN67: Farma | AO67: NEO MELUBRINA TAB 500MG C10 330 | AP67: Verificado
A68: 7501298265100 | B68: 7501298265100 | C68: Neurobión Vitaminas B1 B6 B12 60 Tabletas Recubiertas | D68: MLM438195 | E68: Salud y Equipamiento Médico > Suplementos Alimenticios | F68: =Precios!R68 -> 658 | G68: 494 | H68: =Parámetros!$B$28 -> Nuevo | I68: =Parámetros!$B$29 -> Clásica | J68: Descripción: Neurobión es un complejo de vitaminas neurotropas del grupo B que combina tiamina (B1), piridoxina (B6) y cianocobalamina (B12) en tabletas recubiertas de administración oral. Favorece las funciones y el mantenimiento del sistema nervioso. Está indicado para el tratamiento de las neuritis y neuralgias (neuropatías) y para la prevención y el tratamiento de las deficiencias de las vitaminas B1, B6 y/o B12, incluidas las inducidas por diabetes mellitus o por consumo prolongado de alcohol. Esta presentación contiene 60 tabletas. Beneficios: - Reúne tres vitaminas del complejo B que participan en el funcionamiento de los nervios. - Actúa en los procesos de regeneración de la fibra nerviosa. - Promueve el metabolismo de las proteínas y las grasas, y es fundamental para la transformación de azúcares. - Favorece el aprovechamiento y la absorción de varios nutrientes. - Indicado en neuralgia del trigémino e intercostal, isquialgia, síndrome lumbar y cervical, síndrome del hombro doloroso, neuritis radicular por enfermedades degenerativas de la columna vertebral y paresia facial. Composición: Cada tableta contiene: mononitrato de tiamina (vitamina B1) 100 mg; clorhidrato de piridoxina (vitamina B6) 5 mg; cianocobalamina (vitamina B12) 50 mcg; excipiente cbp una tableta. Contiene lactosa. Modo de uso: Vía oral. Una tableta con cada alimento, 3 veces al día, o como indique su médico. Presentación: Caja con 60 tabletas recubiertas. Advertencias: No lo use si es hipersensible a alguno de los componentes de la fórmula ni si padece policitemia vera o enfermedad de Leber. En caso de embarazo o lactancia, consulte a su médico. La administración de dosis grandes de piridoxina se ha relacionado con síndromes neuropáticos que revierten al suspender el tratamiento. Contiene lactosa: precaución en personas intolerantes. No se use en niños menores de 12 años. Lea las instrucciones del empaque. Consulte a su médico. No se deje al alcance de los niños. | K68: =Parámetros!$B$30 -> Mercado Envíos | L68: =IF(F68>=Parámetros!$B$7,"Envío gratis (obligatorio en Mercado Libre)",Parámetros!$B$31) -> Envío gratis (obligatorio en Mercado Libre) | M68: =Parámetros!$B$32 -> No acepto | N68: =Parámetros!$B$33 -> Sin garantía | O68: MLM45287653 | P68: Neurobión | Q68: Merck (P&G Health) | T68: Tabletas recubiertas | U68: 60 | V68: tabletas | W68: 60 | X68: Tiamina (B1), piridoxina (B6) y cianocobalamina (B12) | Y68: Tiamina 100 mg; piridoxina 5 mg; cianocobalamina 50 mcg por tableta | Z68: Oral | AF68: 0132M79 SSA | AG68: Vitaminas del complejo B; Contiene lactosa; No usar en menores de 12 años; Formato de venta: Caja | AH68: https://raw.githubusercontent.com/zublimemx/marketplaces-product-images/main/products/7501298265100/images/7501298265100_1.jpg | AI68: https://raw.githubusercontent.com/zublimemx/marketplaces-product-images/main/products/7501298265100/images/7501298265100_2.jpg | AN68: Farma | AO68: NEUROBION 60GRAG | AP68: Verificado
A69: 7501943488922 | B69: 7501943488922 | C69: Pañales KleenBebé Absorsec Etapa 6 Extra Jumbo 40 Piezas | D69: MLM178488 | E69: Bebés > Higiene y Cuidado del Bebé > Pañales > Desechables | F69: =Precios!R69 -> 284 | G69: 247 | H69: =Parámetros!$B$28 -> Nuevo | I69: =Parámetros!$B$29 -> Clásica | J69: Descripción: Los pañales desechables KleenBebé Absorsec Etapa 6, talla Extra Jumbo (XJ), son unisex y están pensados para bebés en etapa de crecimiento que necesitan absorción y comodidad durante el día y la noche. Cuentan con núcleo absorbente con sistema BlockGel, que ayuda a retener los líquidos para mantener la piel del bebé seca. Se venden en bolsa con 40 piezas. Características: - Etapa 6, talla Extra Jumbo (XJ), unisex. - Núcleo absorbente con sistema BlockGel para una mejor absorción. - Cubierta respirable y elástico en la cintura para un ajuste cómodo. - Presentación de 40 pañales por bolsa. Modo de uso: Abra el pañal y colóquelo debajo del bebé con las cintas hacia atrás. Lleve la parte delantera entre las piernas, sujete las cintas a los lados y ajuste sin apretar. Cámbielo cuando esté húmedo o sucio y limpie la piel del bebé en cada cambio. Presentación: Bolsa con 40 pañales desechables, Etapa 6, talla Extra Jumbo, unisex. Advertencias: Producto de un solo uso. Deséchelo en la basura, no en el inodoro. Mantenga las bolsas de plástico fuera del alcance de los niños para evitar riesgo de asfixia. Si aparece irritación en la piel del bebé, suspenda su uso y consulte a su pediatra. | K69: =Parámetros!$B$30 -> Mercado Envíos | L69: =IF(F69>=Parámetros!$B$7,"Envío gratis (obligatorio en Mercado Libre)",Parámetros!$B$31) -> A cargo del comprador | M69: =Parámetros!$B$32 -> No acepto | N69: =Parámetros!$B$33 -> Sin garantía | O69: MLM19532240 | P69: KleenBebé | Q69: Kimberly-Clark | R69: Absorsec | S69: Etapa 6 Extra Jumbo | T69: Pañales desechables | U69: 40 | V69: piezas | W69: 40 | AA69: Etapa 6 | AB69: Extra Jumbo (XJ) | AD69: Unisex | AG69: Núcleo absorbente con sistema BlockGel; Formato de venta: Bolsa | AH69: https://raw.githubusercontent.com/zublimemx/marketplaces-product-images/main/products/7501943488922/images/7501943488922_1.jpg | AI69: https://raw.githubusercontent.com/zublimemx/marketplaces-product-images/main/products/7501943488922/images/7501943488922_3.jpg | AJ69: https://raw.githubusercontent.com/zublimemx/marketplaces-product-images/main/products/7501943488922/images/7501943488922_4.jpg | AN69: Mark | AO69: ABSOR EX JUMC/40 | AP69: Verificado
A70: 7501300407047 | B70: 7501300407047 | C70: Febrax Naproxeno 275 mg Paracetamol 300 mg 15 Tabletas | D70: MLM194673 | E70: Salud y Equipamiento Médico > Cuidado de la Salud > Farmacia > Medicamentos de Venta Libre > Analgésicos | F70: =Precios!R70 -> 259 | G70: 270 | H70: =Parámetros!$B$28 -> Nuevo | I70: =Parámetros!$B$29 -> Clásica | J70: Descripción: Febrax, de Siegfried Rhein, es un medicamento en tabletas que combina naproxeno sódico (275 mg), un antiinflamatorio no esteroideo, con paracetamol (300 mg), un analgésico y antipirético. Está indicado como auxiliar en el alivio del dolor y de la fiebre, como el dolor de cabeza, los dolores musculares, el dolor de espalda, el dolor de muelas, las molestias del periodo menstrual y el malestar del resfriado común. Se presenta en caja con 15 tabletas para administración por vía oral. Beneficios: - Doble acción: el naproxeno sódico actúa sobre el dolor y la inflamación, y el paracetamol sobre el dolor y la fiebre. - Auxiliar en dolor de cabeza, dolores musculares, inflamación, dolor de espalda y dolor de muelas. - Auxiliar en el malestar por resfriado común y en las molestias del periodo menstrual. Composición: Cada tableta contiene: naproxeno sódico 275 mg y paracetamol 300 mg. Modo de uso: Vía oral. Tome las tabletas con agua, de preferencia con alimentos para reducir las molestias gástricas. La dosis y la duración del tratamiento son las que indique su médico o el instructivo del empaque; no exceda la dosis recomendada ni lo combine con otros medicamentos que contengan paracetamol o antiinflamatorios. Presentación: Caja con 15 tabletas de 275 mg/300 mg. Advertencias: No lo use si es alérgico al naproxeno, al paracetamol, a la aspirina o a otros antiinflamatorios no esteroideos, ni si tiene úlcera o sangrado del estómago o del intestino. Puede causar molestias gástricas, mareo o somnolencia. Precaución en personas con enfermedad del hígado, del riñón o del corazón, o con hipertensión; evite el consumo de alcohol durante el tratamiento. No se use durante el embarazo ni la lactancia salvo indicación médica. Consérvese a no más de 30 °C y bien cerrado. Lea las instrucciones del empaque. Consulte a su médico. No se deje al alcance de los niños. | K70: =Parámetros!$B$30 -> Mercado Envíos | L70: =IF(F70>=Parámetros!$B$7,"Envío gratis (obligatorio en Mercado Libre)",Parámetros!$B$31) -> A cargo del comprador | M70: =Parámetros!$B$32 -> No acepto | N70: =Parámetros!$B$33 -> Sin garantía | O70: MLM39455774 | P70: Febrax | Q70: Siegfried Rhein | T70: Tabletas | U70: 15 | V70: tabletas | W70: 15 | X70: Naproxeno sódico y paracetamol | Y70: Naproxeno sódico 275 mg; paracetamol 300 mg por tableta | Z70: Oral | AF70: 178M2014 SSA V | AG70: Analgésico, antipirético y antiinflamatorio; Conservación: no más de 30 °C; Formato de venta: Caja | AH70: https://raw.githubusercontent.com/zublimemx/marketplaces-product-images/main/products/7501300407047/images/7501300407047_1.jpg | AI70: https://raw.githubusercontent.com/zublimemx/marketplaces-product-images/main/products/7501300407047/images/7501300407047_2.jpg | AN70: Farma | AO70: FEBRAX C15 TABS 275 300MG 252 | AP70: Verificado
A71: 7501871721214 | B71: 7501871721214 | C71: Novovartalon Glucosamina 1500 mg Meloxicam 15 mg 30 Sobres | D71: MLM457822 | E71: Salud y Equipamiento Médico > Cuidado de la Salud > Farmacia > Medicamentos de Venta Libre > Musculoarticulares Venta Libre | F71: =Precios!R71 -> 1340 | G71: 0 | H71: =Parámetros!$B$28 -> Nuevo | I71: =Parámetros!$B$29 -> Clásica | J71: Descripción: Novovartalon, de Asofarma, es un medicamento en polvo para disolver en agua que combina sulfato de glucosamina (1500 mg) con meloxicam (15 mg), un antiinflamatorio no esteroideo con acción analgésica. Está indicado como auxiliar en el tratamiento de las enfermedades osteoarticulares, en la inflamación y el dolor de la osteoartrosis y de la periartritis de hombro, cadera y rodilla, previniendo la evolución del daño articular. Se presenta en caja con 30 sobres con polvo para administración oral. Beneficios: - Combina glucosamina, usada en el cuidado de las articulaciones, con meloxicam, que reduce la inflamación y el dolor. - Indicado en osteoartrosis y en periartritis de hombro, cadera y rodilla. - Un solo sobre al día; la caja de 30 sobres cubre 30 días de tratamiento. Composición: Cada sobre contiene: sulfato de glucosamina cloruro de sodio 1884 mg, equivalente a 1500 mg de sulfato de glucosamina; meloxicam 15 mg; excipiente cbp 1 sobre. Modo de uso: Vía oral. La dosis es de un sobre por día. Disuelva el contenido del sobre en un vaso con 250 ml de agua hervida fría o purificada y tómelo; el horario queda a elección, aunque se recomienda preferentemente por la mañana. La duración del tratamiento es la que indique su médico. Presentación: Caja con 30 sobres con polvo. Advertencias: Su venta requiere receta médica. No lo use si es alérgico a la glucosamina o al meloxicam, ni si tiene fenilcetonuria, úlcera gástrica o duodenal activa, insuficiencia renal o hepática severa, o antecedentes de asma, urticaria o rinitis provocados por aspirina u otros antiinflamatorios no esteroideos. No se use durante el embarazo. Consérvese a no más de 25 °C y con la caja bien cerrada. Lea las instrucciones del empaque. Consulte a su médico. No se deje al alcance de los niños. | K71: =Parámetros!$B$30 -> Mercado Envíos | L71: =IF(F71>=Parámetros!$B$7,"Envío gratis (obligatorio en Mercado Libre)",Parámetros!$B$31) -> Envío gratis (obligatorio en Mercado Libre) | M71: =Parámetros!$B$32 -> No acepto | N71: =Parámetros!$B$33 -> Sin garantía | O71: MLM66585560 | P71: Novovartalon | Q71: Asofarma de México | T71: Polvo en sobres | U71: 30 | V71: sobres | W71: 30 | X71: Sulfato de glucosamina y meloxicam | Y71: Sulfato de glucosamina 1500 mg; meloxicam 15 mg por sobre | Z71: Oral | AG71: Dosis: un sobre al día disuelto en 250 ml de agua; Conservación: no más de 25 °C; Formato de venta: Caja | AH71: https://raw.githubusercontent.com/zublimemx/marketplaces-product-images/main/products/7501871721214/images/7501871721214_1.jpg | AI71: https://raw.githubusercontent.com/zublimemx/marketplaces-product-images/main/products/7501871721214/images/7501871721214_3.jpg | AJ71: https://raw.githubusercontent.com/zublimemx/marketplaces-product-images/main/products/7501871721214/images/7501871721214_2.jpg | AN71: Farma | AO71: NOVOVARTALON C 30 SOBRES | AP71: Verificado
A72: 7501298221397 | B72: 7501298221397 | C72: Neurobión Vitaminas B1 B6 B12 30 Tabletas Recubiertas | D72: MLM438195 | E72: Salud y Equipamiento Médico > Suplementos Alimenticios | F72: =Precios!R72 -> 410 | G72: 830 | H72: =Parámetros!$B$28 -> Nuevo | I72: =Parámetros!$B$29 -> Clásica | J72: Descripción: Neurobión es un complejo de vitaminas neurotropas del grupo B que combina tiamina (B1), piridoxina (B6) y cianocobalamina (B12) en tabletas recubiertas de administración oral. Favorece las funciones y el mantenimiento del sistema nervioso. Está indicado para el tratamiento de las neuritis y neuralgias (neuropatías) y para la prevención y el tratamiento de las deficiencias de las vitaminas B1, B6 y/o B12, incluidas las inducidas por diabetes mellitus o por consumo prolongado de alcohol. Esta presentación contiene 30 tabletas. Beneficios: - Reúne tres vitaminas del complejo B que participan en el funcionamiento de los nervios. - Actúa en los procesos de regeneración de la fibra nerviosa. - Promueve el metabolismo de las proteínas y las grasas, y es fundamental para la transformación de azúcares. - Favorece el aprovechamiento y la absorción de varios nutrientes. - Indicado en neuralgia del trigémino e intercostal, isquialgia, síndrome lumbar y cervical, síndrome del hombro doloroso, neuritis radicular por enfermedades degenerativas de la columna vertebral y paresia facial. Composición: Cada tableta contiene: mononitrato de tiamina (vitamina B1) 100 mg; clorhidrato de piridoxina (vitamina B6) 5 mg; cianocobalamina (vitamina B12) 50 mcg; excipiente cbp una tableta. Contiene lactosa. Modo de uso: Vía oral. Una tableta con cada alimento, 3 veces al día, o como indique su médico. Presentación: Caja con 30 tabletas recubiertas. Advertencias: No lo use si es hipersensible a alguno de los componentes de la fórmula ni si padece policitemia vera o enfermedad de Leber. En caso de embarazo o lactancia, consulte a su médico. La administración de dosis grandes de piridoxina se ha relacionado con síndromes neuropáticos que revierten al suspender el tratamiento. Contiene lactosa: precaución en personas intolerantes. No se use en niños menores de 12 años. Lea las instrucciones del empaque. Consulte a su médico. No se deje al alcance de los niños. | K72: =Parámetros!$B$30 -> Mercado Envíos | L72: =IF(F72>=Parámetros!$B$7,"Envío gratis (obligatorio en Mercado Libre)",Parámetros!$B$31) -> Envío gratis (obligatorio en Mercado Libre) | M72: =Parámetros!$B$32 -> No acepto | N72: =Parámetros!$B$33 -> Sin garantía | O72: MLM45287873 | P72: Neurobión | Q72: Merck (P&G Health) | T72: Tabletas recubiertas | U72: 30 | V72: tabletas | W72: 30 | X72: Tiamina (B1), piridoxina (B6) y cianocobalamina (B12) | Y72: Tiamina 100 mg; piridoxina 5 mg; cianocobalamina 50 mcg por tableta | Z72: Oral | AF72: 0132M79 SSA | AG72: Vitaminas del complejo B; Contiene lactosa; No usar en menores de 12 años; Formato de venta: Caja | AH72: https://raw.githubusercontent.com/zublimemx/marketplaces-product-images/main/products/7501298221397/images/7501298221397_1.jpg | AI72: https://raw.githubusercontent.com/zublimemx/marketplaces-product-images/main/products/7501298221397/images/7501298221397_2.jpg | AJ72: https://raw.githubusercontent.com/zublimemx/marketplaces-product-images/main/products/7501298221397/images/7501298221397_3.jpg | AN72: Farma | AO72: NEUROBION C30 TABS VIT B1-B6-B12 | AP72: Verificado
